Workbook

Sheet SOFP
I2: Speedy Pioneer LTD | S2: =I2 -> Speedy Pioneer LTD | AC2: =I2 -> Speedy Pioneer LTD | AM2: =S2 -> Speedy Pioneer LTD | AU2: =AM2 -> Speedy Pioneer LTD
C3: MARITIME SOLUTIONS TECHNOLOGY SERVICES (HK) LIMITED | D3: MV PIONEER LADY | I3: M.V. "PIONEER LADY"-Shipmanagement Cost | S3: M.V. "PIONEER LADY"-Owner Cost | AC3: M.V. "PIONEER LADY"-Take Over Cost | AM3: M.V. "PIONEER LADY"-DryDocking Cost | AU3: M.V. "PIONEER LADY"-BMA Flag Change Cost
C4: 海事方案技術服務（香港）有限公司 | I4: (Ship Management Period: 15th Jul-2026 to 31th Dec-2026) | S4: (Owner Cost Period: 15th Jul-2026 to 31th Dec-2026) | AC4: (Take Over Vessel into Management: 15th Jul-2026 to 31th Jul-2026) | AM4: (DD Period: xxxxxxxxxxxxxxxxxxxxx) | AU4: (BMA Flag Change Period: 15th Jul-2026 to 01st Aug-2026)
C6: ="STATENMENT OF FINANCIAL POSITION As at "&TEXT(J6,"dd-mmm-yyyy") -> STATENMENT OF FINANCIAL POSITION As at 14-Oct-2026 | I6: BALANCE SHEET AS AT | J6: =TODAY() -> 46309 | S6: BALANCE SHEET AS AT | T6: =TODAY() -> 46309 | AC6: BALANCE SHEET AS AT | AD6: =TODAY() -> 46309 | AM6: BALANCE SHEET AS AT | AN6: =J6 -> 46309 | AU6: BALANCE SHEET AS AT | AV6: =R6 -> 0
E7: 2026/08/01 to
E8: =TODAY() -> 46309 | N8: US$ | P8: Notes | X8: US$ | Z8: Notes | AH8: US$ | AJ8: Notes | AR8: US$ | AT8: Notes | AZ8: US$ | BB8: Notes
D9: Note | E9: USD$ | I9: CURRENT ASSETS | S9: CURRENT ASSETS | AC9: CURRENT ASSETS | AM9: CURRENT ASSETS | AU9: CURRENT ASSETS
C10: Current assets
C11: Amount due from a director | D11: 6 | E11: =N17+X17+AH17+AR17+AZ17 -> 371554.52 | I11: Accounts Receivable | N11: =L12+L13 -> 0 | P11: 1 | S11: Accounts Receivable | V11: =V12+V13 -> 16371.04 | X11: =V11+V14+V15 -> 16371.04 | Z11: 1 | AC11: Accounts Receivable | AF11: =AF12+AF13 -> 12228.09 | AH11: =AF11+AF14+AF15 -> 12228.09 | AJ11: 1 | AM11: Accounts Receivable | AQ11: =SUM(AQ12:AQ13) -> 0 | AR11: =AQ11+AQ14+AQ15 -> 0 | AT11: 1 | AU11: Accounts Receivable | AY11: =SUM(AY12:AY13) -> 24996.94 | AZ11: =AY11+AY14+AY15 -> 24996.94 | BB11: 1
I12: Balance due from MSTS (cash surplus) | S12: Balance due from OWNER (cash surplus) | V12: 0 | AC12: Balance due from Take-over (cash surplus) | AM12: Balance due from Drydocking (cash surplus) | AU12: Balance due from BMA (cash surplus)
E13: =SUM(E11:E12) -> 371554.52 | I13: Actual accounts receivable | L13: =SUM('Shipmanagement RCVD'!K13:K15) -> 0 | S13: Actual accounts receivable | V13: ='Shipmanagement RCVD'!L2 -> 16371.04 | AC13: Actual accounts receivable | AF13: ='Shipmanagement RCVD'!J2 -> 12228.09 | AM13: Actual accounts receivable | AU13: Actual accounts receivable | AY13: ='Shipmanagement RCVD'!K2 -> 24996.94
C14: Less: Current liabilities | I14: Prepayments | L14: ='Shipmanagement RCVD'!I2 -> 317958.45 | N14: =L14 -> 317958.45 | P14: 1 | S14: Prepayments | Z14: 1 | AC14: Prepayments | AJ14: 1 | AM14: Prepayments | AP14: 0 | AQ14: 0 | AT14: 1 | AU14: Prepayments | AX14: 0 | AY14: 0 | BB14: 1
C15: Accured expenses | E15: =N26+X26+AH26+AR26+AZ26 -> 398259.75 | I15: Other Receivables | N15: =L15 -> 0 | S15: Other Receivables | AC15: Other Receivables | AM15: Other Receivables | AQ15: 0 | AU15: Other Receivables | AY15: 0
C16: 费用 + 待付款 + 拨付备用金 | E16: =N26+X26+AH26+AR26+AZ26 -> 398259.75
N17: =N14 -> 317958.45 | X17: =SUM(X11:X16) -> 16371.04 | AH17: =SUM(AH11:AH16) -> 12228.09 | AR17: =SUM(AR11:AR16) -> 0 | AZ17: =SUM(AZ11:AZ16) -> 24996.94
C18: Net Current Assets/(Liabilities) | E18: =E13-E16 -> -26705.231
I19: CURRENT LIABILITIES | S19: CURRENT LIABILITIES | AC19: CURRENT LIABILITIES | AM19: CURRENT LIABILITIES | AU19: CURRENT LIABILITIES
C21: Net Assets/(Liabilities) | E21: 0 | I21: Accounts Payable | N21: =L22+L23 -> 302102.79 | P21: 1 | S21: Accounts Payable | X21: =V22+V23 -> 36788.27 | Z21: 1 | AC21: Accounts Payable | AH21: =AF22+AF23 -> 18612.14 | AJ21: 1 | AM21: Accounts Payable | AQ21: =AQ22+AQ23 -> 0 | AR21: =AQ21+AQ24 -> 0 | AT21: 1 | AU21: Accounts Payable | AZ21: =AY21+AY23 -> 26341.66 | BB21: 1
I22: Balance due to MSTS (cash deficit) | S22: Balance due to MSTS (cash deficit) | AC22: Balance due to MSTS (cash deficit) | AM22: Balance due to MSTS (cash deficit) | AU22: Balance due to MSTS (cash deficit)
I23: Actual accounts payable | L23: =('Shipmanagement Cost'!X2+'Shipmanagement Cost'!Y2+'Shipmanagement Cost'!Z2+'Shipmanagement Cost'!AA2+'Shipmanagement Cost'!AB2+'Shipmanagement Cost'!T2) -> 302102.79 | S23: Actual accounts payable | V23: ='Owner Cost'!X2+'Owner Cost'!Y2+'Owner Cost'!Z2+'Owner Cost'!AA2+'Owner Cost'!AB2+'Owner Cost'!T2 -> 36788.27 | AC23: Actual accounts payable | AF23: ='Take-Over Cost'!X2+'Take-Over Cost'!Y2+'Take-Over Cost'!Z2+'Take-Over Cost'!AA2+'Take-Over Cost'!AB2+'Take-Over Cost'!T2 -> 18612.14 | AM23: Actual accounts payable | AU23: Actual accounts payable | AY23: ='BMA Flag Change'!Y2+'BMA Flag Change'!Z2+'BMA Flag Change'!AA2+'BMA Flag Change'!AB2+'BMA Flag Change'!AC2+'BMA Flag Change'!T2 -> 26341.66
C24: Equity | I24: Accruals | L24: =('Shipmanagement Cost'!W2) -> 6868.04 | N24: =L24 -> 6868.04 | P24: 1 | S24: Accruals | V24: ='Owner Cost'!W2 -> 0 | X24: =V24 -> 0 | Z24: 1 | AC24: Accruals | AF24: ='Take-Over Cost'!W2 -> 7546.85 | AH24: =AF24 -> 7546.85 | AJ24: 1 | AM24: Accruals | AR24: ='Take-Over Cost'!AG2 -> 0 | AT24: 1 | AU24: Accruals | AY24: ='BMA Flag Change'!X2 -> 0 | AZ24: ='BMA Flag Change'!X2 -> 0 | BB24: 1
C25: Share capital | E25: =E18-E21 -> -26705.231
C26: Issued & Fully Paid 10,000 ordinary shares | D26: 7 | E26: 0 | N26: =SUM(N21:N25) -> 308970.83 | X26: =SUM(X21:X25) -> 36788.27 | AH26: =SUM(AH21:AH25) -> 26158.99 | AR26: =SUM(AR21:AR25) -> 0 | AZ26: =SUM(AZ21:AZ25) -> 26341.66
C27: Retained earnings/(losses) | D27: 7 | E27: =E25-E26 -> -26705.231
E28: =SUM(E26:E27) -> -26705.231 | I28: NET CURRENT ASSETS / (LIABILITIES) | N28: =N17-N26 -> 8987.619 | S28: NET CURRENT ASSETS / (LIABILITIES) | X28: =X17-X26 -> -20417.23 | AC28: NET CURRENT ASSETS / (LIABILITIES) | AH28: =AH17-AH26 -> -13930.9 | AM28: NET CURRENT ASSETS / (LIABILITIES) | AR28: =AR17-AR26 -> 0 | AU28: NET CURRENT ASSETS / (LIABILITIES) | AZ28: =AZ17-AZ26 -> -1344.72
N31: US$ | X31: US$ | AH31: US$ | AR31: US$ | AZ31: US$
C32: Pioneer Lady 费用总结： | D32: 日期： | E32: =TODAY() -> 46309 | I32: FINANCED BY : | S32: FINANCED BY : | AC32: FINANCED BY : | AM32: FINANCED BY : | AU32: FINANCED BY :
C33: XCL Aires Ltd单船船东总收入 | D33: ='Shipmanagement RCVD'!I2+'Shipmanagement RCVD'!J2+'Shipmanagement RCVD'!K2+'Shipmanagement RCVD'!L2+'Shipmanagement RCVD'!M2 -> 371554.52
C34: Pioneer Lady 银行卡账户余额： | D34: ='Bank Verification'!J11 -> 92779.85 | I34: Prior Year Balance Surplus / (Deficit) Brought Forward | P34: 2 | S34: Prior Year Balance Surplus / (Deficit) Brought Forward | X34: 0 | Z34: 2 | AC34: Prior Year Balance Surplus / (Deficit) Brought Forward | AH34: 0 | AJ34: 2 | AM34: Prior Year Balance Surplus / (Deficit) Brought Forward | AR34: 0 | AT34: 2 | AU34: Prior Year Balance Surplus / (Deficit) Brought Forward | AZ34: 0 | BB34: 2
C35: Pioneer Lady 船长 CTM 余额： | D35: ='CTM Expenses List'!AA2 -> 29908 | E35: 非预算待收
C36: 1：Pioneer Lady 船管费用总计 | D36: ='Shipmanagement Cost'!AB2+'Shipmanagement Cost'!T2 -> 193372.59 | E36: 0 | I36: Operating Cost for the Period | L36: =N26 -> 308970.83 | N36: =L36 -> 308970.83 | P36: 2, 2A | S36: Operating Cost for the Period | V36: =X26 -> 36788.27 | X36: =V36 -> 36788.27 | Z36: 2, 2A | AC36: Operating Cost for the Period | AF36: =AH26 -> 26158.99 | AJ36: 2, 2A | AM36: Operating Cost for the Period | AP36: =AR28 -> 0 | AR36: =AP36 -> 0 | AT36: 2, 2A | AU36: Operating Cost for the Period | AX36: =AZ28 -> -1344.72 | AZ36: =AX36 -> -1344.72 | BB36: 2, 2A
C37: 2：Pioneer Lady 帮船东支付总计： | D37: ='Owner Cost'!AB2+'Owner Cost'!T2 -> 19700.04 | E37: =-'Shipmanagement RCVD'!G16 -> 20417.23 | I37: Payment on behalf of Owner | P37: 2 | S37: Payment on behalf of Owner | Z37: 2 | AC37: Payment on behalf of Owner | AF37: 0 | AJ37: 2 | AM37: Payment on behalf of Owner | AP37: 0 | AR37: =AP37 -> 0 | AT37: 2 | AU37: Payment on behalf of Owner | AX37: 0 | AZ37: =AX37 -> 0 | BB37: 2
C38: 3：Pioneer Lady 接船管费用总计： | D38: ='Take-Over Cost'!AB2+'Take-Over Cost'!T2 -> 12428.72 | E38: =-'Shipmanagement RCVD'!G15 -> 13930.9 | I38: Operating Fund Paid to Manager for the Period | L38: =N17 -> 317958.45 | N38: =L38 -> 317958.45 | P38: 2 | S38: Operating Fund Paid to Manager for the Period | V38: =X17 -> 16371.04 | X38: =V38 -> 16371.04 | Z38: 2 | AC38: Operating Fund Paid to Manager for the Period | AF38: =AH17 -> 12228.09 | AH38: 0 | AJ38: 2 | AM38: Operating Fund Paid to Manager for the Period | AP38: 0 | AR38: =AP38 -> 0 | AT38: 2 | AU38: Operating Fund Paid to Manager for the Period | AX38: 0 | AZ38: =AX38 -> 0 | BB38: 2
C39: 4：Pioneer Lady 换船旗为巴哈马费用总计 | D39: ='BMA Flag Change'!AC2+'BMA Flag Change'!T2 -> 26155.9 | E39: =-'Shipmanagement RCVD'!G14 -> 1344.72
C40: 5：Pioneer Lady修船干坞费用费用合计： | D40: ='DD Cost'!AB2+'DD Cost'!S2 -> 0 | E40: ='Shipmanagement RCVD'!M2 -> 0 | I40: AMOUNT DUE TO MSTS Shipmanagement (HK) Limited | N40: =N34-N36-N37+N38 -> 8987.619 | S40: AMOUNT DUE TO MSTS Shipmanagement (HK) Limited | X40: =X38-X36 -> -20417.23 | AC40: AMOUNT DUE TO MSTS Shipmanagement (HK) Limited | AH40: =AF38-AF36 -> -13930.9 | AM40: AMOUNT DUE TO MSTS Shipmanagement (HK) Limited | AR40: =SUM(AR34:AR39) -> 0 | AU40: AMOUNT DUE TO MSTS Shipmanagement (HK) Limited | AZ40: =SUM(AZ34:AZ39) -> -1344.72
C41: 平衡账（总支付−银行−费用−船上备用金）： | D41: =D33-D34-D35-D36-D37-D38-D39-D40 -> -2790.582 | X41: =X40-X28 -> 0 | AH41: =AH40-AH28 -> 0 | AR41: =AR40-AR28 -> 0 | AZ41: =AZ40-AZ28 -> 0
C42: 总结： | D42: =IF(OR(D41>1,D41<-1),"账目没做平","账面做平") -> 账目没做平
J44: =N26+X26+AH26+AZ26 -> 398259.75
J45: =E16 -> 398259.75
E47: =E25-'Bank Verification'!J9 -> -56613.231

Sheet Cost Checking
B2: MV Pioneer Lady | C2: PO | D2: Invoice | J2: Bank | K2: C/N | L2: C/N | N2: 日期 | O2: 收款方 | P2: 付款方 | Q2: 付款额 | R2: 船员工资-9 | S2: 船员GIB上船 | T2: 船员跟船 | U2: CTM | V2: CTM
B3: Description | C3: Amount | D3: Accrual | E3: Receiving | F3: Received | G3: Approved | H3: Paying | I3: Completed | J3: Charge | K3: Accural | L3: Profit(01)
N4: 日期 | O4: 收款方 | P4: 付款方 | Q4: 付款额 | R4: 船员工资-10 | S4: 代付WB工资
B5: Shipmanagement TT RCVD | C5: =C15+F15+I15+I18 -> 371554.52 | I5: ='Shipmanagement RCVD'!I2+'Shipmanagement RCVD'!K2+'Shipmanagement RCVD'!J2+'Shipmanagement RCVD'!L2 -> 371554.52 | J5: ='Shipmanagement RCVD'!O2 -> 40
B6: Shipmanagement Cost | C6: ='Shipmanagement Cost'!AC2 -> 308970.83 | D6: ='Shipmanagement Cost'!W2 -> 6868.04 | E6: ='Shipmanagement Cost'!X2 -> 0 | F6: ='Shipmanagement Cost'!Y2 -> 108730.2 | G6: ='Shipmanagement Cost'!Z2 -> 0 | H6: ='Shipmanagement Cost'!AA2 -> 0 | I6: ='Shipmanagement Cost'!AB2 -> 192452.06 | J6: ='Shipmanagement Cost'!T2 -> 920.53 | K6: ='Shipmanagement Cost'!N2 -> 0 | L6: ='Shipmanagement Cost'!O2 -> 0 | N6: 日期 | O6: 收款方 | P6: 付款方 | Q6: 付款额 | R6: 船员工资-10
B7: Owner Expenses | C7: ='Owner Cost'!AC2 -> 36788.27 | D7: ='Owner Cost'!W2 -> 0 | E7: ='Owner Cost'!X2 -> 0 | F7: ='Owner Cost'!Y2 -> 17088.23 | G7: ='Owner Cost'!Z2 -> 0 | H7: ='Owner Cost'!AA2 -> 0 | I7: ='Owner Cost'!AB2 -> 19680.04 | J7: ='Owner Cost'!T2 -> 20 | K7: ='Owner Cost'!N2 -> 0 | L7: ='Owner Cost'!O2 -> 0
B8: Take-Over Cost | C8: ='Take-Over Cost'!AC2 -> 26158.99 | D8: ='Take-Over Cost'!W2 -> 7546.85 | E8: ='Take-Over Cost'!X2 -> 0 | F8: ='Take-Over Cost'!Y2 -> 6183.42 | G8: ='Take-Over Cost'!Z2 -> 0 | H8: ='Take-Over Cost'!AA2 -> 0 | I8: ='Take-Over Cost'!AB2 -> 12376.24 | J8: ='Take-Over Cost'!T2 -> 52.48 | K8: ='Take-Over Cost'!N2 -> 0 | L8: ='Take-Over Cost'!O2 -> 0
B9: BMA Flag Change | C9: ='BMA Flag Change'!AD2 -> 26341.66 | D9: ='BMA Flag Change'!X2 -> 0 | E9: ='BMA Flag Change'!Y2 -> 0 | F9: ='BMA Flag Change'!Z2 -> 185.76 | G9: ='BMA Flag Change'!AA2 -> 0 | H9: ='BMA Flag Change'!AB2 -> 0 | I9: ='BMA Flag Change'!AC2 -> 26095 | J9: ='BMA Flag Change'!T2 -> 60.9
B10: Expenses Lists | C10: ='Expenses Lists'!AD2 -> 398259.75 | D10: ='Expenses Lists'!X2 -> 14414.89 | E10: ='Expenses Lists'!Y2 -> 0 | F10: ='Expenses Lists'!Z2 -> 132187.61 | G10: ='Expenses Lists'!AA2 -> 0 | H10: ='Expenses Lists'!AB2 -> 0 | I10: ='Expenses Lists'!AC2 -> 250603.34 | J10: ='Expenses Lists'!T2 -> 1053.91 | K10: ='Expenses Lists'!N2 -> 0 | L10: ='Expenses Lists'!O2 -> 0
B11: Diff in Expenses(must 0): | C11: =IF(AND((C10-C8-C6-C7-C9)>-1,(C10-C8-C6-C7-C9)<1),"账面持平",C10-C8-C6-C7-C9) -> 账面持平 | D11: =IF(AND((D10-D8-D6-D7-D9)>-1,(D10-D8-D6-D7-D9)<1),"账面持平",D10-D8-D6-D7-D9) -> 账面持平 | E11: =IF(AND((E10-E8-E6-E7-E9)>-1,(E10-E8-E6-E7-E9)<1),"账面持平",E10-E8-E6-E7-E9) -> 账面持平 | F11: =IF(AND((F10-F8-F6-F7-F9)>-1,(F10-F8-F6-F7-F9)<1),"账面持平",F10-F8-F6-F7-F9) -> 账面持平 | G11: =IF(AND((G10-G8-G6-G7-G9)>-1,(G10-G8-G6-G7-G9)<1),"账面持平",G10-G8-G6-G7-G9) -> 账面持平 | H11: =IF(AND((H10-H8-H6-H7-H9)>-1,(H10-H8-H6-H7-H9)<1),"账面持平",H10-H8-H6-H7-H9) -> 账面持平 | I11: =IF(AND((I10-I8-I6-I7-I9)>-1,(I10-I8-I6-I7-I9)<1),"账面持平",I10-I8-I6-I7-I9) -> 账面持平 | J11: =IF(AND((J10-J8-J6-J7-J9)>-1,(J10-J8-J6-J7-J9)<1),"账面持平",J10-J8-J6-J7-J9) -> 账面持平 | ... L11: =IF(AND((L10-L8-L6-L7-L9)>-1,(L10-L8-L6-L7-L9)<1),"账面持平",L10-L8-L6-L7-L9) -> 账面持平
B13: MV Pioneer Lady | C13: Shipmanagement Expenses | F13: Non-Budget, Owner Expenses | I13: Take-Over Expenses | L13: MSTS
B14: Real-time Account Position | C14: RCVD | D14: Cost | E14: Balance | F14: RCVD | G14: Cost | H14: Balance | I14: RCVD | J14: Cost | K14: Balance | L14: Profit(02)
B15: =C5-C10 -> -26705.231 | C15: ='Shipmanagement RCVD'!I2 -> 317958.45 | D15: ='Shipmanagement Cost'!W2+'Shipmanagement Cost'!X2+'Shipmanagement Cost'!Y2+'Shipmanagement Cost'!Z2+'Shipmanagement Cost'!AA2+'Shipmanagement Cost'!AB2+'Shipmanagement Cost'!T2 -> 308970.83 | E15: =C15-D15 -> 8987.619 | F15: ='Shipmanagement RCVD'!L2 -> 16371.04 | G15: ='Owner Cost'!W2+'Owner Cost'!X2+'Owner Cost'!Y2+'Owner Cost'!Z2+'Owner Cost'!AA2+'Owner Cost'!AB2+'Owner Cost'!T2 -> 36788.27 | H15: =F15-G15 -> -20417.23 | I15: ='Shipmanagement RCVD'!J2 -> 12228.09 | J15: ='Take-Over Cost'!W2+'Take-Over Cost'!X2+'Take-Over Cost'!Y2+'Take-Over Cost'!Z2+'Take-Over Cost'!AA2+'Take-Over Cost'!AB2+'Take-Over Cost'!T2 -> 26158.99 | K15: =I15-J15 -> -13930.9 | L15: ='Expenses Lists'!P2 -> 0
I16: BMA Flag Change, Owner Expenses
I17: RCVD | J17: Cost | K17: Balance
I18: ='Shipmanagement RCVD'!K2 -> 24996.94 | J18: ='BMA Flag Change'!X2+'BMA Flag Change'!Y2+'BMA Flag Change'!Z2+'BMA Flag Change'!AA2+'BMA Flag Change'!AB2+'BMA Flag Change'!AC2+'BMA Flag Change'!T2 -> 26341.66 | K18: =I18-J18 -> -1344.72

Sheet Bank Verification
D2: 美元 | E2: 7982933945 | F2: 入账
D3: 港币 | E3: 7982933945 | F3: 出账
D4: 欧元 | E4: 7982933945 | F4: 结息 | L4: 船队其他船 | M4: 实时单船账户 | N4: 日期
L5: Libra-XS
B6: =TODAY() -> 46309 | C6: 海事管理（MV PIONEER LADY）公司账目一览 | I6: PIONEER LADY银行卡vs账面: | J6: =TODAY() -> 46309 | L6: Pioneer Lady | M6: =J11 -> 92779.85
B7: Pioneer Lady | D7: MV PIONEER LADY（发票）付款进度概要 | I7: PIONEER LADY待支付: | J7: =SUM(C9:G9) -> 146602.5 | L7: CBL Spring
B8: 海事下订单 | C8: Accrual | D8: Receiving | E8: Received | F8: Approved | G8: Paying | H8: Completed | I8: PIONEER LADY(MSTS)收入: | J8: ='Cost Checking'!L15+'Cost Checking'!L10 -> 0 | L8: CBL Summer
B9: ='Cost Checking'!C7+'Cost Checking'!C6+'Cost Checking'!C8+'Cost Checking'!C9 -> 398259.75 | C9: ='Cost Checking'!D6+'Cost Checking'!D7+'Cost Checking'!D8+'Cost Checking'!D9 -> 14414.89 | D9: ='Cost Checking'!E6+'Cost Checking'!E7+'Cost Checking'!E8+'Cost Checking'!E9 -> 0 | E9: ='Cost Checking'!F6+'Cost Checking'!F7+'Cost Checking'!F8+'Cost Checking'!F9 -> 132187.61 | F9: ='Cost Checking'!G6+'Cost Checking'!G7+'Cost Checking'!G8+'Cost Checking'!G9 -> 0 | G9: ='Cost Checking'!H6+'Cost Checking'!H7+'Cost Checking'!H8+'Cost Checking'!H9 -> 0 | H9: ='Cost Checking'!I6+'Cost Checking'!I7+'Cost Checking'!I8+'Cost Checking'!I9 -> 250603.34 | I9: CTM ROB 船上现金资产: | J9: ='CTM Expenses List'!AA2 -> 29908 | L9: 船管账户现金流 | M9: =SUM(M5:M8) -> 92779.85
B10: MV PIONEER LADY (星展银行) 账户进/出账目记录 | H10: 银行付款手续费: | I10: PIONEER LADY单船财务平衡: | J10: =J11+J9-J7 -> -23914.649 | L10: 银行账户短息
B11: 序号 | C11: 日期 | D11: 币种 | E11: 账户 | F11: 入账/出账 | G11: 数额 | H11: =SUM(H12:H1110) -> 1133.91 | I11: PIONEER LADY银行卡PingPong余额: | J11: {=INDEX(J:J,MIN(IF(J12:J35<>"",ROW(J12:J35))))} -> 92779.85 | K11: 备注 | L11: 差别 | M11: =M9-M10 -> 92779.85
B14: 22 | C14: 46300 | D14: 美元 | E14: 7982933945 | F14: 入账 | G14: 9598.45 | H14: 0 | I14: =G14+H14 -> 9598.45 | J14: =IF(F14="入账",(J15+I14),(J15-I14)) -> 92779.85 | K14: PIONEER LADY
B15: 21 | C15: 46293 | D15: 美元 | E15: 7982933945 | F15: 入账 | G15: 9500 | H15: 20 | I15: =G15+H15 -> 9520 | J15: =IF(F15="入账",(J16+I15),(J16-I15)) -> 83181.4 | K15: PIONEER LADY付款失败
B16: 20 | C16: 46295 | D16: 美元 | E16: 7982933945 | F16: 出账 | G16: 2600 | H16: 20 | I16: =G16+H16 -> 2620 | J16: =IF(F16="入账",(J17+I16),(J17-I16)) -> 73661.4 | K16: Libra-XS
B17: 19 | C17: 46295 | D17: 美元 | E17: 7982933945 | F17: 出账 | G17: 30000 | H17: 120 | I17: =G17+H17 -> 30120 | J17: =IF(F17="入账",(J18+I17),(J18-I17)) -> 76281.4 | K17: PIONEER LADY
B18: 18 | C18: 46293 | D18: 美元 | E18: 7982933945 | F18: 出账 | G18: 1660 | H18: 20 | I18: =G18+H18 -> 1680 | J18: =IF(F18="入账",(J19+I18),(J19-I18)) -> 106401.4 | K18: PIONEER LADY
B19: 17 | C19: 46293 | D19: 美元 | E19: 7982933945 | F19: 出账 | G19: 9500 | H19: 20 | I19: =G19+H19 -> 9520 | J19: =IF(F19="入账",(J20+I19),(J20-I19)) -> 108081.4 | K19: PIONEER LADY
B20: 16 | C20: 46289 | D20: 美元 | E20: 7982933945 | F20: 出账 | G20: 4271.4 | H20: 20 | I20: =G20+H20 -> 4291.4 | J20: =IF(F20="入账",(J21+I20),(J21-I20)) -> 117601.4 | K20: PIONEER LADY
B21: 15 | C21: 46287 | D21: 美元 | E21: 7982933945 | F21: 出账 | G21: 1350 | H21: 20 | I21: =G21+H21 -> 1370 | J21: =IF(F21="入账",(J22+I21),(J22-I21)) -> 121892.8 | K21: PIONEER LADY
B22: 14 | C22: 46279 | D22: 美元 | E22: 7982933945 | F22: 出账 | G22: 30000 | H22: 120 | I22: 30120 | J22: =IF(F22="入账",(J23+I22),(J23-I22)) -> 123262.8 | K22: PIONEER LADY
B23: 13 | C23: 46276 | D23: 美元 | E23: 7982933945 | F23: 出账 | G23: 85263.12 | H23: 170.53 | I23: 85433.65 | J23: =IF(F23="入账",(J24+I23),(J24-I23)) -> 153382.8 | K23: PIONEER LADY
B24: 12 | C24: 46275 | D24: 美元 | E24: 7982933945 | F24: 入账 | G24: 202246.07 | H24: 20 | I24: 202226.07 | J24: =IF(F24="入账",(J25+I24),(J25-I24)) -> 238816.45 | K24: PIONEER LADY
B25: 11 | C25: 46273 | D25: 美元 | E25: 7982933945 | F25: 出账 | G25: 50000 | H25: 200 | I25: =G25+H25 -> 50200 | J25: =IF(F25="入账",(J26+I25),(J26-I25)) -> 36590.38 | K25: PIONEER LADY
B26: 10 | C26: 46268 | D26: 美元 | E26: 7982933945 | F26: 出账 | G26: 8121.24 | H26: 32.48 | I26: =G26+H26 -> 8153.72 | J26: =IF(F26="入账",(J27+I26),(J27-I26)) -> 86790.38 | K26: PIONEER LADY
B27: 9 | C27: 46265 | D27: 美元 | E27: 7982933945 | F27: 出账 | G27: 45000 | H27: 180 | I27: =G27+H27 -> 45180 | J27: =IF(F27="入账",(J28+I27),(J28-I27)) -> 94944.1 | K27: PIONEER LADY
B28: 8 | C28: 46265 | D28: 美元 | E28: 7982933945 | F28: 出账 | G28: 5000 | H28: 20 | I28: =G28+H28 -> 5020 | J28: =IF(F28="入账",(J29+I28),(J29-I28)) -> 140124.1 | K28: PIONEER LADY
B29: 7 | C29: 46261 | D29: 美元 | E29: 7982933945 | F29: 出账 | G29: 2000 | H29: 20 | I29: =G29+H29 -> 2020 | J29: =IF(F29="入账",(J30+I29),(J30-I29)) -> 145144.1 | K29: PIONEER LADY
B30: 6 | C30: 46259 | D30: 美元 | E30: 7982933945 | F30: 出账 | H30: 50 | I30: =G30+H30 -> 50 | J30: =IF(F30="入账",(J31+I30),(J31-I30)) -> 147164.1 | K30: PIONEER LADY
B31: 5 | C31: 46252 | D31: 美元 | E31: 7982933945 | F31: 出账 | G31: 10225 | H31: 40.9 | I31: =G31+H31 -> 10265.9 | J31: =IF(F31="入账",(J32+I31),(J32-I31)) -> 147214.1 | K31: PIONEER LADY
B32: 4 | C32: 46248 | D32: 美元 | E32: 7982933945 | F32: 出账 | G32: 2230 | H32: 20 | I32: =G32+H32 -> 2250 | J32: =IF(F32="入账",(J33+I32),(J33-I32)) -> 157480 | K32: PIONEER LADY | L32: =J11-E9-C9 -> -53822.649
B33: 3 | C33: 46248 | D33: 美元 | E33: 7982933945 | F33: 入账 | G33: 156350 | H33: 20 | I33: =G33-H33 -> 156330 | J33: =IF(F33="入账",(J34+I33),(J34-I33)) -> 159730 | K33: PIONEER LADY
B34: 2 | C34: 46227 | D34: 美元 | E34: 7982933945 | F34: 入账 | G34: 2100 | H34: 0 | I34: =G34+H34 -> 2100 | J34: =IF(F34="入账",(J35+I34),(J35-I34)) -> 3400 | K34: PIONEER LADY
B35: 1 | C35: 46225 | D35: 美元 | E35: 7982933945 | F35: 入账 | G35: 1300 | H35: 0 | I35: =G35+H35 -> 1300 | J35: =G35-H35 -> 1300 | K35: PIONEER LADY

Sheet Shipmanagement RCVD
B1: 入账日期 | C1: 类型 | D1: RQA | E1: Supplier | F1: PO Nos | G1: PO Current | H1: Rating | I1: Shipmanagement Amount(USD) | J1: Take-Over Account | K1: BMA Flag Change | L1: Owner Cost | M1: DD Cost | N1: Date | O1: Bank Charge | P1: Bank Charge
D2: Received | E2: Uploaded | F2: Approved | G2: Paying | H2: Completed | I2: =SUM(I3:I25) -> 317958.45 | J2: =SUM(J3:J25) -> 12228.09 | K2: =SUM(K3:K25) -> 24996.94 | L2: =SUM(L3:L25) -> 16371.04 | M2: =SUM(M3:M25) -> 0 | O2: =SUM(O3:O68) -> 40
B13: 46300 | C13: 顾问的费用-王总 | D13: Completed | E13: VENTURE MARITIME (HONG KONG) LIMITED | G13: 9598.45 | H13: 1 | I13: =G13*H13 -> 9598.45 | N13: =B13 -> 46300 | P13: HK Payee Advice_700a20625e0b477d8a20625e0b577dbb.pdf
C14: BMA Flag Change 9月份换船旗费用 | D14: Completed | E14: XCL ARIES LTD | G14: =SOFP!AZ40 -> -1344.72
C15: Take-Over Cost9月份船东费用 | D15: Completed | E15: XCL ARIES LTD | G15: =SOFP!AH40 -> -13930.9
C16: Owner Cost 9月份船东费用 | D16: Completed | E16: XCL ARIES LTD | G16: =SOFP!X40 -> -20417.23
C17: 船舶管理运营拨款10月份 | D17: Completed | E17: XCL ARIES LTD | G17: =5000*31 -> 155000
B18: 46275 | C18: BMA Flag Change 8月份换船旗费用 | D18: Completed | E18: XCL ARIES LTD | G18: 24996.94 | H18: 1 | K18: =G18 -> 24996.94 | N18: 46275 | P18: 63f3beff3842f8c1ab8873eb8078536d.pdf
B19: 46275 | C19: Take-Over Cost 8月份船东费用 | D19: Completed | E19: XCL ARIES LTD | G19: 12228.09 | H19: 1 | J19: =G19 -> 12228.09 | N19: 46275
B20: 46275 | C20: Owner Cost 8月份船东费用 | D20: Completed | E20: XCL ARIES LTD | G20: 15021.04 | H20: 1 | L20: =G20 -> 15021.04 | N20: 46275
B21: 46275 | C21: 船舶管理运营拨款9月份 | D21: Completed | E21: XCL ARIES LTD | G21: 150000 | H21: 1 | I21: =G21-O21 -> 149980 | N21: 46275 | O21: 20
B22: 46234 | C22: GRESIK加淡水100吨 | D22: Completed | E22: XCL ARIES LTD | G22: 1350 | H22: 1 | L22: 1350 | N22: =B22 -> 46234 | P22: 电子回单详情.pdf
B23: 46248 | C23: 船舶管理运营拨款8月份 | D23: Completed | E23: XCL ARIES LTD | G23: 155000 | H23: 1 | I23: =G23-O23 -> 154980 | N23: 46248 | O23: 20
B24: 46227 | C24: 接船费预付款 | D24: Completed | E24: 5 Ocean Ship Service (HK) Limited | G24: 2100 | H24: 1 | I24: =(G24*H24)-L24 -> 2100 | N24: 46227 | P24: Payment_Certificate_20260723210333.pdf
B25: 46225 | C25: 船舶维修服务-ACC Motor repair | D25: Completed | E25: 5 Ocean Ship Service (HK) Limited | G25: 1300 | H25: 1 | I25: =G25*H25 -> 1300 | N25: 46225 | P25: Payment_Certificate_20260722134815.pdf
B27: T/O Date | C27: Ship Management Expenses-Rcvd | D27: =I2 -> 317958.45
B28: 46218 | C28: Ship Take-over Expenses-Rcvd | D28: =J2 -> 12228.09
B29: Days | C29: Non Budget Expenses-Rcvd | D29: =L2 -> 16371.04
B30: =TODAY()-B28 -> 91 | C30: DD Expenses-Rcvd | D30: =K2 -> 24996.94
B31: Others | C31: Total Costs | D31: =SUM(D27:D30) -> 371554.52
C32: OPEX(Including O.B.O Payment) | D32: =(D27+D28+D29+D30)/(TODAY()-B28) -> 4083.0167

Sheet Expenses Lists
A1: 入账日期 | B1: 类型 | C1: RQA | D1: Supplier | E1: PO Nos | F1: Pay. Approval | G1: PO Current | H1: Rating | I1: PO Amount (USD) | J1: Account Code | K1: GRN/Date | L1: GRN Amount(USD) | M1: Invoice Amount(USD) | N1: C/N,Accural | O1: C/N Profit | P1: Profit | Q1: Invoice Date | R1: Due Date | S1: Payment Status | T1: Bank Charge | U1: Bank Slip | V1: Attachement | W1: Attachement | X1: Accrual | Y1: Receiving | Z1: Received | AA1: Approved | AB1: Paying | AC1: Completed
C2: Receiving | D2: Received | E2: Approved | G2: Paying | H2: Completed | I2: =SUM(I4:I101) -> 491536.62 | L2: =SUM(L4:L129) -> 491586.62 | M2: =SUM(M4:M129) -> 490602.02 | N2: =SUM(N83:N101) -> 0 | O2: =SUM(O83:O101) -> 0 | P2: =SUM(P83:P101) -> 0 | T2: =SUM(T4:T103) -> 1053.91 | V2: Invoices | W2: Credit Note | X2: =SUM(X4:X166) -> 14414.89 | Y2: =SUM(Y4:Y166) -> 0 | Z2: =SUM(Z4:Z166) -> 132187.61 | AA2: =SUM(AA4:AA166) -> 0 | AB2: =SUM(AB4:AB166) -> 0 | AC2: =SUM(AC4:AC166) -> 250603.34 | AD2: =SUM(X2:AC2)+T2 -> 398259.75
A3: 46265 | B3: CTM 月度船上结余 | D3: MSTS | G3: ='CTM Expenses List'!AA2 -> 29908 | H3: 1 | I3: =-G3 -> -29908 | J3: 6000007 | K3: 46265 | L3: =I3 -> -29908 | M3: =L3 -> -29908 | S3: Completed | X3: =IF(S3="Accrual",M3,"") | Y3: =IF(S3="Receiving",M3,"") | Z3: =IF(S3="Received",M3,"") | AA3: =IF(S3="Approved",M3,"") | AB3: =IF(S3="Paying",M3,"") | AC3: =IF(S3="Completed",M3,"") -> -29908
X4: =IF(S4="Accrual",M4,"") | Y4: =IF(S4="Receiving",M4,"") | Z4: =IF(S4="Received",M4,"") | AA4: =IF(S4="Approved",M4,"") | AB4: =IF(S4="Paying",M4,"") | AC4: =IF(S4="Completed",M4,"")
A5: 46309 | B5: 9月份船员工资+其他费用 | D5: Top Marine Limited | G5: 77881.96 | H5: 1 | I5: =G5*H5 -> 77881.96 | J5: 1000001 | K5: =A5 -> 46309 | L5: =I5 -> 77881.96 | M5: =L5 -> 77881.96 | S5: Received | X5: =IF(S5="Accrual",M5,"") | Y5: =IF(S5="Receiving",M5,"") | Z5: =IF(S5="Received",M5,"") -> 77881.96 | AA5: =IF(S5="Approved",M5,"") | AB5: =IF(S5="Paying",M5,"") | AC5: =IF(S5="Completed",M5,"")
A6: 46295 | B6: 帮Libra-XS支付巴哈马年度国旗国检验 | D6: SIMINTEC | G6: 2600 | H6: 1 | I6: =G6*H6 -> 2600 | L6: =I6 -> 2600 | M6: =L6 -> 2600 | S6: Completed | T6: 20 | X6: =IF(S6="Accrual",M6,"") | Y6: =IF(S6="Receiving",M6,"") | Z6: =IF(S6="Received",M6,"") | AA6: =IF(S6="Approved",M6,"") | AB6: =IF(S6="Paying",M6,"") | AC6: =IF(S6="Completed",M6,"") -> 2600
A7: 46295 | B7: 9月份客餐费用支出 | D7: CTM | G7: 249 | H7: 1 | I7: =G7*H7 -> 249 | J7: 6000002 | K7: =A7 -> 46295 | L7: =I7 -> 249 | M7: =L7 -> 249 | S7: Completed | X7: =IF(S7="Accrual",M7,"") | Y7: =IF(S7="Receiving",M7,"") | Z7: =IF(S7="Received",M7,"") | AA7: =IF(S7="Approved",M7,"") | AB7: =IF(S7="Paying",M7,"") | AC7: =IF(S7="Completed",M7,"") -> 249
A8: 46295 | B8: 9月份全船伙食费支出 | D8: CTM | G8: 5592 | H8: 1 | I8: =G8*H8 -> 5592 | J8: 1000002 | K8: =A8 -> 46295 | L8: =I8 -> 5592 | M8: =L8 -> 5592 | S8: Completed | X8: =IF(S8="Accrual",M8,"") | Y8: =IF(S8="Receiving",M8,"") | Z8: =IF(S8="Received",M8,"") | AA8: =IF(S8="Approved",M8,"") | AB8: =IF(S8="Paying",M8,"") | AC8: =IF(S8="Completed",M8,"") -> 5592
A9: 46293 | B9: 巴生港锚地检验陪同费 | D9: Silver Base Maritime Sdn. Bhd. | G9: 1660 | H9: 1 | I9: =G9*H9 -> 1660 | J9: 4000014 | L9: =I9 -> 1660 | M9: =L9 -> 1660 | S9: Completed | T9: 20 | X9: =IF(S9="Accrual",M9,"") | Y9: =IF(S9="Receiving",M9,"") | Z9: =IF(S9="Received",M9,"") | AA9: =IF(S9="Approved",M9,"") | AB9: =IF(S9="Paying",M9,"") | AC9: =IF(S9="Completed",M9,"") -> 1660
A10: 46293 | B10: 借款给 MULAU SHIPMANAGEMENT (HK) LIMITED付款失败 | D10: Maritime Solutions Technology Services (HK) Limited | G10: -9500 | H10: 1 | I10: =G10*H10 -> -9500 | L10: =I10 -> -9500 | M10: =L10 -> -9500 | S10: Completed | T10: -20 | AC10: =IF(S10="Completed",M10,"") -> -9500
A11: 46293 | B11: 借款给 MULAU SHIPMANAGEMENT (HK) LIMITED | D11: Maritime Solutions Technology Services (HK) Limited | G11: 9500 | H11: 1 | I11: =G11*H11 -> 9500 | L11: =I11 -> 9500 | M11: =L11 -> 9500 | S11: Completed | T11: 20 | X11: =IF(S11="Accrual",M11,"") | Y11: =IF(S11="Receiving",M11,"") | Z11: =IF(S11="Received",M11,"") | AA11: =IF(S11="Approved",M11,"") | AB11: =IF(S11="Paying",M11,"") | AC11: =IF(S11="Completed",M11,"") -> 9500
A12: 46289 | B12: PIONEER LADY_海卫通卫星通信服务费 | D12: Marinesat海卫通网络科技有限公司 | G12: 8487.98 | H12: 0.149 | I12: =G12*H12 -> 1264.709 | J12: 6000017 | L12: =I12 -> 1264.709 | M12: =L12 -> 1264.709 | S12: Received | X12: =IF(S12="Accrual",M12,"") | Y12: =IF(S12="Receiving",M12,"") | Z12: =IF(S12="Received",M12,"") -> 1264.709 | AA12: =IF(S12="Approved",M12,"") | AB12: =IF(S12="Paying",M12,"") | AC12: =IF(S12="Completed",M12,"")
A13: 46289 | B13: PIONEER LADY_办公租赁费+薪资 | G13: =157197.89+70000 -> 227197.89 | H13: 0.14937855 | I13: =G13*H13 -> 33938.492 | J13: 6000016 | L13: =I13 -> 33938.492 | M13: =L13 -> 33938.492 | S13: Completed | T13: 120 | X13: =IF(S13="Accrual",M13,"") | Y13: =IF(S13="Receiving",M13,"") | Z13: =IF(S13="Received",M13,"") | AA13: =IF(S13="Approved",M13,"") | AB13: =IF(S13="Paying",M13,"") | AC13: =IF(S13="Completed",M13,"") -> 33938.492
A14: 46286 | B14: Termination of FME | D14: The LISCR Trust Company | G14: 300 | H14: 1 | I14: =G14*H14 -> 300 | J14: 9000005 | L14: =I14 -> 300 | M14: =L14 -> 300 | Q14: 46285 | S14: Completed | X14: =IF(S14="Accrual",M14,"") | Y14: =IF(S14="Receiving",M14,"") | Z14: =IF(S14="Received",M14,"") | AA14: =IF(S14="Approved",M14,"") | AB14: =IF(S14="Paying",M14,"") | AC14: =IF(S14="Completed",M14,"") -> 300
A15: 46286 | B15: LISCR Annual Registration+Agent Fee | D15: The LISCR Trust Company | G15: 1050 | H15: 1 | I15: =G15*H15 -> 1050 | J15: 9000005 | L15: =I15 -> 1050 | M15: =L15 -> 1050 | Q15: 46183 | R15: 46254 | S15: Completed | T15: 20 | X15: =IF(S15="Accrual",M15,"") | Y15: =IF(S15="Receiving",M15,"") | Z15: =IF(S15="Received",M15,"") | AA15: =IF(S15="Approved",M15,"") | AB15: =IF(S15="Paying",M15,"") | AC15: =IF(S15="Completed",M15,"") -> 1050
A16: 46286 | B16: 柯凯敏青岛就医及路费支出 | D16: CTM | G16: 149 | H16: 1 | I16: =G16*H16 -> 149 | J16: 7000009 | K16: =A16 -> 46286 | L16: =I16 -> 149 | M16: =L16 -> 149 | S16: Completed | X16: =IF(S16="Accrual",M16,"") | Y16: =IF(S16="Receiving",M16,"") | Z16: =IF(S16="Received",M16,"") | AA16: =IF(S16="Approved",M16,"") | AB16: =IF(S16="Paying",M16,"") | AC16: =IF(S16="Completed",M16,"") -> 149
A17: 46286 | B17: 678月季度自修奖金支出 | D17: CTM | G17: 3000 | H17: 1 | I17: =G17*H17 -> 3000 | J17: 10000007 | K17: =A17 -> 46286 | L17: =I17 -> 3000 | M17: =L17 -> 3000 | S17: Completed | X17: =IF(S17="Accrual",M17,"") | Y17: =IF(S17="Receiving",M17,"") | Z17: =IF(S17="Received",M17,"") | AA17: =IF(S17="Approved",M17,"") | AB17: =IF(S17="Paying",M17,"") | AC17: =IF(S17="Completed",M17,"") -> 3000
A18: 46285 | B18: 青岛通用物料申请 | C18: DPILT26009 | D18: DanTecs (HK) Marine Solutions Limited | E18: PILDT26009 | G18: 4113.43 | H18: 1 | I18: 4113.43 | J18: 2000005 | L18: 4113.43 | M18: =L18 -> 4113.43 | Q18: 46283 | R18: 46313 | S18: Received | X18: =IF(S18="Accrual",M18,"") | Y18: =IF(S18="Receiving",M18,"") | Z18: =IF(S18="Received",M18,"") -> 4113.43 | AA18: =IF(S18="Approved",M18,"") | AB18: =IF(S18="Paying",M18,"") | AC18: =IF(S18="Completed",M18,"")
A19: 46284 | B19: 青岛港加工缆车刹车操作杆费用-周琦支付 | G19: 522.51 | H19: 1 | I19: =G19*H19 -> 522.51 | J19: 4000002 | L19: =I19 -> 522.51 | M19: =L19 -> 522.51 | S19: Completed | X19: =IF(S19="Accrual",M19,"") | Y19: =IF(S19="Receiving",M19,"") | Z19: =IF(S19="Received",M19,"") | AA19: =IF(S19="Approved",M19,"") | AB19: =IF(S19="Paying",M19,"") | AC19: =IF(S19="Completed",M19,"") -> 522.51
A20: 46284 | B20: 青岛代理收 SPRO费用300美元 | D20: CTM | G20: 300 | H20: 1 | I20: =G20*H20 -> 300 | J20: 6000001 | K20: =A20 -> 46284 | L20: =I20 -> 300 | M20: =L20 -> 300 | S20: Completed | X20: =IF(S20="Accrual",M20,"") | Y20: =IF(S20="Receiving",M20,"") | Z20: =IF(S20="Received",M20,"") | AA20: =IF(S20="Approved",M20,"") | AB20: =IF(S20="Paying",M20,"") | AC20: =IF(S20="Completed",M20,"") -> 300
A21: 46284 | B21: 青岛购买BondedStore香烟 | D21: CTM | G21: 1010 | H21: 1 | I21: =G21*H21 -> 1010 | J21: 6000020 | K21: =A21 -> 46284 | L21: =I21 -> 1010 | M21: =L21 -> 1010 | S21: Completed | X21: =IF(S21="Accrual",M21,"") | Y21: =IF(S21="Receiving",M21,"") | Z21: =IF(S21="Received",M21,"") | AA21: =IF(S21="Approved",M21,"") | AB21: =IF(S21="Paying",M21,"") | AC21: =IF(S21="Completed",M21,"") -> 1010
A22: 46283 | B22: 日照购买Bonded Store酒水等支出 | D22: CTM | G22: 293 | H22: 1 | I22: =G22*H22 -> 293 | J22: 6000020 | K22: =A22 -> 46283 | L22: =I22 -> 293 | M22: =L22 -> 293 | S22: Completed | X22: =IF(S22="Accrual",M22,"") | Y22: =IF(S22="Receiving",M22,"") | Z22: =IF(S22="Received",M22,"") | AA22: =IF(S22="Approved",M22,"") | AB22: =IF(S22="Paying",M22,"") | AC22: =IF(S22="Completed",M22,"") -> 293
A23: 46281 | B23: 青岛港冰机修理 | D23: GORDON MARINE REFRIGERATION CO.,LTD, | G23: 28650 | H23: 0.149 | I23: =G23*H23 -> 4268.85 | J23: 4000005 | L23: =I23 -> 4268.85 | M23: =L23 -> 4268.85 | S23: Accrual | X23: =IF(S23="Accrual",M23,"") -> 4268.85 | Y23: =IF(S23="Receiving",M23,"") | Z23: =IF(S23="Received",M23,"") | AA23: =IF(S23="Approved",M23,"") | AB23: =IF(S23="Paying",M23,"") | AC23: =IF(S23="Completed",M23,"")
A24: 46281 | B24: 冰种+码头管理费 | C24: EPILT26004 | D24: DanTecs (HK) Marine Solutions Limited | E24: PILET26004 | G24: 560 | H24: 1 | I24: 560 | J24: 2000008 | L24: 560 | M24: 560 | S24: Received | Z24: =IF(S24="Received",M24,"") -> 560
B25: 冲回原船管欠船员7月份伙食费支出 | D25: MSTS | G25: -1544 | H25: 1 | I25: -1544 | J25: 6000007 | L25: -1544 | M25: -1544 | X25: =IF(S25="Accrual",M25,"") | Y25: =IF(S25="Receiving",M25,"") | Z25: =IF(S25="Received",M25,"") | AA25: =IF(S25="Approved",M25,"") | AB25: =IF(S25="Paying",M25,"") | AC25: =IF(S25="Completed",M25,"")
A26: 46284 | B26: 办公室杂项费用 | G26: 298.31 | H26: 1 | I26: =G26*H26 -> 298.31 | J26: 6000016 | L26: =I26 -> 298.31 | M26: =L26 -> 298.31 | S26: Completed | X26: =IF(S26="Accrual",M26,"") | Y26: =IF(S26="Receiving",M26,"") | Z26: =IF(S26="Received",M26,"") | AA26: =IF(S26="Approved",M26,"") | AB26: =IF(S26="Paying",M26,"") | AC26: =IF(S26="Completed",M26,"") -> 298.31
A27: 46274 | B27: Pioneer Lady岚桥港值班及交通补贴-周琦RMB3541.02 | G27: 522.51 | H27: 1 | I27: =G27*H27 -> 522.51 | J27: 6000006 | L27: =I27 -> 522.51 | M27: =L27 -> 522.51 | X27: =IF(S27="Accrual",M27,"") | Y27: =IF(S27="Receiving",M27,"") | Z27: =IF(S27="Received",M27,"") | AA27: =IF(S27="Approved",M27,"") | AB27: =IF(S27="Paying",M27,"") | AC27: =IF(S27="Completed",M27,"")
A28: 46272 | B28: 青岛港采购油漆 | C28: DPILT26008 | D28: DanTecs (HK) Marine Solutions Limited | E28: PILDT26008 | G28: 12974.8 | H28: 1 | I28: =G28*H28 -> 12974.8 | J28: 2000004 | L28: =I28 -> 12974.8 | M28: =L28 -> 12974.8 | Q28: 46283 | R28: 46313 | S28: Received | X28: =IF(S28="Accrual",M28,"") | Y28: =IF(S28="Receiving",M28,"") | Z28: =IF(S28="Received",M28,"") -> 12974.8 | AA28: =IF(S28="Approved",M28,"") | AB28: =IF(S28="Paying",M28,"") | AC28: =IF(S28="Completed",M28,"")
A29: 46272 | B29: 岚桥港舱盖 UT 超声波检验费-Owner Paid | D29: REASUN INSURANCE SURVEYORS & ADJUSTERS CO., LTD | E29: SY2026080042LND | G29: 1200 | H29: 1 | I29: =G29*H29 -> 1200 | J29: 4000014 | K29: 46266 | L29: =I29 -> 1200 | M29: =L29 -> 1200 | Q29: 46266 | R29: 46268 | X29: =IF(S29="Accrual",M29,"") | Y29: =IF(S29="Receiving",M29,"") | Z29: =IF(S29="Received",M29,"") | AA29: =IF(S29="Approved",M29,"") | AB29: =IF(S29="Paying",M29,"") | AC29: =IF(S29="Completed",M29,"")
A30: 46269 | B30: BMA 换旗相关证书费用 | D30: Top Marine Limited | G30: 2565 | H30: 1 | I30: =G30*H30 -> 2565 | J30: 9000000 | L30: =I30 -> 2565 | M30: =L30 -> 2565 | S30: Completed | X30: =IF(S30="Accrual",M30,"") | Y30: =IF(S30="Receiving",M30,"") | Z30: =IF(S30="Received",M30,"") | AA30: =IF(S30="Approved",M30,"") | AB30: =IF(S30="Paying",M30,"") | AC30: =IF(S30="Completed",M30,"") -> 2565
A31: 46269 | B31: 8 月份船员海外换班费 | D31: Top Marine Limited | G31: 12501.04 | H31: 1 | I31: =G31*H31 -> 12501.04 | J31: 1000090 | L31: =I31 -> 12501.04 | M31: =L31 -> 12501.04 | S31: Completed | X31: =IF(S31="Accrual",M31,"") | Y31: =IF(S31="Receiving",M31,"") | Z31: =IF(S31="Received",M31,"") | AA31: =IF(S31="Approved",M31,"") | AB31: =IF(S31="Paying",M31,"") | AC31: =IF(S31="Completed",M31,"") -> 12501.04
A32: 46269 | B32: 8 月份船员工资 | D32: Top Marine Limited | G32: 70197.08 | H32: 1 | I32: =G32*H32 -> 70197.08 | J32: 1000001 | L32: =I32 -> 70197.08 | M32: =L32 -> 70197.08 | S32: Completed | T32: 170.53 | X32: =IF(S32="Accrual",M32,"") | Y32: =IF(S32="Receiving",M32,"") | Z32: =IF(S32="Received",M32,"") | AA32: =IF(S32="Approved",M32,"") | AB32: =IF(S32="Paying",M32,"") | AC32: =IF(S32="Completed",M32,"") -> 70197.08
A33: 46267 | B33: 提现后的差额费用 | G33: 2301.47 | H33: 1 | I33: =G33*H33 -> 2301.47 | J33: 6000016 | L33: =I33 -> 2301.47 | M33: =L33 -> 2301.47 | S33: Completed | X33: =IF(S33="Accrual",M33,"") | Y33: =IF(S33="Receiving",M33,"") | Z33: =IF(S33="Received",M33,"") | AA33: =IF(S33="Approved",M33,"") | AB33: =IF(S33="Paying",M33,"") | AC33: =IF(S33="Completed",M33,"") -> 2301.47
A34: 46267 | B34: 办公室费用 | G34: 10292.19 | H34: 1 | I34: =G34*H34 -> 10292.19 | J34: 6000013 | L34: =I34 -> 10292.19 | M34: =L34 -> 10292.19 | S34: Completed | X34: =IF(S34="Accrual",M34,"") | Y34: =IF(S34="Receiving",M34,"") | Z34: =IF(S34="Received",M34,"") | AA34: =IF(S34="Approved",M34,"") | AB34: =IF(S34="Paying",M34,"") | AC34: =IF(S34="Completed",M34,"") -> 10292.19
A35: 46267 | B35: 通信数据流量费 | D35: TELEOCEAN INC | G35: 44.8 | H35: 1 | I35: =G35*H35 -> 44.8 | J35: 6000017 | K35: 46266 | L35: =I35 -> 44.8 | M35: =L35 -> 44.8 | Q35: 46266 | R35: 46281 | S35: Received | X35: =IF(S35="Accrual",M35,"") | Y35: =IF(S35="Receiving",M35,"") | Z35: =IF(S35="Received",M35,"") -> 44.8 | AA35: =IF(S35="Approved",M35,"") | AB35: =IF(S35="Paying",M35,"") | AC35: =IF(S35="Completed",M35,"")
A36: 46267 | B36: Vizada 通信订阅费（8月） | D36: TELEOCEAN INC | G36: 150 | H36: 1 | I36: =G36*H36 -> 150 | J36: 6000017 | K36: 46267 | L36: =I36 -> 150 | M36: =L36 -> 150 | Q36: 46267 | R36: 46282 | S36: Received | X36: =IF(S36="Accrual",M36,"") | Y36: =IF(S36="Receiving",M36,"") | Z36: =IF(S36="Received",M36,"") -> 150 | AA36: =IF(S36="Approved",M36,"") | AB36: =IF(S36="Paying",M36,"") | AC36: =IF(S36="Completed",M36,"")
A37: 46266 | B37: MSTS股份转移 | G37: 30622.61 | H37: 1 | I37: =G37*H37 -> 30622.61 | J37: 6000016 | L37: =I37 -> 30622.61 | M37: =L37 -> 30622.61 | S37: Completed | T37: 120 | X37: =IF(S37="Accrual",M37,"") | Y37: =IF(S37="Receiving",M37,"") | Z37: =IF(S37="Received",M37,"") | AA37: =IF(S37="Approved",M37,"") | AB37: =IF(S37="Paying",M37,"") | AC37: =IF(S37="Completed",M37,"") -> 30622.61
A38: 46266 | B38: 周老轨岚桥防船代理费用 | D38: CTM | G38: 120 | H38: 1 | I38: =G38*H38 -> 120 | J38: 6000001 | K38: =A38 -> 46266 | L38: =I38 -> 120 | M38: =L38 -> 120 | S38: Completed | X38: =IF(S38="Accrual",M38,"") | Y38: =IF(S38="Receiving",M38,"") | Z38: =IF(S38="Received",M38,"") | AA38: =IF(S38="Approved",M38,"") | AB38: =IF(S38="Paying",M38,"") | AC38: =IF(S38="Completed",M38,"") -> 120
A39: 46266 | B39: 岚桥加淡水200吨 | D39: CTM | G39: 1400 | H39: 1 | I39: =G39*H39 -> 1400 | J39: 6000001 | K39: =A39 -> 46266 | L39: =I39 -> 1400 | M39: =L39 -> 1400 | S39: Completed | X39: =IF(S39="Accrual",M39,"") | Y39: =IF(S39="Receiving",M39,"") | Z39: =IF(S39="Received",M39,"") | AA39: =IF(S39="Approved",M39,"") | AB39: =IF(S39="Paying",M39,"") | AC39: =IF(S39="Completed",M39,"") -> 1400
A40: 46266 | B40: 海事海关系统更改费用 | D40: CTM | G40: 375 | H40: 1 | I40: =G40*H40 -> 375 | J40: 6000011 | K40: =A40 -> 46266 | L40: =I40 -> 375 | M40: =L40 -> 375 | S40: Completed | X40: =IF(S40="Accrual",M40,"") | Y40: =IF(S40="Receiving",M40,"") | Z40: =IF(S40="Received",M40,"") | AA40: =IF(S40="Approved",M40,"") | AB40: =IF(S40="Paying",M40,"") | AC40: =IF(S40="Completed",M40,"") -> 375
A41: 46265 | B41: 董事长基金-周总 | G41: 10000 | H41: 1 | I41: =G41*H41 -> 10000 | J41: 6000016 | L41: =I41 -> 10000 | M41: =L41 -> 10000 | S41: Completed | X41: =IF(S41="Accrual",M41,"") | Y41: =IF(S41="Receiving",M41,"") | Z41: =IF(S41="Received",M41,"") | AA41: =IF(S41="Approved",M41,"") | AB41: =IF(S41="Paying",M41,"") | AC41: =IF(S41="Completed",M41,"") -> 10000
A42: 46265 | B42: 8月份客餐费用支出 | D42: CTM | G42: 662 | H42: 1 | I42: =G42*H42 -> 662 | J42: 1000002 | L42: =I42 -> 662 | M42: =L42 -> 662 | S42: Completed | W42: =IF(S42="Accrual",I42,"") | X42: =IF(S42="Accrual",M42,"") | Y42: =IF(S42="Receiving",M42,"") | Z42: =IF(S42="Received",M42,"") | AA42: =IF(S42="Approved",M42,"") | AB42: =IF(S42="Paying",M42,"") | AC42: =IF(S42="Completed",M42,"") -> 662
A43: 46265 | B43: 8月份全船伙食费支出 | D43: CTM | G43: 5400 | H43: 1 | I43: =G43*H43 -> 5400 | J43: 1000002 | L43: =I43 -> 5400 | M43: =L43 -> 5400 | S43: Completed | W43: =IF(S43="Accrual",I43,"") | X43: =IF(S43="Accrual",M43,"") | Y43: =IF(S43="Receiving",M43,"") | Z43: =IF(S43="Received",M43,"") | AA43: =IF(S43="Approved",M43,"") | AB43: =IF(S43="Paying",M43,"") | AC43: =IF(S43="Completed",M43,"") -> 5400
A44: 46262 | B44: 化学品 | C44: EPILT26003 | D44: DanTecs (HK) Marine Solutions Limited | E44: PILET26003 | G44: 2260.32 | H44: 1 | I44: 2260.32 | J44: 2000009 | L44: 2260.32 | M44: 2842.32 | S44: Received | Z44: =IF(S44="Received",M44,"") -> 2842.32
A45: 46262 | B45: 岚桥采购油漆 | C45: DPILT26006 | D45: 钧源船舶服务有限公司 | E45: PILDT26006 | G45: 7015.75 | H45: 1 | I45: =G45*H45 -> 7015.75 | J45: 2000004 | L45: =I45 -> 7015.75 | M45: 4271.4 | Q45: 46265 | R45: 46296 | S45: Completed | T45: 20 | X45: =IF(S45="Accrual",M45,"") | Y45: =IF(S45="Receiving",M45,"") | Z45: =IF(S45="Received",M45,"") | AA45: =IF(S45="Approved",M45,"") | AB45: =IF(S45="Paying",M45,"") | AC45: =IF(S45="Completed",M45,"") -> 4271.4
A46: 46262 | B46: 文具物料 | C46: DPILT26001 | D46: DanTecs (HK) Marine Solutions Limited | E46: PILDT26001 | G46: 923.53 | H46: 1 | I46: =G46*H46 -> 923.53 | J46: 2000007 | L46: =I46 -> 923.53 | M46: =L46 -> 923.53 | Q46: 46283 | R46: 46313 | S46: Received | X46: =IF(S46="Accrual",M46,"") | Y46: =IF(S46="Receiving",M46,"") | Z46: =IF(S46="Received",M46,"") -> 923.53 | AA46: =IF(S46="Approved",M46,"") | AB46: =IF(S46="Paying",M46,"") | AC46: =IF(S46="Completed",M46,"")
A47: 46262 | B47: 甲板物料-2通用物料 | C47: DPILT26002-2 | D47: DanTecs (HK) Marine Solutions Limited | E47: PILDT26002-2 | G47: 2832.54 | H47: 1 | I47: =G47*H47 -> 2832.54 | J47: 2000007 | L47: =I47 -> 2832.54 | M47: 3116.88 | Q47: 46283 | R47: 46313 | S47: Received | X47: =IF(S47="Accrual",M47,"") | Y47: =IF(S47="Receiving",M47,"") | Z47: =IF(S47="Received",M47,"") -> 3116.88 | AA47: =IF(S47="Approved",M47,"") | AB47: =IF(S47="Paying",M47,"") | AC47: =IF(S47="Completed",M47,"")
A48: 46262 | B48: 甲板物料-1缆绳检测仪+耳机 | C48: DPILT26002-1 | D48: DanTecs (HK) Marine Solutions Limited | E48: PILDT26002-1 | G48: 2745 | H48: 1 | I48: =G48*H48 -> 2745 | J48: 2000007 | L48: =I48 -> 2745 | M48: 4000 | Q48: 46283 | R48: 46313 | S48: Received | X48: =IF(S48="Accrual",M48,"") | Y48: =IF(S48="Receiving",M48,"") | Z48: =IF(S48="Received",M48,"") -> 4000 | AA48: =IF(S48="Approved",M48,"") | AB48: =IF(S48="Paying",M48,"") | AC48: =IF(S48="Completed",M48,"")
A49: 46262 | B49: 救生和消防物料 | C49: DPILT26003 | D49: DanTecs (HK) Marine Solutions Limited | E49: PILDT26003 | G49: 1205.28 | H49: 1 | I49: =G49*H49 -> 1205.28 | J49: 2000006 | L49: =I49 -> 1205.28 | M49: =L49 -> 1205.28 | Q49: 46283 | R49: 46313 | S49: Received | X49: =IF(S49="Accrual",M49,"") | Y49: =IF(S49="Receiving",M49,"") | Z49: =IF(S49="Received",M49,"") -> 1205.28 | AA49: =IF(S49="Approved",M49,"") | AB49: =IF(S49="Paying",M49,"") | AC49: =IF(S49="Completed",M49,"")
A50: 46262 | B50: 生活物料 | C50: DPILT26004 | D50: DanTecs (HK) Marine Solutions Limited | E50: PILDT26004 | G50: 1620.42 | H50: 1 | I50: =G50*H50 -> 1620.42 | J50: 2000012 | L50: =I50 -> 1620.42 | M50: =L50 -> 1620.42 | Q50: 46283 | R50: 46313 | S50: Received | X50: =IF(S50="Accrual",M50,"") | Y50: =IF(S50="Receiving",M50,"") | Z50: =IF(S50="Received",M50,"") -> 1620.42 | AA50: =IF(S50="Approved",M50,"") | AB50: =IF(S50="Paying",M50,"") | AC50: =IF(S50="Completed",M50,"")
A51: 46262 | B51: 药品及医疗器材 | C51: DPILT26005 | D51: DanTecs (HK) Marine Solutions Limited | E51: PILDT26005 | G51: 365.27 | H51: 1 | I51: =G51*H51 -> 365.27 | J51: 2000001 | L51: =I51 -> 365.27 | M51: =L51 -> 365.27 | Q51: 46283 | R51: 46313 | S51: Received | X51: =IF(S51="Accrual",M51,"") | Y51: =IF(S51="Receiving",M51,"") | Z51: =IF(S51="Received",M51,"") -> 365.27 | AA51: =IF(S51="Approved",M51,"") | AB51: =IF(S51="Paying",M51,"") | AC51: =IF(S51="Completed",M51,"")
A52: 46262 | B52: 主机缸盖 | C52: EPILP26001 | D52: DanTecs (HK) Marine Solutions Limited | E52: PILEP26001 | G52: 300 | H52: 1 | I52: 300 | J52: 3000007 | L52: =I52 -> 300 | M52: =L52 -> 300 | Q52: 46283 | R52: 46313 | S52: Received | X52: =IF(S52="Accrual",M52,"") | Y52: =IF(S52="Receiving",M52,"") | Z52: =IF(S52="Received",M52,"") -> 300 | AA52: =IF(S52="Approved",M52,"") | AB52: =IF(S52="Paying",M52,"") | AC52: =IF(S52="Completed",M52,"")
A53: 46262 | B53: 主机缸套 | C53: EPILP26002 | D53: ZHOUSHAN HAISHAN MARINE SERVICE CO., LIMITED | E53: PILEP26002 | G53: 16 | H53: 1 | I53: =G53*H53 -> 16 | J53: 3000007 | L53: =I53 -> 16 | M53: =L53 -> 16 | S53: Received | X53: =IF(S53="Accrual",M53,"") | Y53: =IF(S53="Receiving",M53,"") | Z53: =IF(S53="Received",M53,"") -> 16 | AA53: =IF(S53="Approved",M53,"") | AB53: =IF(S53="Paying",M53,"") | AC53: =IF(S53="Completed",M53,"")
A54: 46262 | B54: 主机燃油阀 | C54: EPILP26003 | D54: ZHOUSHAN HAISHAN MARINE SERVICE CO., LIMITED | E54: PILEP26003 | G54: 821.22 | H54: 1 | I54: =G54*H54 -> 821.22 | J54: 3000007 | L54: =I54 -> 821.22 | M54: =L54 -> 821.22 | S54: Received | X54: =IF(S54="Accrual",M54,"") | Y54: =IF(S54="Receiving",M54,"") | Z54: =IF(S54="Received",M54,"") -> 821.22 | AA54: =IF(S54="Approved",M54,"") | AB54: =IF(S54="Paying",M54,"") | AC54: =IF(S54="Completed",M54,"")
A55: 46262 | B55: 主机填料涵 | C55: EPILP26004 | D55: ZHOUSHAN HAISHAN MARINE SERVICE CO., LIMITED | E55: PILEP26004 | G55: 31.56 | H55: 1 | I55: =G55*H55 -> 31.56 | J55: 3000007 | L55: =I55 -> 31.56 | M55: =L55 -> 31.56 | S55: Received | X55: =IF(S55="Accrual",M55,"") | Y55: =IF(S55="Receiving",M55,"") | Z55: =IF(S55="Received",M55,"") -> 31.56 | AA55: =IF(S55="Approved",M55,"") | AB55: =IF(S55="Paying",M55,"") | AC55: =IF(S55="Completed",M55,"")
A56: 46262 | B56: 主机震动缓冲器 | C56: EPILP26005 | D56: DanTecs (HK) Marine Solutions Limited | E56: PILEP26005 | G56: 35 | H56: 1 | I56: 35 | J56: 3000007 | L56: =I56 -> 35 | M56: =L56 -> 35 | Q56: 46283 | R56: 46313 | S56: Received | X56: =IF(S56="Accrual",M56,"") | Y56: =IF(S56="Receiving",M56,"") | Z56: =IF(S56="Received",M56,"") -> 35 | AA56: =IF(S56="Approved",M56,"") | AB56: =IF(S56="Paying",M56,"") | AC56: =IF(S56="Completed",M56,"")
A57: 46262 | B57: 主机排气阀 | C57: EPILP26006 | D57: DanTecs (HK) Marine Solutions Limited | E57: PILEP26006 | G57: 194.68 | H57: 1 | I57: 194.68 | J57: 3000007 | L57: 194.68 | M57: =L57 -> 194.68 | Q57: 46283 | R57: 46313 | S57: Received | X57: =IF(S57="Accrual",M57,"") | Y57: =IF(S57="Receiving",M57,"") | Z57: =IF(S57="Received",M57,"") -> 194.68 | AA57: =IF(S57="Approved",M57,"") | AB57: =IF(S57="Paying",M57,"") | AC57: =IF(S57="Completed",M57,"")
A58: 46262 | B58: 主机供油单元 | C58: EPILP26007 | D58: DanTecs (HK) Marine Solutions Limited | E58: PILEP26007 | G58: 2523 | H58: 1 | I58: =G58*H58 -> 2523 | J58: 3000007 | L58: 2523 | M58: =L58 -> 2523 | Q58: 46283 | R58: 46313 | S58: Received | X58: =IF(S58="Accrual",M58,"") | Y58: =IF(S58="Receiving",M58,"") | Z58: =IF(S58="Received",M58,"") -> 2523 | AA58: =IF(S58="Approved",M58,"") | AB58: =IF(S58="Paying",M58,"") | AC58: =IF(S58="Completed",M58,"")
A59: 46262 | B59: 滑油分油机 | C59: EPILP26008 | D59: DanTecs (HK) Marine Solutions Limited | E59: PILEP26008 | G59: 332 | H59: 1 | I59: 332 | J59: 3000012 | L59: 332 | M59: =L59 -> 332 | Q59: 46283 | R59: 46313 | S59: Received | X59: =IF(S59="Accrual",M59,"") | Y59: =IF(S59="Receiving",M59,"") | Z59: =IF(S59="Received",M59,"") -> 332 | AA59: =IF(S59="Approved",M59,"") | AB59: =IF(S59="Paying",M59,"") | AC59: =IF(S59="Completed",M59,"")
A60: 46262 | B60: 发电机 | C60: EPILP26009 | D60: RMS MARINE SERVICE COMPANY LTD | E60: PILEP26009 | G60: 2032.5 | H60: 1 | I60: =G60*H60 -> 2032.5 | J60: 3000008 | L60: =I60 -> 2032.5 | M60: =L60 -> 2032.5 | S60: Accrual | X60: =IF(S60="Accrual",M60,"") -> 2032.5 | Y60: =IF(S60="Receiving",M60,"") | Z60: =IF(S60="Received",M60,"") | AA60: =IF(S60="Approved",M60,"") | AB60: =IF(S60="Paying",M60,"") | AC60: =IF(S60="Completed",M60,"")
A61: 46262 | B61: 发电机增压器 | C61: EPILP26010 | D61: DanTecs (HK) Marine Solutions Limited | E61: PILEP26010 | G61: 996 | H61: 1 | I61: 996 | J61: 3000008 | L61: 996 | M61: =L61 -> 996 | Q61: 46283 | R61: 46313 | S61: Received | X61: =IF(S61="Accrual",M61,"") | Y61: =IF(S61="Receiving",M61,"") | Z61: =IF(S61="Received",M61,"") -> 996 | AA61: =IF(S61="Approved",M61,"") | AB61: =IF(S61="Paying",M61,"") | AC61: =IF(S61="Completed",M61,"")
A62: 46262 | B62: 主空压机 | C62: EPILP26011 | D62: RMS MARINE SERVICE COMPANY LTD | E62: PILEP26011 | G62: 136.36 | H62: 1 | I62: =G62*H62 -> 136.36 | J62: 3000012 | L62: =I62 -> 136.36 | M62: =L62 -> 136.36 | S62: Accrual | X62: =IF(S62="Accrual",M62,"") -> 136.36 | Y62: =IF(S62="Receiving",M62,"") | Z62: =IF(S62="Received",M62,"") | AA62: =IF(S62="Approved",M62,"") | AB62: =IF(S62="Paying",M62,"") | AC62: =IF(S62="Completed",M62,"")
A63: 46262 | B63: 燃油分油机 | C63: EPILP26012 | D63: DanTecs (HK) Marine Solutions Limited | E63: PILEP26012 | G63: 937 | H63: 1 | I63: 937 | J63: 3000012 | L63: 937 | M63: =L63 -> 937 | Q63: 46283 | R63: 46313 | S63: Received | X63: =IF(S63="Accrual",M63,"") | Y63: =IF(S63="Receiving",M63,"") | Z63: =IF(S63="Received",M63,"") -> 937 | AA63: =IF(S63="Approved",M63,"") | AB63: =IF(S63="Paying",M63,"") | AC63: =IF(S63="Completed",M63,"")
A64: 46262 | B64: 造水机 | C64: EPILP26013 | D64: RMS MARINE SERVICE COMPANY LTD | E64: PILEP26013 | G64: 904.33 | H64: 1 | I64: =G64*H64 -> 904.33 | J64: 3000012 | L64: =I64 -> 904.33 | M64: =L64 -> 904.33 | S64: Accrual | X64: =IF(S64="Accrual",M64,"") -> 904.33 | Y64: =IF(S64="Receiving",M64,"") | Z64: =IF(S64="Received",M64,"") | AA64: =IF(S64="Approved",M64,"") | AB64: =IF(S64="Paying",M64,"") | AC64: =IF(S64="Completed",M64,"")
A65: 46262 | B65: 汽笛+运费 | C65: EPILP26015 | D65: ZHOUSHAN HAISHAN MARINE SERVICE CO., LIMITED | E65: PILEP26015 | G65: 1127.37 | H65: 1 | I65: =G65*H65 -> 1127.37 | J65: 3000006 | L65: =I65 -> 1127.37 | M65: =L65+100 -> 1227.37 | S65: Received | X65: =IF(S65="Accrual",M65,"") | Y65: =IF(S65="Receiving",M65,"") | Z65: =IF(S65="Received",M65,"") -> 1227.37 | AA65: =IF(S65="Approved",M65,"") | AB65: =IF(S65="Paying",M65,"") | AC65: =IF(S65="Completed",M65,"")
A66: 46262 | B66: 压载水处理系统 | C66: EPILP26017 | D66: DanTecs (HK) Marine Solutions Limited | E66: PILEP26017 | G66: 1741.1 | H66: 1 | I66: 1741.1 | J66: 3000010 | L66: 1741.1 | M66: 1837.47 | Q66: 46283 | R66: 46313 | S66: Received | X66: =IF(S66="Accrual",M66,"") | Y66: =IF(S66="Receiving",M66,"") | Z66: =IF(S66="Received",M66,"") -> 1837.47 | AA66: =IF(S66="Approved",M66,"") | AB66: =IF(S66="Paying",M66,"") | AC66: =IF(S66="Completed",M66,"")
A67: 46262 | B67: 甲板克令吊 | C67: EPILP26019 | D67: DanTecs (HK) Marine Solutions Limited | E67: PILEP26019 | G67: 3206.79 | H67: 1 | I67: 3206.79 | J67: 3000004 | L67: 3206.79 | M67: 1620.58 | Q67: 46283 | R67: 46313 | S67: Received | X67: =IF(S67="Accrual",M67,"") | Y67: =IF(S67="Receiving",M67,"") | Z67: =IF(S67="Received",M67,"") -> 1620.58 | AA67: =IF(S67="Approved",M67,"") | AB67: =IF(S67="Paying",M67,"") | AC67: =IF(S67="Completed",M67,"")
A68: 46262 | B68: 生活污水处理装置 | C68: EPILP26020 | D68: DanTecs (HK) Marine Solutions Limited | E68: PILEP26020 | G68: 700 | H68: 1 | I68: 700 | J68: 3000012 | L68: =I68 -> 700 | M68: =L68 -> 700 | Q68: 46283 | R68: 46313 | S68: Received | X68: =IF(S68="Accrual",M68,"") | Y68: =IF(S68="Receiving",M68,"") | Z68: =IF(S68="Received",M68,"") -> 700 | AA68: =IF(S68="Approved",M68,"") | AB68: =IF(S68="Paying",M68,"") | AC68: =IF(S68="Completed",M68,"")
A69: 46262 | B69: 压载泵 | C69: EPILP26021 | D69: DanTecs (HK) Marine Solutions Limited | E69: PILEP26021 | G69: 155 | H69: 1 | I69: 155 | J69: 3000004 | L69: =I69 -> 155 | M69: =L69 -> 155 | Q69: 46283 | R69: 46313 | S69: Received | X69: =IF(S69="Accrual",M69,"") | Y69: =IF(S69="Receiving",M69,"") | Z69: =IF(S69="Received",M69,"") -> 155 | AA69: =IF(S69="Approved",M69,"") | AB69: =IF(S69="Paying",M69,"") | AC69: =IF(S69="Completed",M69,"")
A70: 46262 | B70: 消防泵备件(Fire & G/S RVP160S SHINKO) | C70: EPILP26022 | D70: ZHOUSHAN HAISHAN MARINE SERVICE CO., LIMITED | E70: PILEP26022 | G70: 485 | H70: 1 | I70: =G70*H70 -> 485 | J70: 3000003 | L70: =I70 -> 485 | M70: =L70 -> 485 | S70: Received | X70: =IF(S70="Accrual",M70,"") | Y70: =IF(S70="Receiving",M70,"") | Z70: =IF(S70="Received",M70,"") -> 485 | AA70: =IF(S70="Approved",M70,"") | AB70: =IF(S70="Paying",M70,"") | AC70: =IF(S70="Completed",M70,"")
A71: 46262 | B71: 消防泵备件(Fire & G/S RVP160S SHINKO) | C71: EPILP26023 | D71: DanTecs (HK) Marine Solutions Limited | E71: PILEP26023 | G71: 350 | H71: 1 | I71: 350 | J71: 3000012 | L71: =I71 -> 350 | M71: =L71 -> 350 | Q71: 46283 | R71: 46313 | S71: Received | X71: =IF(S71="Accrual",M71,"") | Y71: =IF(S71="Receiving",M71,"") | Z71: =IF(S71="Received",M71,"") -> 350 | AA71: =IF(S71="Approved",M71,"") | AB71: =IF(S71="Paying",M71,"") | AC71: =IF(S71="Completed",M71,"")
A72: 46262 | B72: 液压块 | C72: EPILP26024 | D72: DanTecs (HK) Marine Solutions Limited | E72: PILEP26024 | G72: 653 | H72: 1 | I72: =G72*H72 -> 653 | J72: 3000004 | L72: =I72 -> 653 | M72: =L72 -> 653 | Q72: 46283 | R72: 46313 | S72: Received | X72: =IF(S72="Accrual",M72,"") | Y72: =IF(S72="Receiving",M72,"") | Z72: =IF(S72="Received",M72,"") -> 653 | AA72: =IF(S72="Approved",M72,"") | AB72: =IF(S72="Paying",M72,"") | AC72: =IF(S72="Completed",M72,"")
A73: 46262 | B73: 2号滑油分油机马达 | C73: EPILP26025 | D73: DanTecs (HK) Marine Solutions Limited | E73: PILEP26025 | G73: 285 | H73: 1 | I73: =G73*H73 -> 285 | J73: 3000012 | L73: =I73 -> 285 | M73: =L73 -> 285 | Q73: 46283 | R73: 46313 | S73: Received | X73: =IF(S73="Accrual",M73,"") | Y73: =IF(S73="Receiving",M73,"") | Z73: =IF(S73="Received",M73,"") -> 285 | AA73: =IF(S73="Approved",M73,"") | AB73: =IF(S73="Paying",M73,"") | AC73: =IF(S73="Completed",M73,"")
A74: 46262 | B74: 机舱半年 通用物料申请单 | C74: EPILT26001 | D74: DanTecs (HK) Marine Solutions Limited | E74: PILET26001 | G74: 6971.22 | H74: 1 | I74: =G74*H74 -> 6971.22 | J74: 2000011 | L74: =I74 -> 6971.22 | M74: 7438.57 | Q74: 46283 | R74: 46313 | S74: Received | X74: =IF(S74="Accrual",M74,"") | Y74: =IF(S74="Receiving",M74,"") | Z74: =IF(S74="Received",M74,"") -> 7438.57 | AA74: =IF(S74="Approved",M74,"") | AB74: =IF(S74="Paying",M74,"") | AC74: =IF(S74="Completed",M74,"")
A75: 46262 | B75: 救生消防年检 | D75: ZHOUSHAN HAISHAN MARINE SERVICE CO., LIMITED | G75: 3794.85 | H75: 1 | I75: =G75*H75 -> 3794.85 | J75: 4000011 | L75: =I75 -> 3794.85 | M75: =L75 -> 3794.85 | S75: Accrual | X75: =IF(S75="Accrual",M75,"") -> 3794.85 | Y75: =IF(S75="Receiving",M75,"") | Z75: =IF(S75="Received",M75,"") | AA75: =IF(S75="Approved",M75,"") | AB75: =IF(S75="Paying",M75,"") | AC75: =IF(S75="Completed",M75,"")
A76: 46262 | B76: 通导设备修理 | D76: Fuzhou Changxin Electronic Co.,Ltd | G76: 17900 | H76: 0.149 | I76: =G76*H76 -> 2667.1 | J76: 4000010 | L76: =I76 -> 2667.1 | M76: =22000*0.149 -> 3278 | S76: Accrual | X76: =IF(S76="Accrual",M76,"") -> 3278 | Y76: =IF(S76="Receiving",M76,"") | Z76: =IF(S76="Received",M76,"") | AA76: =IF(S76="Approved",M76,"") | AB76: =IF(S76="Paying",M76,"") | AC76: =IF(S76="Completed",M76,"")
A77: 46261 | B77: 冰机压缩机一台—周总支付 | D77: GORDON MARINE REFRIGERATION CO.,LTD | G77: 12500 | H77: 0.148148 | I77: =G77*H77 -> 1851.85 | J77: 3000007 | L77: =I77 -> 1851.85 | M77: 1851.85 | X77: =IF(S77="Accrual",M77,"") | Y77: =IF(S77="Receiving",M77,"") | Z77: =IF(S77="Received",M77,"") | AA77: =IF(S77="Approved",M77,"") | AB77: =IF(S77="Paying",M77,"") | AC77: =IF(S77="Completed",M77,"")
A78: 46259 | B78: 付款没付成功，银行扣款手续费USD50 | J78: 6000016 | L78: 50 | S78: Completed | T78: 50 | X78: =IF(S78="Accrual",M78,"") | Y78: =IF(S78="Receiving",M78,"") | Z78: =IF(S78="Received",M78,"") | AA78: =IF(S78="Approved",M78,"") | AB78: =IF(S78="Paying",M78,"") | AC78: =IF(S78="Completed",M78,"") -> 0
A79: 46257 | B79: HOMONHON水手张善钧购药支出 | D79: CTM | G79: 733 | H79: 1 | I79: =G79*H79 -> 733 | J79: 1000006 | L79: =I79 -> 733 | M79: =L79 -> 733 | S79: Completed | X79: =IF(S79="Accrual",M79,"") | Y79: =IF(S79="Receiving",M79,"") | Z79: =IF(S79="Received",M79,"") | AA79: =IF(S79="Approved",M79,"") | AB79: =IF(S79="Paying",M79,"") | AC79: =IF(S79="Completed",M79,"") -> 733
A80: 46252 | B80: 气瓶押金 | D80: Wilhelmsen Ships Service AS | E80: S10329491 | G80: 8121.24 | H80: 1 | I80: =G80*H80 -> 8121.24 | J80: 6000016 | L80: =I80 -> 8121.24 | M80: =L80 -> 8121.24 | S80: Completed | T80: 32.48 | X80: =IF(S80="Accrual",M80,"") | Y80: =IF(S80="Receiving",M80,"") | Z80: =IF(S80="Received",M80,"") | AA80: =IF(S80="Approved",M80,"") | AB80: =IF(S80="Paying",M80,"") | AC80: =IF(S80="Completed",M80,"") -> 8121.24
A81: 46251 | B81: V2605扫洗舱劳务费 | D81: CTM | G81: 1125 | H81: 1 | I81: =G81*H81 -> 1125 | J81: 9000001 | L81: =I81 -> 1125 | M81: =L81 -> 1125 | S81: Completed | X81: =IF(S81="Accrual",M81,"") | Y81: =IF(S81="Receiving",M81,"") | Z81: =IF(S81="Received",M81,"") | AA81: =IF(S81="Approved",M81,"") | AB81: =IF(S81="Paying",M81,"") | AC81: =IF(S81="Completed",M81,"") -> 1125
A82: 46248 | B82: 董事长基金-周总 | G82: 10000 | H82: 1 | I82: =G82*H82 -> 10000 | J82: 6000016 | L82: =I82 -> 10000 | M82: =L82 -> 10000 | S82: Completed | X82: =IF(S82="Accrual",M82,"") | Y82: =IF(S82="Receiving",M82,"") | Z82: =IF(S82="Received",M82,"") | AA82: =IF(S82="Approved",M82,"") | AB82: =IF(S82="Paying",M82,"") | AC82: =IF(S82="Completed",M82,"") -> 10000
A83: 46247 | B83: Water ingress detection 备件 - 潜水式压力变送器 LMK457 | D83: OCEAN FLEET (HK) SPARE PARTS CO., LIMITED | E83: PILM26052101 | G83: 475 | H83: 1 | I83: =G83*H83 -> 475 | J83: 3000012 | L83: =I83 -> 475 | M83: =L83 -> 475 | Q83: 46247 | R83: 46277 | X83: =IF(S83="Accrual",M83,"") | Y83: =IF(S83="Receiving",M83,"") | Z83: =IF(S83="Received",M83,"") | AA83: =IF(S83="Approved",M83,"") | AB83: =IF(S83="Paying",M83,"") | AC83: =IF(S83="Completed",M83,"")
A84: 46247 | B84: BMA Flag Statutory Record Book | D84: DANTECS (HK) MARINE SOLUTIONS LIMITED | G84: 185.76 | H84: 1 | I84: =G84*H84 -> 185.76 | J84: 2000007 | L84: =I84 -> 185.76 | M84: =L84 -> 185.76 | Q84: 46247 | R84: 46277 | S84: Received | X84: =IF(S84="Accrual",M84,"") | Y84: =IF(S84="Receiving",M84,"") | Z84: =IF(S84="Received",M84,"") -> 185.76 | AA84: =IF(S84="Approved",M84,"") | AB84: =IF(S84="Paying",M84,"") | AC84: =IF(S84="Completed",M84,"")
A85: 46241 | B85: Flag Change Radio Survey Charge | D85: Fuzhou Changxin Electronic Co.,Ltd | G85: 10225 | H85: 1 | I85: =G85*H85 -> 10225 | J85: 9000000 | L85: =I85 -> 10225 | M85: =L85 -> 10225 | Q85: 46241 | R85: 46248 | S85: Completed | T85: 40.9 | X85: =IF(S85="Accrual",M85,"") | Y85: =IF(S85="Receiving",M85,"") | Z85: =IF(S85="Received",M85,"") | AA85: =IF(S85="Approved",M85,"") | AB85: =IF(S85="Paying",M85,"") | AC85: =IF(S85="Completed",M85,"") -> 10225
A86: 46238 | B86: 菲律宾 CTM 代理代办服务费 | D86: TOP MARINE LIMITED | G86: 2000 | H86: 1 | I86: =G86*H86 -> 2000 | J86: 6000007 | L86: =I86 -> 2000 | M86: =L86 -> 2000 | S86: Completed | T86: 20 | X86: =IF(S86="Accrual",M86,"") | Y86: =IF(S86="Receiving",M86,"") | Z86: =IF(S86="Received",M86,"") | AA86: =IF(S86="Approved",M86,"") | AB86: =IF(S86="Paying",M86,"") | AC86: =IF(S86="Completed",M86,"") -> 2000
A87: 46238 | B87: 代理给船长5万备用金 | D87: CTM | G87: 50000 | H87: 1 | I87: 50000 | J87: 6000007 | L87: 50000 | M87: 50000 | T87: 200 | X87: =IF(S87="Accrual",M87,"") | Y87: =IF(S87="Receiving",M87,"") | Z87: =IF(S87="Received",M87,"") | AA87: =IF(S87="Approved",M87,"") | AB87: =IF(S87="Paying",M87,"") | AC87: =IF(S87="Completed",M87,"")
A88: 46238 | B88: BMA Flag register Fee-Owner Paid | D88: OCEAN QUEEN SHIPPING CO.,LTD. | G88: 10769.64 | H88: 1 | I88: =G88*H88 -> 10769.64 | J88: 9000000 | L88: =I88 -> 10769.64 | M88: =L88 -> 10769.64 | X88: =IF(S88="Accrual",M88,"") | Y88: =IF(S88="Receiving",M88,"") | Z88: =IF(S88="Received",M88,"") | AA88: =IF(S88="Approved",M88,"") | AB88: =IF(S88="Paying",M88,"") | AC88: =IF(S88="Completed",M88,"")
A89: 46237 | B89: Vizada 通信订阅费（接船） | D89: TELEOCEAN INC | G89: 150 | H89: 1 | I89: =G89*H89 -> 150 | J89: 6000017 | L89: =I89 -> 150 | M89: =L89 -> 150 | S89: Completed | W89: 46248 | X89: =IF(S89="Accrual",M89,"") | Y89: =IF(S89="Receiving",M89,"") | Z89: =IF(S89="Received",M89,"") | AA89: =IF(S89="Approved",M89,"") | AB89: =IF(S89="Paying",M89,"") | AC89: =IF(S89="Completed",M89,"") -> 150
A90: 46238 | B90: 改船籍港特殊劳务费200美元 | D90: CTM | G90: 200 | H90: 1 | I90: =G90*H90 -> 200 | J90: 9990001 | K90: 46238 | L90: =I90 -> 200 | M90: =L90 -> 200 | S90: Completed | W90: =IF(S90="Accrual",I90,"") | X90: =IF(S90="Accrual",M90,"") | Y90: =IF(S90="Receiving",M90,"") | Z90: =IF(S90="Received",M90,"") | AA90: =IF(S90="Approved",M90,"") | AB90: =IF(S90="Paying",M90,"") | AC90: =IF(S90="Completed",M90,"") -> 200
A91: 46237 | B91: 原船管欠船员7月份伙食费支出 | D91: CTM | G91: 1544 | H91: 1 | I91: =G91*H91 -> 1544 | J91: 1000002 | K91: 46237 | L91: =I91 -> 1544 | M91: =L91 -> 1544 | S91: Completed | W91: =IF(S91="Accrual",I91,"") | X91: =IF(S91="Accrual",M91,"") | Y91: =IF(S91="Receiving",M91,"") | Z91: =IF(S91="Received",M91,"") | AA91: =IF(S91="Approved",M91,"") | AB91: =IF(S91="Paying",M91,"") | AC91: =IF(S91="Completed",M91,"") -> 1544
A92: 46235 | B92: LR船检两名外锚地登离船代理费用支出 | D92: CTM | F92: =I13+I19+I26+I33+I34+I37+I41+I77+I82 -> 99827.432 | G92: 9230 | H92: 1 | I92: =G92*H92 -> 9230 | J92: 9990001 | K92: 46236 | L92: =I92 -> 9230 | M92: =L92 -> 9230 | S92: Completed | W92: =IF(S92="Accrual",I92,"") | X92: =IF(S92="Accrual",M92,"") | Y92: =IF(S92="Receiving",M92,"") | Z92: =IF(S92="Received",M92,"") | AA92: =IF(S92="Approved",M92,"") | AB92: =IF(S92="Paying",M92,"") | AC92: =IF(S92="Completed",M92,"") -> 9230
A93: 46234 | B93: GMDSS年检共工程师登离船代理费用支出 | D93: CTM | G93: 2150 | H93: 1 | I93: =G93*H93 -> 2150 | J93: 9990001 | K93: 46235 | L93: =I93 -> 2150 | M93: =L93 -> 2150 | S93: Completed | W93: =IF(S93="Accrual",I93,"") | X93: =IF(S93="Accrual",M93,"") | Y93: =IF(S93="Receiving",M93,"") | Z93: =IF(S93="Received",M93,"") | AA93: =IF(S93="Approved",M93,"") | AB93: =IF(S93="Paying",M93,"") | AC93: =IF(S93="Completed",M93,"") -> 2150
A94: 46234 | B94: AAIC 接船相关费用（年费+LOG+旗国激活+押金） | D94: TELEOCEAN INC | G94: 2080 | H94: 1 | I94: 2080 | J94: 6000014 | L94: =I94 -> 2080 | M94: =L94 -> 2080 | Q94: 46234 | R94: 46249 | S94: Completed | T94: 20 | X94: =IF(S94="Accrual",M94,"") | Y94: =IF(S94="Receiving",M94,"") | Z94: =IF(S94="Received",M94,"") | AA94: =IF(S94="Approved",M94,"") | AB94: =IF(S94="Paying",M94,"") | AC94: =IF(S94="Completed",M94,"") -> 2080
A95: 46234 | B95: LISCR Deletion Overtime Cost-Owner Paid | D95: LISCR Flag | G95: 1435 | H95: 1 | I95: =G95*H95 -> 1435 | J95: 6000014 | L95: =I95 -> 1435 | M95: =L95 -> 1435 | W95: 46277 | X95: =IF(S95="Accrual",M95,"") | Y95: =IF(S95="Receiving",M95,"") | Z95: =IF(S95="Received",M95,"") | AA95: =IF(S95="Approved",M95,"") | AB95: =IF(S95="Paying",M95,"") | AC95: =IF(S95="Completed",M95,"")
A96: 46234 | B96: GRESIK加淡水100吨 | D96: CTM | G96: 1350 | H96: 1 | I96: =G96*H96 -> 1350 | J96: 6000001 | L96: =I96 -> 1350 | M96: =L96 -> 1350 | S96: Completed | X96: =IF(S96="Accrual",M96,"") | Y96: =IF(S96="Receiving",M96,"") | Z96: =IF(S96="Received",M96,"") | AA96: =IF(S96="Approved",M96,"") | AB96: =IF(S96="Paying",M96,"") | AC96: =IF(S96="Completed",M96,"") -> 1350
A97: 46233 | B97: 制作新船章两枚 | D97: CTM | G97: 25 | H97: 1 | I97: =G97*H97 -> 25 | J97: 6000013 | K97: 46234 | L97: =I97 -> 25 | M97: =L97 -> 25 | S97: Completed | X97: =IF(S97="Accrual",M97,"") | Y97: =IF(S97="Receiving",M97,"") | Z97: =IF(S97="Received",M97,"") | AA97: =IF(S97="Approved",M97,"") | AB97: =IF(S97="Paying",M97,"") | AC97: =IF(S97="Completed",M97,"") -> 25
A98: 46232 | B98: BMA Pre-inspection Fee-Owner Paid | D98: Intermaritime Group Services | G98: 6580 | H98: 1 | I98: =G98*H98 -> 6580 | J98: 9000000 | L98: =I98 -> 6580 | M98: =L98 -> 6580 | X98: =IF(S98="Accrual",M98,"") | Y98: =IF(S98="Receiving",M98,"") | Z98: =IF(S98="Received",M98,"") | AA98: =IF(S98="Approved",M98,"") | AB98: =IF(S98="Paying",M98,"") | AC98: =IF(S98="Completed",M98,"")
A99: 46231 | B99: 招待费—周琦支付 | G99: 441.18 | H99: 1 | I99: =G99*H99 -> 441.18 | J99: 6000002 | L99: =I99 -> 441.18 | M99: =L99 -> 441.18 | X99: =IF(S99="Accrual",M99,"") | Y99: =IF(S99="Receiving",M99,"") | Z99: =IF(S99="Received",M99,"") | AA99: =IF(S99="Approved",M99,"") | AB99: =IF(S99="Paying",M99,"") | AC99: =IF(S99="Completed",M99,"")
A100: 46233 | B100: CTM RMB100,000 hand carried onboard when tookover vessel≈14815美元 | D100: CTM | G100: 14815 | H100: 1 | I100: 14815 | J100: 6000007 | K100: 46233 | L100: 14815 | M100: 14815 | T100: 200 | X100: =IF(S100="Accrual",M100,"") | Y100: =IF(S100="Receiving",M100,"") | Z100: =IF(S100="Received",M100,"") | AA100: =IF(S100="Approved",M100,"") | AB100: =IF(S100="Paying",M100,"") | AC100: =IF(S100="Completed",M100,"")
...

Sheet CTM Expenses List
A1: 入账日期 | B1: 类型 | C1: Action | D1: Supplier | E1: PO Nos | F1: PO Current | G1: Rating | H1: PO Amount (USD) | I1: Account Code | J1: GRN/Date | K1: GRN Amount(USD) | L1: Invoice Amount(USD) | M1: Others | N1: Food | O1: Store | P1: Invoice Date | Q1: Due Date | R1: Payment Status | S1: Bank Charge | T1: Attachement | U1: Attachement | V1: Accrual | W1: Receiving | X1: Received | Y1: Approved | Z1: Paying | AA1: Completed
C2: Receiving | D2: Received | E2: Approved | F2: Paying | G2: Completed | H2: =SUM($H$3:H81) -> 29908 | K2: =SUM($K$3:K81) -> 29908 | L2: =SUM($L$3:L81) -> 29908 | M2: =SUM(M3:M121) -> 0 | N2: =SUM(N3:N121) -> 0 | O2: =SUM(O3:O121) -> 0 | S2: =SUM(S3:S29) -> 0 | T2: Invoices | U2: Credit Note | V2: =SUM($V$3:V81) -> 0 | W2: =SUM($W$3:W81) -> 0 | X2: =SUM(X3:X29) -> 0 | Y2: =SUM(Y3:Y29) -> 0 | Z2: =SUM(Z3:Z29) -> 0 | AA2: =SUM(AA3:AA29) -> 29908
V3: =IF(R3="Accrual",H3,"") | W3: =IF(R3="Receiving",K3,"") | X3: =IF(R3="Received",L3,"") | Y3: =IF(R3="Approved",L3,"") | Z3: =IF(R3="Paying",L3,"") | AA3: =IF(R3="Completed",L3,"")
A4: 46295 | B4: 9月份客餐费用支出 | C4: out | D4: CTM | F4: -249 | G4: 1 | H4: =F4*G4 -> -249 | I4: 6000002 | J4: =A4 -> 46295 | K4: =H4 -> -249 | L4: =K4 -> -249 | R4: Completed | T4: 9月份客餐费用支出249美元.pdf | V4: =IF(R4="Accrual",H4,"") | W4: =IF(R4="Receiving",K4,"") | X4: =IF(R4="Received",L4,"") | Y4: =IF(R4="Approved",L4,"") | Z4: =IF(R4="Paying",L4,"") | AA4: =IF(R4="Completed",L4,"") -> -249
A5: 46295 | B5: 9月份全船伙食费支出 | C5: out | D5: CTM | F5: -5592 | G5: 1 | H5: =F5*G5 -> -5592 | I5: 1000002 | J5: =A5 -> 46295 | K5: =H5 -> -5592 | L5: =K5 -> -5592 | R5: Completed | T5: 2026年9月份伙食费收据5592美元.pdf | V5: =IF(R5="Accrual",H5,"") | W5: =IF(R5="Receiving",K5,"") | X5: =IF(R5="Received",L5,"") | Y5: =IF(R5="Approved",L5,"") | Z5: =IF(R5="Paying",L5,"") | AA5: =IF(R5="Completed",L5,"") -> -5592
A6: 46286 | B6: 柯凯敏青岛就医及路费支出 | C6: out | D6: CTM | F6: -149 | G6: 1 | H6: =F6*G6 -> -149 | I6: 7000009 | J6: =A6 -> 46286 | K6: =H6 -> -149 | L6: =K6 -> -149 | R6: Completed | T6: 柯凯敏青岛就医及路费支出149美元.pdf | V6: =IF(R6="Accrual",H6,"") | W6: =IF(R6="Receiving",K6,"") | X6: =IF(R6="Received",L6,"") | Y6: =IF(R6="Approved",L6,"") | Z6: =IF(R6="Paying",L6,"") | AA6: =IF(R6="Completed",L6,"") -> -149
A7: 46286 | B7: 678月季度自修奖金支出 | C7: out | D7: CTM | F7: -3000 | G7: 1 | H7: =F7*G7 -> -3000 | I7: 10000007 | J7: =A7 -> 46286 | K7: =H7 -> -3000 | L7: =K7 -> -3000 | R7: Completed | T7: 678月自修奖金支出3000美元.pdf | V7: =IF(R7="Accrual",H7,"") | W7: =IF(R7="Receiving",K7,"") | X7: =IF(R7="Received",L7,"") | Y7: =IF(R7="Approved",L7,"") | Z7: =IF(R7="Paying",L7,"") | AA7: =IF(R7="Completed",L7,"") -> -3000
A8: 46284 | B8: 青岛代理收 SPRO费用300美元 | C8: out | D8: CTM | F8: -300 | G8: 1 | H8: =F8*G8 -> -300 | I8: 6000001 | J8: =A8 -> 46284 | K8: =H8 -> -300 | L8: =K8 -> -300 | R8: Completed | T8: 青岛代理收SPRO 费用300美元.pdf | V8: =IF(R8="Accrual",H8,"") | W8: =IF(R8="Receiving",K8,"") | X8: =IF(R8="Received",L8,"") | Y8: =IF(R8="Approved",L8,"") | Z8: =IF(R8="Paying",L8,"") | AA8: =IF(R8="Completed",L8,"") -> -300
A9: 46284 | B9: 青岛购买BondedStore香烟 | C9: out | D9: CTM | F9: -1010 | G9: 1 | H9: =F9*G9 -> -1010 | I9: 6000020 | J9: =A9 -> 46284 | K9: =H9 -> -1010 | L9: =K9 -> -1010 | R9: Completed | T9: 青岛购买Bonded Store香烟1010美元.pdf | V9: =IF(R9="Accrual",H9,"") | W9: =IF(R9="Receiving",K9,"") | X9: =IF(R9="Received",L9,"") | Y9: =IF(R9="Approved",L9,"") | Z9: =IF(R9="Paying",L9,"") | AA9: =IF(R9="Completed",L9,"") -> -1010
A10: 46283 | B10: 日照购买Bonded Store酒水等支出 | C10: out | D10: CTM | F10: -293 | G10: 1 | H10: =F10*G10 -> -293 | I10: 6000020 | J10: =A10 -> 46283 | K10: =H10 -> -293 | L10: =K10 -> -293 | R10: Completed | T10: 日照购买Bonded Store酒水等支出293美元.pdf | V10: =IF(R10="Accrual",H10,"") | W10: =IF(R10="Receiving",K10,"") | X10: =IF(R10="Received",L10,"") | Y10: =IF(R10="Approved",L10,"") | Z10: =IF(R10="Paying",L10,"") | AA10: =IF(R10="Completed",L10,"") -> -293
A11: 46266 | B11: 周老轨岚桥防船代理费用 | C11: out | D11: CTM | F11: -120 | G11: 1 | H11: =F11*G11 -> -120 | I11: 6000001 | J11: =A11 -> 46266 | K11: =H11 -> -120 | L11: =K11 -> -120 | R11: Completed | T11: 机务访船代理费120美元.pdf | V11: =IF(R11="Accrual",H11,"") | W11: =IF(R11="Receiving",K11,"") | X11: =IF(R11="Received",L11,"") | Y11: =IF(R11="Approved",L11,"") | Z11: =IF(R11="Paying",L11,"") | AA11: =IF(R11="Completed",L11,"") -> -120
A12: 46266 | B12: 岚桥加淡水200吨 | C12: out | D12: CTM | F12: -1400 | G12: 1 | H12: =F12*G12 -> -1400 | I12: 6000001 | J12: =A12 -> 46266 | K12: =H12 -> -1400 | L12: =K12 -> -1400 | R12: Completed | T12: 岚桥加淡水费用1400美元.pdf | V12: =IF(R12="Accrual",H12,"") | W12: =IF(R12="Receiving",K12,"") | X12: =IF(R12="Received",L12,"") | Y12: =IF(R12="Approved",L12,"") | Z12: =IF(R12="Paying",L12,"") | AA12: =IF(R12="Completed",L12,"") -> -1400
A13: 46266 | B13: 海事海关系统更改费用 | C13: out | D13: CTM | F13: -375 | G13: 1 | H13: =F13*G13 -> -375 | I13: 6000011 | J13: =A13 -> 46266 | K13: =H13 -> -375 | L13: =K13 -> -375 | R13: Completed | T13: 海事海关系统更改费用375美元.pdf | V13: =IF(R13="Accrual",H13,"") | W13: =IF(R13="Receiving",K13,"") | X13: =IF(R13="Received",L13,"") | Y13: =IF(R13="Approved",L13,"") | Z13: =IF(R13="Paying",L13,"") | AA13: =IF(R13="Completed",L13,"") -> -375
A14: 46265 | B14: 8月份客餐费用支出 | C14: out | D14: CTM | F14: -662 | G14: 1 | H14: =F14*G14 -> -662 | I14: 1000002 | J14: =A14 -> 46265 | K14: =H14 -> -662 | L14: =K14 -> -662 | R14: Completed | T14: 8月份客餐费用支出.pdf | V14: =IF(R14="Accrual",H14,"") | W14: =IF(R14="Receiving",K14,"") | X14: =IF(R14="Received",L14,"") | Y14: =IF(R14="Approved",L14,"") | Z14: =IF(R14="Paying",L14,"") | AA14: =IF(R14="Completed",L14,"") -> -662
A15: 46265 | B15: 8月份全船伙食费支出 | C15: out | D15: CTM | F15: -5400 | G15: 1 | H15: =F15*G15 -> -5400 | I15: 1000002 | J15: =A15 -> 46265 | K15: =H15 -> -5400 | L15: =K15 -> -5400 | R15: Completed | T15: 8月份船员伙食费用支出.pdf | V15: =IF(R15="Accrual",H15,"") | W15: =IF(R15="Receiving",K15,"") | X15: =IF(R15="Received",L15,"") | Y15: =IF(R15="Approved",L15,"") | Z15: =IF(R15="Paying",L15,"") | AA15: =IF(R15="Completed",L15,"") -> -5400
A16: 46257 | B16: HOMONHON水手张善钧购药支出 | C16: out | D16: CTM | F16: -733 | G16: 1 | H16: =F16*G16 -> -733 | I16: 1000006 | J16: =A16 -> 46257 | K16: =H16 -> -733 | L16: =K16 -> -733 | R16: Completed | T16: HOMONHON张善钧购药支出.pdf | W16: =IF(R16="Receiving",K16,"") | X16: =IF(R16="Received",L16,"") | Y16: =IF(R16="Approved",L16,"") | Z16: =IF(R16="Paying",L16,"") | AA16: =IF(R16="Completed",L16,"") -> -733
A17: 46251 | B17: V2605扫洗舱劳务费 | C17: out | D17: CTM | F17: -1125 | G17: 1 | H17: =F17*G17 -> -1125 | I17: 9000001 | J17: =A17 -> 46251 | K17: =H17 -> -1125 | L17: =K17 -> -1125 | R17: Completed | T17: PAYMENT LIST OF V2605 HOLD CLEANING BONUS.pdf | W17: =IF(R17="Receiving",K17,"") | X17: =IF(R17="Received",L17,"") | Y17: =IF(R17="Approved",L17,"") | Z17: =IF(R17="Paying",L17,"") | AA17: =IF(R17="Completed",L17,"") -> -1125
A18: 46238 | B18: 交付船长备用金 | C18: In | D18: CTM | F18: 50000 | G18: 1 | H18: =F18*G18 -> 50000 | I18: 6000007 | J18: 12‑Aug‑26 | K18: =H18 -> 50000 | L18: =K18 -> 50000 | R18: Completed | T18: CTM 50000USD RECEIPT.pdf | W18: =IF(R18="Receiving",K18,"") | X18: =IF(R18="Received",L18,"") | Y18: =IF(R18="Approved",L18,"") | Z18: =IF(R18="Paying",L18,"") | AA18: =IF(R18="Completed",L18,"") -> 50000
A19: 46238 | B19: 改船籍港特殊劳务费200美元 | C19: out | D19: CTM | F19: -200 | G19: 1 | H19: =F19*G19 -> -200 | I19: 9990001 | J19: 46238 | K19: =H19 -> -200 | L19: =K19 -> -200 | R19: Completed | T19: 改船籍港特殊劳务费200美元.pdf | V19: =IF(R19="Accrual",H19,"") | W19: =IF(R19="Receiving",K19,"") | X19: =IF(R19="Received",L19,"") | Y19: =IF(R19="Approved",L19,"") | Z19: =IF(R19="Paying",L19,"") | AA19: =IF(R19="Completed",L19,"") -> -200
A20: 46237 | B20: 原船管欠船员7月份伙食费支出 | C20: out | D20: CTM | F20: -1544 | G20: 1 | H20: =F20*G20 -> -1544 | I20: 1000002 | J20: 46237 | K20: =H20 -> -1544 | L20: =K20 -> -1544 | R20: Completed | T20: 7月份原船管伙食欠款1544美元收据 | V20: =IF(R20="Accrual",H20,"") | W20: =IF(R20="Receiving",K20,"") | X20: =IF(R20="Received",L20,"") | Y20: =IF(R20="Approved",L20,"") | Z20: =IF(R20="Paying",L20,"") | AA20: =IF(R20="Completed",L20,"") -> -1544
A21: 46235 | B21: LR船检两名外锚地登离船代理费用支出 | C21: out | D21: CTM | F21: -9230 | G21: 1 | H21: =F21*G21 -> -9230 | I21: 9990001 | J21: 46236 | K21: =H21 -> -9230 | L21: =K21 -> -9230 | R21: Completed | T21: LR 两名船检猫的登离船代理费用支出.pdf | V21: =IF(R21="Accrual",H21,"") | W21: =IF(R21="Receiving",K21,"") | X21: =IF(R21="Received",L21,"") | Y21: =IF(R21="Approved",L21,"") | Z21: =IF(R21="Paying",L21,"") | AA21: =IF(R21="Completed",L21,"") -> -9230
A22: 46234 | B22: GMDSS年检共工程师登离船代理费用支出 | C22: out | D22: CTM | F22: -2150 | G22: 1 | H22: =F22*G22 -> -2150 | I22: 9990001 | J22: 46235 | K22: =H22 -> -2150 | L22: =K22 -> -2150 | R22: Completed | T22: GMDSS年检工程师登离轮代理费支出.pdf | V22: =IF(R22="Accrual",H22,"") | W22: =IF(R22="Receiving",K22,"") | X22: =IF(R22="Received",L22,"") | Y22: =IF(R22="Approved",L22,"") | Z22: =IF(R22="Paying",L22,"") | AA22: =IF(R22="Completed",L22,"") -> -2150
A23: 46234 | B23: GRESIK加淡水100吨 | C23: out | D23: CTM | F23: -1350 | G23: 1 | H23: =F23*G23 -> -1350 | I23: 6000001 | J23: 46234 | K23: =H23 -> -1350 | L23: =K23 -> -1350 | R23: Completed | T23: Gresik加淡水100吨.pdf | V23: =IF(R23="Accrual",H23,"") | W23: =IF(R23="Receiving",K23,"") | X23: =IF(R23="Received",L23,"") | Y23: =IF(R23="Approved",L23,"") | Z23: =IF(R23="Paying",L23,"") | AA23: =IF(R23="Completed",L23,"") -> -1350
A24: 46233 | B24: 制作新船章两枚 | C24: out | D24: CTM | F24: -25 | G24: 1 | H24: =F24*G24 -> -25 | I24: 6000013 | J24: 46233 | K24: =H24 -> -25 | L24: =K24 -> -25 | R24: Completed | T24: 制作两枚船章.pdf | AA24: =IF(R24="Completed",L24,"") -> -25
A25: 46233 | B25: CTM RMB100,000 hand carried onboard when tookover vessel≈14815美元 | C25: In | D25: CTM | F25: 14815 | G25: 1 | H25: =F25*G25 -> 14815 | I25: 6000007 | J25: 46233 | K25: =H25 -> 14815 | L25: =K25 -> 14815 | R25: Completed | T25: 备用金收据14815USD.pdf | V25: =IF(R25="Accrual",H25,"") | W25: =IF(R25="Receiving",K25,"") | X25: =IF(R25="Received",L25,"") | Y25: =IF(R25="Approved",L25,"") | Z25: =IF(R25="Paying",L25,"") | AA25: =IF(R25="Completed",L25,"") -> 14815

Sheet Shipmanagement Cost
A1: 入账日期 | B1: 类型 | C1: RQA | D1: Supplier | E1: PO Nos | F1: Pay. Approval | G1: PO Current | H1: Rating | I1: PO Amount (USD) | J1: Account Code | K1: GRN/Date | L1: GRN Amount(USD) | M1: Invoice Amount(USD) | N1: C/N,Accural | O1: C/N Profit | P1: Profit | Q1: Invoice Date | R1: Due Date | S1: Payment Status | T1: Bank Charge | U1: Bank Slip | V1: Attachement | W1: Accrual | X1: Receiving | Y1: Received | Z1: Approved | AA1: Paying | AB1: Completed
C2: Receiving | D2: Received | E2: Approved | G2: Paying | H2: Completed | I2: =SUM($I$4:I161) -> 371476.96 | L2: =SUM($L$4:L161) -> 371476.96 | M2: =SUM($M$4:M161) -> 371321.3 | N2: =SUM(N3:N154) -> 0 | O2: =SUM(O3:O154) -> 0 | P2: =SUM(P3:P154) -> 0 | T2: =SUM(T3:T114) -> 920.53 | V2: Invoices | W2: =SUM(W4:W114) -> 6868.04 | X2: =SUM(X4:X114) -> 0 | Y2: =SUM(Y4:Y114) -> 108730.2 | Z2: =SUM(Z4:Z114) -> 0 | AA2: =SUM(AA4:AA114) -> 0 | AB2: =SUM(AB4:AB114) -> 192452.06 | AC2: =SUM(W2:AB2)+T2 -> 308970.83
A3: 46265 | B3: CTM 月度船上结余 | D3: MSTS | G3: ='CTM Expenses List'!AA2 -> 29908 | H3: 1 | I3: =-G3 -> -29908 | J3: 6000007 | K3: 46265 | L3: =I3 -> -29908 | M3: =L3 -> -29908 | S3: Completed | W3: =IF(S3="Receiving",M3,"") | X3: =IF(S3="Received",M3,"") | Y3: =IF(S3="Approved",M3,"") | Z3: =IF(S3="Paying",M3,"") | AA3: =IF(S3="Paying",M3,"") | AB3: =IF(S3="Completed",M3,"") -> -29908
AB4: =IF(S4="Completed",M4,"")
A5: 46309 | B5: 9月份船员工资+其他费用 | D5: Top Marine Limited | G5: 77881.96 | H5: 1 | I5: =G5*H5 -> 77881.96 | J5: 1000001 | K5: =A5 -> 46309 | L5: =I5 -> 77881.96 | M5: =L5 -> 77881.96 | S5: Received | V5: PIONEER LADY 9月账单(1).pdf | Y5: =IF(S5="Received",M5,"") -> 77881.96 | AB5: =IF(S5="Completed",M5,"")
A6: 46295 | B6: 帮Libra-XS支付巴哈马年度国旗国检验 | D6: SIMINTEC | G6: 2600 | H6: 1 | I6: =G6*H6 -> 2600 | L6: =I6 -> 2600 | M6: =I6 -> 2600 | S6: Completed | T6: 20 | U6: Payment_Certificate_20260930094805(1).pdf | Y6: =IF(S6="Received",M6,"") | AB6: =IF(S6="Completed",M6,"") -> 2600
A7: 46295 | B7: 9月份全船伙食费支出 | D7: CTM | G7: 5592 | H7: 1 | I7: =G7*H7 -> 5592 | J7: 1000002 | K7: =A7 -> 46295 | L7: =I7 -> 5592 | M7: =I7 -> 5592 | S7: Completed | V7: 2026年9月份伙食费收据5592美元.pdf | W7: =IF(S7="Accrual",M7,"") | X7: =IF(S7="Receiving",M7,"") | Y7: =IF(S7="Received",M7,"") | Z7: =IF(S7="Approved",M7,"") | AA7: =IF(S7="Paying",M7,"") | AB7: =IF(S7="Completed",M7,"") -> 5592
A8: 46293 | B8: 借款给 MULAU SHIPMANAGEMENT (HK) LIMITED付款失败 | D8: Maritime Solutions Technology Services (HK) Limited | G8: -9500 | H8: 1 | I8: =G8*H8 -> -9500 | L8: =I8 -> -9500 | M8: =I8 -> -9500 | S8: Completed | T8: -20 | Y8: =IF(S8="Received",M8,"") | AB8: =IF(S8="Completed",M8,"") -> -9500
A9: 46293 | B9: 借款给 MULAU SHIPMANAGEMENT (HK) LIMITED | D9: Maritime Solutions Technology Services (HK) Limited | G9: 9500 | H9: 1 | I9: =G9*H9 -> 9500 | L9: =I9 -> 9500 | M9: =L9 -> 9500 | S9: Completed | T9: 20 | W9: =IF(S9="Accrual",M9,"") | X9: =IF(S9="Receiving",M9,"") | Y9: =IF(S9="Received",M9,"") | Z9: =IF(S9="Approved",M9,"") | AA9: =IF(S9="Paying",M9,"") | AB9: =IF(S9="Completed",M9,"") -> 9500
A10: 46289 | B10: PIONEER LADY_海卫通卫星通信服务费 | D10: Marinesat海卫通网络科技有限公司 | G10: 8487.98 | H10: 0.149 | I10: =G10*H10 -> 1264.709 | J10: 6000017 | L10: =I10 -> 1264.709 | M10: =L10 -> 1264.709 | S10: Received | V10: SC0026080016-PIONEER LADY-Maritime Solutions Technology Service (HK) Limited-20260831.pdf | W10: =IF(S10="Accrual",M10,"") | X10: =IF(S10="Receiving",M10,"") | Y10: =IF(S10="Received",M10,"") -> 1264.709 | Z10: =IF(S10="Approved",M10,"") | AA10: =IF(S10="Paying",M10,"") | AB10: =IF(S10="Completed",M10,"")
A11: 46289 | B11: PIONEER LADY_办公租赁费+薪资 | D11: Maritime Solutions Technology Services (HK) Limited | G11: =157197.89+70000 -> 227197.89 | H11: 0.14937855 | I11: =G11*H11 -> 33938.492 | J11: 6000016 | L11: =I11 -> 33938.492 | M11: =L11 -> 33938.492 | S11: Completed | T11: 120 | U11: 20260930周总提现30000USD.pdf | V11: Invoice--单船开形式发票-Pioneer Lady办公室租金+员工薪资.pdf | W11: =IF(S11="Accrual",M11,"") | X11: =IF(S11="Receiving",M11,"") | Y11: =IF(S11="Received",M11,"") | Z11: =IF(S11="Approved",M11,"") | AA11: =IF(S11="Paying",M11,"") | AB11: =IF(S11="Completed",M11,"") -> 33938.492
A12: 46286 | B12: 2026年6,7,8月季度自修奖金支出 | D12: CTM | G12: 1000 | H12: 1 | I12: =G12*H12 -> 1000 | J12: 10000007 | K12: =A12 -> 46286 | L12: =I12 -> 1000 | M12: =L12 -> 1000 | S12: Completed | V12: 678月自修奖金支出3000美元.pdf | W12: =IF(S12="Accrual",M12,"") | X12: =IF(S12="Receiving",M12,"") | Y12: =IF(S12="Received",M12,"") | Z12: =IF(S12="Approved",M12,"") | AA12: =IF(S12="Paying",M12,"") | AB12: =IF(S12="Completed",M12,"") -> 1000
A13: 46286 | B13: 柯凯敏青岛就医及路费支出 | D13: CTM | G13: 149 | H13: 1 | I13: =G13*H13 -> 149 | J13: 7000009 | K13: =A13 -> 46286 | L13: =I13 -> 149 | M13: =L13 -> 149 | S13: Completed | V13: 柯凯敏青岛就医及路费支出149美元.pdf | W13: =IF(S13="Accrual",M13,"") | X13: =IF(S13="Receiving",M13,"") | Y13: =IF(S13="Received",M13,"") | Z13: =IF(S13="Approved",M13,"") | AA13: =IF(S13="Paying",M13,"") | AB13: =IF(S13="Completed",M13,"") -> 149
A14: 46284 | B14: 青岛代理收 SPRO费用300美元 | D14: CTM | G14: 300 | H14: 1 | I14: =G14*H14 -> 300 | J14: 6000001 | K14: =A14 -> 46284 | L14: =I14 -> 300 | M14: =L14 -> 300 | S14: Completed | V14: 青岛代理收SPRO 费用300美元.pdf | W14: =IF(S14="Accrual",M14,"") | X14: =IF(S14="Receiving",M14,"") | Y14: =IF(S14="Received",M14,"") | Z14: =IF(S14="Approved",M14,"") | AA14: =IF(S14="Paying",M14,"") | AB14: =IF(S14="Completed",M14,"") -> 300
A15: 46284 | B15: 青岛购买BondedStore香烟 | D15: CTM | G15: 1010 | H15: 1 | I15: =G15*H15 -> 1010 | J15: 6000020 | K15: =A15 -> 46284 | L15: =I15 -> 1010 | M15: =L15 -> 1010 | S15: Completed | V15: 青岛购买Bonded Store香烟1010美元.pdf | W15: =IF(S15="Accrual",M15,"") | X15: =IF(S15="Receiving",M15,"") | Y15: =IF(S15="Received",M15,"") | Z15: =IF(S15="Approved",M15,"") | AA15: =IF(S15="Paying",M15,"") | AB15: =IF(S15="Completed",M15,"") -> 1010
A16: 46283 | B16: 日照购买Bonded Store酒水等支出 | D16: CTM | G16: 293 | H16: 1 | I16: =G16*H16 -> 293 | J16: 6000020 | K16: =A16 -> 46283 | L16: =I16 -> 293 | M16: =L16 -> 293 | S16: Completed | V16: 日照购买Bonded Store酒水等支出293美元(1).pdf | W16: =IF(S16="Accrual",M16,"") | X16: =IF(S16="Receiving",M16,"") | Y16: =IF(S16="Received",M16,"") | Z16: =IF(S16="Approved",M16,"") | AA16: =IF(S16="Paying",M16,"") | AB16: =IF(S16="Completed",M16,"") -> 293
B17: 冲回原船管欠船员7月份伙食费支出 | D17: MSTS | G17: -1544 | H17: 1 | I17: -1544 | J17: 6000007 | L17: -1544 | M17: -1544 | W17: =IF(S17="Accrual",M17,"") | X17: =IF(S17="Receiving",M17,"") | Y17: =IF(S17="Received",M17,"") | Z17: =IF(S17="Approved",M17,"") | AA17: =IF(S17="Paying",M17,"") | AB17: =IF(S17="Completed",M17,"")
A18: 46277 | B18: 办公室杂项费用 | D18: Maritime Solutions Technology Services (HK) Limited | G18: 298.31 | H18: 1 | I18: =G18*H18 -> 298.31 | J18: 6000016 | L18: =I18 -> 298.31 | M18: =L18 -> 298.31 | S18: Completed | V18: 办公室费用-深圳博远20260922--$298.31(2).pdf | W18: =IF(S18="Accrual",M18,"") | X18: =IF(S18="Receiving",M18,"") | Y18: =IF(S18="Received",M18,"") | Z18: =IF(S18="Approved",M18,"") | AA18: =IF(S18="Paying",M18,"") | AB18: =IF(S18="Completed",M18,"") -> 298.31
A19: 46274 | B19: Pioneer Lady岚桥港值班及交通补贴-周琦RMB3541.02 | D19: Maritime Solutions Technology Services (HK) Limited | G19: 522.51 | H19: 1 | I19: =G19*H19 -> 522.51 | J19: 6000006 | L19: =I19 -> 522.51 | M19: =L19 -> 522.51 | S19: Completed | V19: Pioneer Lady蓝桥港值班津贴_20260909(1).pdf | W19: =IF(S19="Accrual",M19,"") | X19: =IF(S19="Receiving",M19,"") | Y19: =IF(S19="Received",M19,"") | Z19: =IF(S19="Approved",M19,"") | AA19: =IF(S19="Paying",M19,"") | AB19: =IF(S19="Completed",M19,"") -> 522.51
A20: 46269 | B20: 2026年8 月份船员工资 | D20: Top Marine Limited | G20: 70197.08 | H20: 1 | I20: =G20*H20 -> 70197.08 | J20: 1000001 | L20: =I20 -> 70197.08 | M20: =L20 -> 70197.08 | S20: Completed | T20: 170.53 | U20: Payment_Certificate_20260911154058.pdf | V20: PIONEER LADY 8月船员工资(2).pdf | W20: =IF(S20="Accrual",M20,"") | X20: =IF(S20="Receiving",M20,"") | Y20: =IF(S20="Received",M20,"") | Z20: =IF(S20="Approved",M20,"") | AA20: =IF(S20="Paying",M20,"") | AB20: =IF(S20="Completed",M20,"") -> 70197.08
A21: 46267 | B21: 通信数据流量费 | D21: TELEOCEAN INC | G21: 44.8 | H21: 1 | I21: =G21*H21 -> 44.8 | J21: 6000017 | K21: 46266 | L21: =I21 -> 44.8 | M21: =L21 -> 44.8 | Q21: 46266 | R21: 46281 | S21: Received | V21: Invoice_PIONEER LADY_C_2026_08_21358741_Stratos.pdf | W21: =IF(S21="Accrual",M21,"") | X21: =IF(S21="Receiving",M21,"") | Y21: =IF(S21="Received",M21,"") -> 44.8 | Z21: =IF(S21="Approved",M21,"") | AA21: =IF(S21="Paying",M21,"") | AB21: =IF(S21="Completed",M21,"")
A22: 46267 | B22: Vizada 通信订阅费（8月） | D22: TELEOCEAN INC | G22: 150 | H22: 1 | I22: =G22*H22 -> 150 | J22: 6000017 | K22: 46267 | L22: =I22 -> 150 | M22: =L22 -> 150 | Q22: 46267 | R22: 46282 | S22: Received | V22: Invoice_PIONEER LADY_C Monthly_2026_08_21363280_Stratos.pdf | W22: =IF(S22="Accrual",M22,"") | X22: =IF(S22="Receiving",M22,"") | Y22: =IF(S22="Received",M22,"") -> 150 | Z22: =IF(S22="Approved",M22,"") | AA22: =IF(S22="Paying",M22,"") | AB22: =IF(S22="Completed",M22,"")
A23: 46267 | B23: 提现后的差额费用 | D23: Maritime Solutions Technology Services (HK) Limited | G23: 2301.47 | H23: 1 | I23: =G23*H23 -> 2301.47 | J23: 6000016 | L23: =I23 -> 2301.47 | M23: =L23 -> 2301.47 | S23: Completed | U23: 20260831周总提现5000USD(1).pdf | V23: 提现后差额费用--2026.08.31(2).pdf | W23: =IF(S23="Accrual",M23,"") | X23: =IF(S23="Receiving",M23,"") | Y23: =IF(S23="Received",M23,"") | Z23: =IF(S23="Approved",M23,"") | AA23: =IF(S23="Paying",M23,"") | AB23: =IF(S23="Completed",M23,"") -> 2301.47
A24: 46267 | B24: 办公室费用 | D24: Maritime Solutions Technology Services (HK) Limited | G24: 10292.19 | H24: 1 | I24: =G24*H24 -> 10292.19 | J24: 6000013 | L24: =I24 -> 10292.19 | M24: =L24 -> 10292.19 | S24: Completed | V24: 办公费用69527.18RMB—10292.19USD(2).pdf | W24: =IF(S24="Accrual",M24,"") | X24: =IF(S24="Receiving",M24,"") | Y24: =IF(S24="Received",M24,"") | Z24: =IF(S24="Approved",M24,"") | AA24: =IF(S24="Paying",M24,"") | AB24: =IF(S24="Completed",M24,"") -> 10292.19
A25: 46266 | B25: MSTS股份转移 | D25: Maritime Solutions Technology Services (HK) Limited | G25: 30622.61 | H25: 1 | I25: =G25*H25 -> 30622.61 | J25: 6000016 | L25: =I25 -> 30622.61 | M25: =L25 -> 30622.61 | S25: Completed | T25: 120 | U25: Payment_Certificate_20260920113437.pdf | V25: Invoice--单船开形式发票-段正权股份(1).pdf | W25: =IF(S25="Accrual",M25,"") | X25: =IF(S25="Receiving",M25,"") | Y25: =IF(S25="Received",M25,"") | Z25: =IF(S25="Approved",M25,"") | AA25: =IF(S25="Paying",M25,"") | AB25: =IF(S25="Completed",M25,"") -> 30622.61
A26: 46266 | B26: 周老轨岚桥防船代理费用 | D26: CTM | F26: 机务访船代理费120美元.pdf | G26: 120 | H26: 1 | I26: =G26*H26 -> 120 | J26: 6000001 | K26: =A26 -> 46266 | L26: =I26 -> 120 | M26: =L26 -> 120 | S26: Completed | V26: 机务访船代理费120美元.pdf | W26: =IF(S26="Accrual",M26,"") | X26: =IF(S26="Receiving",M26,"") | Y26: =IF(S26="Received",M26,"") | Z26: =IF(S26="Approved",M26,"") | AA26: =IF(S26="Paying",M26,"") | AB26: =IF(S26="Completed",M26,"") -> 120
A27: 46262 | B27: 发电机 | C27: EPILP26009 | D27: RMS MARINE SERVICE COMPANY LTD | E27: PILEP26009 | F27: EPILP26009-PIONEER LADY 订单确认报告_20260923135413.pdf | G27: 2032.5 | H27: 1 | I27: =G27*H27 -> 2032.5 | J27: 3000008 | L27: =I27 -> 2032.5 | M27: =L27 -> 2032.5 | S27: Accrual | W27: =IF(S27="Accrual",M27,"") -> 2032.5 | X27: =IF(S27="Receiving",M27,"") | Y27: =IF(S27="Received",M27,"") | Z27: =IF(S27="Approved",M27,"") | AA27: =IF(S27="Paying",M27,"") | AB27: =IF(S27="Completed",M27,"")
A28: 46262 | B28: 化学品 | C28: EPILT26003 | D28: DanTecs (HK) Marine Solutions Limited | E28: PILET26003 | F28: EPILT26003-PIONEER LADY 订单确认报告_20260930154202.pdf | G28: 2260.32 | H28: 1 | I28: 2260.32 | J28: 2000009 | L28: 2260.32 | M28: 2842.32 | S28: Received | V28: EPILT26003__INVOICE(1).pdf | W28: =IF(S28="Accrual",M28,"") | X28: =IF(S28="Receiving",M28,"") | Y28: =IF(S28="Received",M28,"") -> 2842.32 | Z28: =IF(S28="Approved",M28,"") | AA28: =IF(S28="Paying",M28,"") | AB28: =IF(S28="Completed",M28,"")
A29: 46262 | B29: 燃油分油机 | C29: EPILP26012 | D29: DanTecs (HK) Marine Solutions Limited | E29: PILEP26012 | F29: DPILT26009-PIONEER LADY 订单确认报告_20260929101940(1).pdf | G29: 937 | H29: 1 | I29: 937 | J29: 3000012 | L29: 937 | M29: =L29 -> 937 | Q29: 46283 | R29: 46313 | S29: Received | V29: EPILP26012__INVOICE.pdf | W29: =IF(S29="Accrual",M29,"") | X29: =IF(S29="Receiving",M29,"") | Y29: =IF(S29="Received",M29,"") -> 937 | Z29: =IF(S29="Approved",M29,"") | AA29: =IF(S29="Paying",M29,"") | AB29: =IF(S29="Completed",M29,"")
A30: 46262 | B30: 岚桥采购油漆 | C30: DPILT26006 | D30: 钧源船舶服务有限公司 | E30: PILDT26006 | F30: DPILT26006-PIONEER LADY 订单确认报告_20261001112318.pdf | G30: 7015.75 | H30: 1 | I30: =G30*H30 -> 7015.75 | J30: 2000004 | L30: =I30 -> 7015.75 | M30: 4271.4 | Q30: 46265 | R30: 46296 | S30: Completed | T30: 20 | U30: Entrusted_Payment_Certificate_S05202609240320523257112_20260924112224.pdf | V30: Pioneer Lady-销售INV(1).pdf | W30: =IF(S30="Accrual",M30,"") | X30: =IF(S30="Receiving",M30,"") | Y30: =IF(S30="Received",M30,"") | Z30: =IF(S30="Approved",M30,"") | AA30: =IF(S30="Paying",M30,"") | AB30: =IF(S30="Completed",M30,"") -> 4271.4
A31: 46262 | B31: 造水机 | C31: EPILP26013 | D31: RMS MARINE SERVICE COMPANY LTD | E31: PILEP26013 | F31: EPILP26013-PIONEER LADY 订单确认报告_20260923141439.pdf | G31: 904.33 | H31: 1 | I31: =G31*H31 -> 904.33 | J31: 3000012 | L31: =I31 -> 904.33 | M31: =L31 -> 904.33 | S31: Accrual | W31: =IF(S31="Accrual",M31,"") -> 904.33 | X31: =IF(S31="Receiving",M31,"") | Y31: =IF(S31="Received",M31,"") | Z31: =IF(S31="Approved",M31,"") | AA31: =IF(S31="Paying",M31,"") | AB31: =IF(S31="Completed",M31,"")
A32: 46262 | B32: 主空压机 | C32: EPILP26011 | D32: RMS MARINE SERVICE COMPANY LTD | E32: PILEP26011 | F32: EPILP26011-PIONEER LADY 订单确认报告_20260923135659.pdf | G32: 136.36 | H32: 1 | I32: =G32*H32 -> 136.36 | J32: 3000012 | L32: =I32 -> 136.36 | M32: =L32 -> 136.36 | S32: Accrual | W32: =IF(S32="Accrual",M32,"") -> 136.36 | X32: =IF(S32="Receiving",M32,"") | Y32: =IF(S32="Received",M32,"") | Z32: =IF(S32="Approved",M32,"") | AA32: =IF(S32="Paying",M32,"") | AB32: =IF(S32="Completed",M32,"")
A33: 46262 | B33: 文具物料 | C33: DPILT26001 | D33: DanTecs (HK) Marine Solutions Limited | E33: PILDT26001 | F33: DPILT26004订单确认报告_20260923115934.pdf | G33: 923.53 | H33: 1 | I33: =G33*H33 -> 923.53 | J33: 2000007 | L33: =I33 -> 923.53 | M33: =L33 -> 923.53 | Q33: 46283 | R33: 46313 | S33: Received | V33: DPILT26001__INVOICE.pdf | W33: =IF(S33="Accrual",M33,"") | X33: =IF(S33="Receiving",M33,"") | Y33: =IF(S33="Received",M33,"") -> 923.53 | Z33: =IF(S33="Approved",M33,"") | AA33: =IF(S33="Paying",M33,"") | AB33: =IF(S33="Completed",M33,"")
A34: 46262 | B34: 甲板物料-2通用物料 | C34: DPILT26002-2 | D34: DanTecs (HK) Marine Solutions Limited | E34: PILDT26002-2 | F34: DPILT26002订单确认报告_20260923115648.pdf | G34: 2832.54 | H34: 1 | I34: =G34*H34 -> 2832.54 | J34: 2000007 | L34: =I34 -> 2832.54 | M34: 3116.88 | Q34: 46283 | R34: 46313 | S34: Received | V34: DPILT26002-2__INVOICE.pdf | W34: =IF(S34="Accrual",M34,"") | X34: =IF(S34="Receiving",M34,"") | Y34: =IF(S34="Received",M34,"") -> 3116.88 | Z34: =IF(S34="Approved",M34,"") | AA34: =IF(S34="Paying",M34,"") | AB34: =IF(S34="Completed",M34,"")
A35: 46262 | B35: 甲板物料-1缆绳检测仪+耳机 | C35: DPILT26002-1 | D35: DanTecs (HK) Marine Solutions Limited | E35: PILDT26002-1 | F35: DPILT26002订单确认报告_20260923115648(1).pdf | G35: 2745 | H35: 1 | I35: =G35*H35 -> 2745 | J35: 2000007 | L35: =I35 -> 2745 | M35: 4000 | Q35: 46283 | R35: 46313 | S35: Received | V35: DPILT26002-1__INVOICE(1).pdf | W35: =IF(S35="Accrual",M35,"") | X35: =IF(S35="Receiving",M35,"") | Y35: =IF(S35="Received",M35,"") -> 4000 | Z35: =IF(S35="Approved",M35,"") | AA35: =IF(S35="Paying",M35,"") | AB35: =IF(S35="Completed",M35,"")
A36: 46262 | B36: 救生和消防物料 | C36: DPILT26003 | D36: DanTecs (HK) Marine Solutions Limited | E36: PILDT26003 | F36: DPILT26003订单确认报告_20260923115825.pdf | G36: 1205.28 | H36: 1 | I36: =G36*H36 -> 1205.28 | J36: 2000006 | L36: =I36 -> 1205.28 | M36: =L36 -> 1205.28 | Q36: 46283 | R36: 46313 | S36: Received | V36: DPILT26003__INVOICE.pdf | W36: =IF(S36="Accrual",M36,"") | X36: =IF(S36="Receiving",M36,"") | Y36: =IF(S36="Received",M36,"") -> 1205.28 | Z36: =IF(S36="Approved",M36,"") | AA36: =IF(S36="Paying",M36,"") | AB36: =IF(S36="Completed",M36,"")
A37: 46262 | B37: 生活物料 | C37: DPILT26004 | D37: DanTecs (HK) Marine Solutions Limited | E37: PILDT26004 | F37: DPILT26004订单确认报告_20260923115934(1).pdf | G37: 1620.42 | H37: 1 | I37: =G37*H37 -> 1620.42 | J37: 2000012 | L37: =I37 -> 1620.42 | M37: =L37 -> 1620.42 | Q37: 46283 | R37: 46313 | S37: Received | V37: DPILT26004__INVOICE.pdf | W37: =IF(S37="Accrual",M37,"") | X37: =IF(S37="Receiving",M37,"") | Y37: =IF(S37="Received",M37,"") -> 1620.42 | Z37: =IF(S37="Approved",M37,"") | AA37: =IF(S37="Paying",M37,"") | AB37: =IF(S37="Completed",M37,"")
A38: 46262 | B38: 药品及医疗器材 | C38: DPILT26005 | D38: DanTecs (HK) Marine Solutions Limited | E38: PILDT26005 | F38: DPILT26005订单确认报告_20260923120026.pdf | G38: 365.27 | H38: 1 | I38: =G38*H38 -> 365.27 | J38: 2000001 | L38: =I38 -> 365.27 | M38: =L38 -> 365.27 | Q38: 46283 | R38: 46313 | S38: Received | V38: DPILT26005__INVOICE.pdf | W38: =IF(S38="Accrual",M38,"") | X38: =IF(S38="Receiving",M38,"") | Y38: =IF(S38="Received",M38,"") -> 365.27 | Z38: =IF(S38="Approved",M38,"") | AA38: =IF(S38="Paying",M38,"") | AB38: =IF(S38="Completed",M38,"")
A39: 46262 | B39: 主机缸盖 | C39: EPILP26001 | D39: DanTecs (HK) Marine Solutions Limited | E39: PILEP26001 | F39: EPILP26001-PIONEER LADY 订单确认报告_20260923132752.pdf | G39: 300 | H39: 1 | I39: 300 | J39: 3000007 | L39: 300 | M39: =L39 -> 300 | Q39: 46283 | R39: 46313 | S39: Received | V39: EPILP26001__INVOICE.pdf | W39: =IF(S39="Accrual",M39,"") | X39: =IF(S39="Receiving",M39,"") | Y39: =IF(S39="Received",M39,"") -> 300 | Z39: =IF(S39="Approved",M39,"") | AA39: =IF(S39="Paying",M39,"") | AB39: =IF(S39="Completed",M39,"")
A40: 46262 | B40: 主机震动缓冲器 | C40: EPILP26005 | D40: DanTecs (HK) Marine Solutions Limited | E40: PILEP26005 | F40: EPILP26005-PIONEER LADY 订单确认报告_20260923134923.pdf | G40: 35 | H40: 1 | I40: 35 | J40: 3000007 | L40: 35 | M40: =L40 -> 35 | Q40: 46283 | R40: 46313 | S40: Received | V40: EPILP26005__INVOICE.pdf | W40: =IF(S40="Accrual",M40,"") | X40: =IF(S40="Receiving",M40,"") | Y40: =IF(S40="Received",M40,"") -> 35 | Z40: =IF(S40="Approved",M40,"") | AA40: =IF(S40="Paying",M40,"") | AB40: =IF(S40="Completed",M40,"")
A41: 46262 | B41: 生活污水处理装置 | C41: EPILP26020 | D41: DanTecs (HK) Marine Solutions Limited | E41: PILEP26020 | F41: EPILP26020-PIONEER LADY 订单确认报告_20260923152935.pdf | G41: 700 | H41: 1 | I41: 700 | J41: 3000012 | L41: 700 | M41: =L41 -> 700 | Q41: 46283 | R41: 46313 | S41: Received | V41: EPILP26020__INVOICE.pdf | W41: =IF(S41="Accrual",M41,"") | X41: =IF(S41="Receiving",M41,"") | Y41: =IF(S41="Received",M41,"") -> 700 | Z41: =IF(S41="Approved",M41,"") | AA41: =IF(S41="Paying",M41,"") | AB41: =IF(S41="Completed",M41,"")
A42: 46262 | B42: 压载泵 | C42: EPILP26021 | D42: DanTecs (HK) Marine Solutions Limited | E42: PILEP26021 | F42: EPILP26021-PIONEER LADY 订单确认报告_20260923153850.pdf | G42: 155 | H42: 1 | I42: 155 | J42: 3000004 | L42: 155 | M42: =L42 -> 155 | Q42: 46283 | R42: 46313 | S42: Received | V42: EPILP26021__INVOICE.pdf | W42: =IF(S42="Accrual",M42,"") | X42: =IF(S42="Receiving",M42,"") | Y42: =IF(S42="Received",M42,"") -> 155 | Z42: =IF(S42="Approved",M42,"") | AA42: =IF(S42="Paying",M42,"") | AB42: =IF(S42="Completed",M42,"")
A43: 46262 | B43: 消防泵备件(Fire & G/S RVP160S SHINKO) | C43: EPILP26023 | D43: DanTecs (HK) Marine Solutions Limited | E43: PILEP26023 | F43: EPILP26023-PIONEER LADY 订单确认报告_20260923155339.pdf | G43: 350 | H43: 1 | I43: 350 | J43: 3000012 | L43: =I43 -> 350 | M43: =L43 -> 350 | Q43: 46283 | R43: 46313 | S43: Received | V43: EPILP26023__INVOICE.pdf | W43: =IF(S43="Accrual",M43,"") | X43: =IF(S43="Receiving",M43,"") | Y43: =IF(S43="Received",M43,"") -> 350 | Z43: =IF(S43="Approved",M43,"") | AA43: =IF(S43="Paying",M43,"") | AB43: =IF(S43="Completed",M43,"")
A44: 46262 | B44: 发电机增压器 | C44: EPILP26010 | D44: DanTecs (HK) Marine Solutions Limited | E44: PILEP26010 | F44: EPILP26010-PIONEER LADY 订单确认报告_20260923135509.pdf | G44: 996 | H44: 1 | I44: 996 | J44: 3000008 | L44: 996 | M44: =L44 -> 996 | Q44: 46283 | R44: 46313 | S44: Received | V44: EPILP26010__INVOICE(1).pdf | W44: =IF(S44="Accrual",M44,"") | X44: =IF(S44="Receiving",M44,"") | Y44: =IF(S44="Received",M44,"") -> 996 | Z44: =IF(S44="Approved",M44,"") | AA44: =IF(S44="Paying",M44,"") | AB44: =IF(S44="Completed",M44,"")
A45: 46262 | B45: 滑油分油机 | C45: EPILP26008 | D45: DanTecs (HK) Marine Solutions Limited | E45: PILEP26008 | F45: EPILP26008-PIONEER LADY 订单确认报告_20260923135329.pdf | G45: 332 | H45: 1 | I45: 332 | J45: 3000012 | L45: 332 | M45: =L45 -> 332 | Q45: 46283 | R45: 46313 | S45: Received | V45: EPILP26008__INVOICE.pdf | W45: =IF(S45="Accrual",M45,"") | X45: =IF(S45="Receiving",M45,"") | Y45: =IF(S45="Received",M45,"") -> 332 | Z45: =IF(S45="Approved",M45,"") | AA45: =IF(S45="Paying",M45,"") | AB45: =IF(S45="Completed",M45,"")
A46: 46262 | B46: 主机供油单元 | C46: EPILP26007 | D46: DanTecs (HK) Marine Solutions Limited | E46: PILEP26007 | F46: EPILP26007-PIONEER LADY 订单确认报告_20260930113513.pdf | G46: 2523 | H46: 1 | I46: =G46*H46 -> 2523 | J46: 3000007 | L46: =I46 -> 2523 | M46: =L46 -> 2523 | Q46: 46283 | R46: 46313 | S46: Received | V46: EPILP26007__INVOICE.pdf | W46: =IF(S46="Accrual",M46,"") | X46: =IF(S46="Receiving",M46,"") | Y46: =IF(S46="Received",M46,"") -> 2523 | Z46: =IF(S46="Approved",M46,"") | AA46: =IF(S46="Paying",M46,"") | AB46: =IF(S46="Completed",M46,"")
A47: 46262 | B47: 主机排气阀 | C47: EPILP26006 | D47: DanTecs (HK) Marine Solutions Limited | E47: PILEP26006 | F47: EPILP26006-PIONEER LADY 订单确认报告_20260923135001.pdf | G47: 194.68 | H47: 1 | I47: 194.68 | J47: 3000007 | L47: =I47 -> 194.68 | M47: =L47 -> 194.68 | Q47: 46283 | R47: 46313 | S47: Received | V47: EPILP26006__INVOICE.pdf | W47: =IF(S47="Accrual",M47,"") | X47: =IF(S47="Receiving",M47,"") | Y47: =IF(S47="Received",M47,"") -> 194.68 | Z47: =IF(S47="Approved",M47,"") | AA47: =IF(S47="Paying",M47,"") | AB47: =IF(S47="Completed",M47,"")
A48: 46262 | B48: 机舱半年 通用物料申请单 | C48: EPILT26001 | D48: DanTecs (HK) Marine Solutions Limited | E48: PILET26001 | F48: EPILT26001-PIONEER LADY 订单确认报告_20260923163929.pdf | G48: 6971.22 | H48: 1 | I48: =G48*H48 -> 6971.22 | J48: 2000011 | L48: =I48 -> 6971.22 | M48: 7438.57 | Q48: 46283 | R48: 46313 | S48: Received | V48: EPILT26001__INVOICE.pdf | W48: =IF(S48="Accrual",M48,"") | X48: =IF(S48="Receiving",M48,"") | Y48: =IF(S48="Received",M48,"") -> 7438.57 | Z48: =IF(S48="Approved",M48,"") | AA48: =IF(S48="Paying",M48,"") | AB48: =IF(S48="Completed",M48,"") | AC48: =IF(S50="Completed",M50,"")
A49: 46262 | B49: 消防泵备件(Fire & G/S RVP160S SHINKO) | C49: EPILP26022 | D49: ZHOUSHAN HAISHAN MARINE SERVICE CO., LIMITED | E49: PILEP26022 | F49: EPILP26022-PIONEER LADY 订单确认报告_20260923155023.pdf | G49: 485 | H49: 1 | I49: =G49*H49 -> 485 | J49: 3000003 | L49: =I49 -> 485 | M49: =L49 -> 485 | Q49: 46287 | S49: Received | V49: EPILP26022 发票.pdf | W49: =IF(S49="Accrual",M49,"") | X49: =IF(S49="Receiving",M49,"") | Y49: =IF(S49="Received",M49,"") -> 485 | Z49: =IF(S49="Approved",M49,"") | AA49: =IF(S49="Paying",M49,"") | AB49: =IF(S49="Completed",M49,"") | AC49: =IF(S51="Completed",M51,"")
A50: 46262 | B50: 主机填料涵 | C50: EPILP26004 | D50: ZHOUSHAN HAISHAN MARINE SERVICE CO., LIMITED | E50: PILEP26004 | F50: EPILP26004-PIONEER LADY 订单确认报告_20260923134154.pdf | G50: 31.56 | H50: 1 | I50: =G50*H50 -> 31.56 | J50: 3000007 | L50: =I50 -> 31.56 | M50: =L50 -> 31.56 | Q50: 46287 | S50: Received | V50: EPILP26004 发票.pdf | W50: =IF(S50="Accrual",M50,"") | X50: =IF(S50="Receiving",M50,"") | Y50: =IF(S50="Received",M50,"") -> 31.56 | Z50: =IF(S50="Approved",M50,"") | AA50: =IF(S50="Paying",M50,"") | AB50: =IF(S50="Completed",M50,"") | AC50: =IF(S52="Completed",M52,"")
A51: 46262 | B51: 主机燃油阀 | C51: EPILP26003 | D51: ZHOUSHAN HAISHAN MARINE SERVICE CO., LIMITED | E51: PILEP26003 | F51: EPILP26003-PIONEER LADY 订单确认报告_20260923134003.pdf | G51: 821.22 | H51: 1 | I51: =G51*H51 -> 821.22 | J51: 3000007 | L51: =I51 -> 821.22 | M51: =L51 -> 821.22 | Q51: 46287 | S51: Received | V51: EPILP26003 发票.pdf | W51: =IF(S51="Accrual",M51,"") | X51: =IF(S51="Receiving",M51,"") | Y51: =IF(S51="Received",M51,"") -> 821.22 | Z51: =IF(S51="Approved",M51,"") | AA51: =IF(S51="Paying",M51,"") | AB51: =IF(S51="Completed",M51,"")
A52: 46262 | B52: 主机缸套 | C52: EPILP26002 | D52: ZHOUSHAN HAISHAN MARINE SERVICE CO., LIMITED | E52: PILEP26002 | F52: EPILP26002-PIONEER LADY 订单确认报告_20260923133222.pdf | G52: 16 | H52: 1 | I52: =G52*H52 -> 16 | J52: 3000007 | L52: =I52 -> 16 | M52: =L52 -> 16 | Q52: 46287 | S52: Received | V52: EPILP26002 发票.pdf | W52: =IF(S52="Accrual",M52,"") | X52: =IF(S52="Receiving",M52,"") | Y52: =IF(S52="Received",M52,"") -> 16 | Z52: =IF(S52="Approved",M52,"") | AA52: =IF(S52="Paying",M52,"") | AB52: =IF(S52="Completed",M52,"")
A53: 46262 | B53: 救生消防年检 | D53: ZHOUSHAN HAISHAN MARINE SERVICE CO., LIMITED | F53: 消防年检确认报告_20260923172254.pdf | G53: 3794.85 | H53: 1 | I53: =G53*H53 -> 3794.85 | J53: 4000011 | L53: =I53 -> 3794.85 | M53: =L53 -> 3794.85 | S53: Accrual | W53: =IF(S53="Accrual",M53,"") -> 3794.85 | X53: =IF(S53="Receiving",M53,"") | Y53: =IF(S53="Received",M53,"") | Z53: =IF(S53="Approved",M53,"") | AA53: =IF(S53="Paying",M53,"") | AB53: =IF(S53="Completed",M53,"")
A54: 46265 | B54: 董事长基金-周总 | F54: 董事长基金--2026.08.31.pdf | G54: 10000 | H54: 1 | I54: =G54*H54 -> 10000 | J54: 6000016 | L54: =I54 -> 10000 | M54: =L54 -> 10000 | S54: Completed | U54: 2026/8/14合并支付 | V54: 董事长基金--2026.08.31.pdf | W54: =IF(S54="Accrual",M54,"") | X54: =IF(S54="Receiving",M54,"") | Y54: =IF(S54="Received",M54,"") | Z54: =IF(S54="Approved",M54,"") | AA54: =IF(S54="Paying",M54,"") | AB54: =IF(S54="Completed",M54,"") -> 10000
A55: 46265 | B55: 8月份全船伙食费支出 | D55: CTM | F55: 8月份船员伙食费用支出(1).pdf | G55: 5400 | H55: 1 | I55: =G55*H55 -> 5400 | J55: 1000002 | L55: =I55 -> 5400 | M55: =L55 -> 5400 | S55: Completed | V55: 8月份船员伙食费用支出(1).pdf | W55: =IF(S55="Accrual",M55,"") | X55: =IF(S55="Receiving",M55,"") | Y55: =IF(S55="Received",M55,"") | Z55: =IF(S55="Approved",M55,"") | AA55: =IF(S55="Paying",M55,"") | AB55: =IF(S55="Completed",M55,"") -> 5400
A56: 46259 | B56: 付款没付成功，银行扣款手续费USD50 | J56: 6000009 | T56: 50 | U56: 银行扣款手续费USD50.pdf | W56: =IF(S56="Accrual",M56,"") | X56: =IF(S56="Receiving",M56,"") | Y56: =IF(S56="Received",M56,"") | Z56: =IF(S56="Approved",M56,"") | AA56: =IF(S56="Paying",M56,"") | AB56: =IF(S56="Completed",M56,"")
A57: 46248 | B57: 董事长基金-周总 | F57: 董事长基金--2026.07.31.pdf | G57: 10000 | H57: 1 | I57: =G57*H57 -> 10000 | J57: 6000016 | L57: =I57 -> 10000 | M57: =L57 -> 10000 | S57: Completed | U57: 20260831-周总提现45000USD.pdf | V57: 董事长基金--2026.08.14.pdf | W57: =IF(S57="Accrual",M57,"") | X57: =IF(S57="Receiving",M57,"") | Y57: =IF(S57="Received",M57,"") | Z57: =IF(S57="Approved",M57,"") | AA57: =IF(S57="Paying",M57,"") | AB57: =IF(S57="Completed",M57,"") -> 10000
A58: 46238 | B58: 菲律宾 CTM 代理代办服务费 | D58: TOP MARINE LIMITED | E58: PSI-2608-104 | F58: 20260827_代理费2000付款凭证.pdf | G58: 2000 | H58: 1 | I58: =G58*H58 -> 2000 | J58: 6000007 | K58: 46238 | L58: =I58 -> 2000 | M58: =L58 -> 2000 | Q58: 46238 | S58: Completed | T58: 20 | U58: Payment_Certificate_20260920112405.pdf | V58: 20260827_代理费2000付款凭证.pdf | W58: =IF(S58="Accrual",M58,"") | X58: =IF(S58="Receiving",M58,"") | Y58: =IF(S58="Received",M58,"") | Z58: =IF(S58="Approved",M58,"") | AA58: =IF(S58="Paying",M58,"") | AB58: =IF(S58="Completed",M58,"") -> 2000
A59: 46237 | B59: 原船管欠船员7月份伙食费支出 | D59: CTM | F59: 7月份原船管伙食欠款1544美元收据(2).pdf | G59: 1544 | H59: 1 | I59: =G59*H59 -> 1544 | J59: 1000002 | K59: 46237 | L59: =I59 -> 1544 | M59: =L59 -> 1544 | S59: Completed | V59: 7月份原船管伙食欠款1544美元收据(2).pdf | W59: =IF(S59="Accrual",M59,"") | X59: =IF(S59="Receiving",M59,"") | Y59: =IF(S59="Received",M59,"") | Z59: =IF(S59="Approved",M59,"") | AA59: =IF(S59="Paying",M59,"") | AB59: =IF(S59="Completed",M59,"") -> 1544
A60: 46238 | B60: 代理给船长5万备用金 | D60: CTM | F60: CTM 50000USD RECEIPT(2).pdf | G60: 50000 | H60: 1 | I60: 50000 | J60: 6000007 | L60: 50000 | M60: 50000 | T60: 200 | U60: 20260908__备用金_5WUSD付款凭证银行.pdf | V60: CTM 50000USD RECEIPT(2).pdf | W60: =IF(S60="Accrual",M60,"") | X60: =IF(S60="Receiving",M60,"") | Y60: =IF(S60="Received",M60,"") | Z60: =IF(S60="Approved",M60,"") | AA60: =IF(S60="Paying",M60,"") | AB60: =IF(S60="Completed",M60,"")
A61: 46233 | B61: CTM RMB100,000 hand carried onboard when tookover vessel≈14815美元 | D61: CTM | F61: 备用金收据14815USD.pdf | G61: 14815 | H61: 1 | I61: 14815 | J61: 6000007 | K61: 46233 | L61: 14815 | M61: 14815 | T61: 200 | V61: 备用金收据14815USD.pdf | W61: =IF(S61="Accrual",M61,"") | X61: =IF(S61="Receiving",M61,"") | Y61: =IF(S61="Received",M61,"") | Z61: =IF(S61="Approved",M61,"") | AA61: =IF(S61="Paying",M61,"") | AB61: =IF(S61="Completed",M61,"")
AB62: =IF(S62="Completed",M62,"")

Sheet Owner Cost
A1: 入账日期 | B1: 类型 | C1: RQA | D1: Supplier | E1: PO Nos | F1: Pay. Approval | G1: PO Current | H1: Rating | I1: PO Amount (USD) | J1: Account Code | K1: GRN/Date | L1: GRN Amount(USD) | M1: Invoice Amount(USD) | N1: C/N,Accural | O1: C/N Profit | P1: Profit | Q1: Invoice Date | R1: Due Date | S1: Payment Status | T1: Bank Charge | U1: Bank Slip | V1: Attachement | W1: Accrual | X1: Receiving | Y1: Received | Z1: Approved | AA1: Paying | AB1: Completed | AC1: 已收 | AD1: 已开票 | AE1: 待收 | AF1: 船东付
C2: Receiving | D2: Received | E2: Approved | G2: Paying | H2: Completed | I2: =SUM(I3:I116) -> 37968.27 | L2: =SUM(L3:L116) -> 37968.27 | M2: =SUM(M3:M116) -> 37968.27 | N2: =SUM(N3:N117) -> 0 | O2: =SUM(O3:O117) -> 0 | P2: =SUM(P3:P117) -> 0 | T2: =SUM(T3:T116) -> 20 | V2: Invoices | W2: =SUM(W3:W116) -> 0 | X2: =SUM(X3:X116) -> 0 | Y2: =SUM(Y3:Y116) -> 17088.23 | Z2: =SUM(Z3:Z116) -> 0 | AA2: =SUM(AA3:AA116) -> 0 | AB2: =SUM(AB3:AB116) -> 19680.04 | AC2: =SUM(W2:AB2)+T2 -> 36788.27 | AD2: 备注
W3: =IF(S3="Accrual",M3,"") | X3: =IF(S3="Receiving",M3,"") | Y3: =IF(S3="Received",M3,"") | Z3: =IF(S3="Approved",M3,"") | AA3: =IF(S3="Paying",M3,"") | AB3: =IF(S3="Completed",M3,"")
A5: 46295 | B5: 9月份客餐费用支出 | D5: CTM | G5: 249 | H5: 1 | I5: =G5*H5 -> 249 | J5: 6000002 | K5: =A5 -> 46295 | L5: =I5 -> 249 | M5: =L5 -> 249 | S5: Completed | V5: 9月份客餐费用支出249美元.pdf | W5: =IF(S5="Accrual",M5,"") | X5: =IF(S5="Receiving",M5,"") | Y5: =IF(S5="Received",M5,"") | Z5: =IF(S5="Approved",M5,"") | AA5: =IF(S5="Paying",M5,"") | AB5: =IF(S5="Completed",M5,"") -> 249 | AC5: =IF(OR(AD5="船东付",AD5="待收"),0,M5) -> 0 | AD5: 待收
A6: 46293 | B6: 巴生港锚地检验陪同费--Rightship 检验 | D6: Silver Base Maritime Sdn. Bhd. | G6: 1660 | H6: 1 | I6: =G6*H6 -> 1660 | J6: 4000014 | L6: =I6 -> 1660 | M6: =L6 -> 1660 | S6: Completed | T6: 20 | U6: Payment_Certificate_20260928170911.pdf | V6: PINV PIONEER LADY (INSPECTION ATTEND).pdf | W6: =IF(S6="Accrual",M6,"") | X6: =IF(S6="Receiving",M6,"") | Y6: =IF(S6="Received",M6,"") | AB6: =IF(S6="Completed",M6,"") -> 1660 | AC6: =IF(OR(AD6="船东付",AD6="待收"),0,M6) -> 0 | AD6: 待收
A7: 46285 | B7: 青岛通用物料申请 | C7: DPILT26009 | D7: DanTecs (HK) Marine Solutions Limited | E7: PILDT26009 | F7: DPILT26009-PIONEER LADY 订单确认报告_20260929101940.pdf | G7: 4113.43 | H7: 1 | I7: 4113.43 | J7: 2000005 | K7: 46283 | L7: 4113.43 | M7: 4113.43 | Q7: 46283 | R7: 46313 | S7: Received | V7: DPILT26009__INVOICE.pdf | W7: =IF(S7="Accrual",M7,"") | X7: =IF(S7="Receiving",M7,"") | Y7: =IF(S7="Received",M7,"") -> 4113.43 | Z7: =IF(S7="Approved",M7,"") | AA7: =IF(S7="Paying",M7,"") | AB7: =IF(S7="Completed",M7,"") | AC7: =IF(OR(AD7="船东付",AD7="待收"),0,M7) -> 0 | AD7: 待收
A8: 46272 | B8: 青岛港采购油漆 | C8: DPILT26008 | D8: DanTecs (HK) Marine Solutions Limited | E8: PILDT26008 | F8: Pioneer Lady 船舶申请订单确认报告(DPILT26008)(1).pdf | G8: 12974.8 | H8: 1 | I8: =G8*H8 -> 12974.8 | J8: 2000004 | K8: 46283 | L8: =I8 -> 12974.8 | M8: 12974.8 | Q8: 46283 | R8: 46313 | S8: Received | V8: DPILT26008__INVOICE.pdf | W8: =IF(S8="Accrual",M8,"") | X8: =IF(S8="Receiving",M8,"") | Y8: =IF(S8="Received",M8,"") -> 12974.8 | AB8: =IF(S8="Completed",M8,"") | AC8: =IF(OR(AD8="船东付",AD8="待收"),0,M8) -> 0 | AD8: 待收
A9: 46272 | B9: 岚桥港舱盖 UT 超声波检验费-Owner Paid | D9: REASUN INSURANCE SURVEYORS & ADJUSTERS CO., LTD | E9: SY2026080042LND | G9: 1200 | H9: 1 | I9: =G9*H9 -> 1200 | J9: 4000014 | K9: 46266 | L9: =I9 -> 1200 | M9: =L9 -> 1200 | V9: DEBIT NOTE---SY2026080042LND(MV PIONEER LADY USHCT).pdf | W9: =IF(S9="Accrual",M9,"") | X9: =IF(S9="Receiving",M9,"") | Y9: =IF(S9="Received",M9,"") | AB9: =IF(S9="Completed",M9,"") | AC9: =IF(OR(AD9="船东付",AD9="待收"),0,M9) -> 0 | AD9: 船东付
A10: 46269 | B10: 8 月份船员海外换班费 | D10: Top Marine Limited | G10: 12501.04 | H10: 1 | I10: =G10*H10 -> 12501.04 | J10: 1000090 | L10: =I10 -> 12501.04 | M10: =L10 -> 12501.04 | S10: Completed | U10: 船员换班，工资，船旗证书合并支付 | V10: 8 月份船员海外换班费(1)(1).pdf | W10: =IF(S10="Accrual",M10,"") | X10: =IF(S10="Receiving",M10,"") | Y10: =IF(S10="Received",M10,"") | AB10: =IF(S10="Completed",M10,"") -> 12501.04 | AC10: =IF(OR(AD10="船东付",AD10="待收"),0,M10) -> 12501.04 | AD10: 已收
A11: 46266 | B11: 岚桥加淡水200吨 | D11: CTM | G11: 1400 | H11: 1 | I11: =G11*H11 -> 1400 | J11: 6000001 | K11: =A11 -> 46266 | L11: =I11 -> 1400 | M11: =L11 -> 1400 | S11: Completed | V11: 岚桥加淡水费用1400美元.pdf | W11: =IF(S11="Accrual",M11,"") | X11: =IF(S11="Receiving",M11,"") | Y11: =IF(S11="Received",M11,"") | Z11: =IF(S11="Approved",M11,"") | AA11: =IF(S11="Paying",M11,"") | AB11: =IF(S11="Completed",M11,"") -> 1400 | AC11: =IF(OR(AD11="船东付",AD11="待收"),0,M11) -> 0 | AD11: 待收
A12: 46265 | B12: 8月份客餐费用支出 | D12: CTM | G12: 662 | H12: 1 | I12: =G12*H12 -> 662 | J12: 1000002 | L12: =I12 -> 662 | M12: =L12 -> 662 | S12: Completed | V12: 8月份客餐费用支出.pdf | W12: =IF(S12="Accrual",M12,"") | X12: =IF(S12="Receiving",M12,"") | Y12: =IF(S12="Received",M12,"") | Z12: =IF(S12="Approved",M12,"") | AA12: =IF(S12="Paying",M12,"") | AB12: =IF(S12="Completed",M12,"") -> 662 | AC12: =IF(OR(AD12="船东付",AD12="待收"),0,M12) -> 662 | AD12: 已收
A13: 46257 | B13: HOMONHON水手张善钧购药支出 | D13: CTM | G13: 733 | H13: 1 | I13: =G13*H13 -> 733 | J13: 1000006 | L13: =I13 -> 733 | M13: =L13 -> 733 | S13: Completed | V13: HOMONHON张善钧购药支出.pdf | X13: =IF(S13="Receiving",M13,"") | Y13: =IF(S13="Received",M13,"") | Z13: =IF(S13="Approved",M13,"") | AA13: =IF(S13="Paying",M13,"") | AB13: =IF(S13="Completed",M13,"") -> 733 | AC13: =IF(OR(AD13="船东付",AD13="待收"),0,M13) -> 733 | AD13: 已收
A14: 46251 | B14: V2605扫洗舱劳务费 | D14: CTM | G14: 1125 | H14: 1 | I14: =G14*H14 -> 1125 | J14: 9000001 | L14: =I14 -> 1125 | M14: =L14 -> 1125 | S14: Completed | V14: PAYMENT LIST OF V2605 HOLD CLEANING BONUS.pdf | W14: =IF(S14="Accrual",M14,"") | X14: =IF(S14="Receiving",M14,"") | Y14: =IF(S14="Received",M14,"") | Z14: =IF(S14="Approved",M14,"") | AA14: =IF(S14="Paying",M14,"") | AB14: =IF(S14="Completed",M14,"") -> 1125 | AC14: =IF(OR(AD14="船东付",AD14="待收"),0,M14) -> 1125 | AD14: 已收
A15: 46234 | B15: GRESIK加淡水100吨 | D15: CTM | G15: 1350 | H15: 1 | I15: =G15*H15 -> 1350 | J15: 6000001 | K15: 46234 | L15: =I15 -> 1350 | M15: =L15 -> 1350 | S15: Completed | V15: Gresik加淡水100吨.pdf | W15: =IF(S15="Accrual",M15,"") | X15: =IF(S15="Receiving",M15,"") | Y15: =IF(S15="Received",M15,"") | Z15: =IF(S15="Approved",M15,"") | AA15: =IF(S15="Paying",M15,"") | AB15: =IF(S15="Completed",M15,"") -> 1350 | AC15: =IF(OR(AD15="船东付",AD15="待收"),0,M15) -> 1350 | AD15: 已收
X16: =IF(S17="Receiving",M17,"")
AE18: =AB11+Y8+Y7+AB6+AB5 -> 20397.23

Sheet Take-Over Cost
A1: 入账日期 | B1: 类型 | C1: RQA | D1: Supplier | E1: PO Nos | F1: Pay. Approval | G1: PO Current | H1: Rating | I1: PO Amount (USD) | J1: Account Code | K1: GRN/Date | L1: GRN Amount(USD) | M1: Invoice Amount(USD) | N1: C/N,Accural | O1: C/N Profit | P1: Profit | Q1: Invoice Date | R1: Due Date | S1: Payment Status | T1: Bank Charge | U1: Bank Slip | V1: Attachement | W1: Accrual | X1: Receiving | Y1: Received | Z1: Approved | AA1: Paying | AB1: Completed | AC1: 已收 | AD1: 已开票 | AE1: 待收 | AF1: 船东付
C2: Receiving | D2: Received | E2: Approved | G2: Paying | H2: Completed | I2: =SUM(I3:I127) -> 29734.81 | L2: =SUM(L3:L127) -> 29734.81 | M2: =SUM(M3:M127) -> 28955.87 | N2: =SUM(N3:N128) -> 0 | O2: =SUM(O3:O128) -> 0 | P2: =SUM(P3:P128) -> 0 | T2: =SUM(T3:T127) -> 52.48 | V2: Invoices | W2: =SUM(W3:W127) -> 7546.85 | X2: =SUM(X3:X127) -> 0 | Y2: =SUM(Y3:Y127) -> 6183.42 | Z2: =SUM(Z3:Z127) -> 0 | AA2: =SUM(AA3:AA127) -> 0 | AB2: =SUM(AB3:AB127) -> 12376.24 | AC2: =SUM(W2:AB2)+T2 -> 26158.99 | AD2: 备注
W3: =IF(S3="Accrual",M3,"") | X3: =IF(S3="Receiving",M3,"") | Y3: =IF(S3="Received",M3,"") | Z3: =IF(S3="Approved",M3,"") | AA3: =IF(S3="Paying",M3,"") | AB3: =IF(S3="Completed",M3,"")
A4: 46286 | B4: 2026年6，7，8月季度自修奖金支出 | D4: CTM | G4: 2000 | H4: 1 | I4: =G4*H4 -> 2000 | J4: 10000007 | K4: =A4 -> 46286 | L4: =I4 -> 2000 | M4: =L4 -> 2000 | S4: Completed | V4: 678月自修奖金支出3000美元.pdf | W4: =IF(S4="Accrual",M4,"") | X4: =IF(S4="Receiving",M4,"") | Y4: =IF(S4="Received",M4,"") | Z4: =IF(S4="Approved",M4,"") | AA4: =IF(S4="Paying",M4,"") | AB4: =IF(S4="Completed",M4,"") -> 2000 | AC4: =IF(OR(AD4="船东付",AD4="待收"),0,M4) -> 0 | AD4: 待收
A5: 46284 | B5: 青岛港加工缆车刹车操作杆费用-周琦支付RMB3500 | G5: 522.51 | H5: 1 | I5: =G5*H5 -> 522.51 | J5: 4000002 | L5: =I5 -> 522.51 | M5: =L5 -> 522.51 | V5: 20260919_青岛港加工缆车刹车操作杆费用（RMB3500）522.51USD.pdf | W5: =IF(S5="Accrual",M5,"") | X5: =IF(S5="Receiving",M5,"") | AB5: =IF(S5="Completed",M5,"") | AC5: =IF(OR(AD5="船东付",AD5="待收"),0,L5) -> 0 | AD5: 待收
A6: 46281 | B6: 青岛港冰机修理 | D6: GORDON MARINE REFRIGERATION CO.,LTD, | F6: Pioneer Lady 船舶申请订单确认报告(EPILP26026冰机修理)(1)(1).pdf | G6: 28650 | H6: 0.149 | I6: =G6*H6 -> 4268.85 | J6: 4000005 | L6: =I6 -> 4268.85 | M6: =L6 -> 4268.85 | S6: Accrual | V6: PIONEER LADY -形式发票(2).pdf | W6: =IF(S6="Accrual",M6,"") -> 4268.85 | X6: =IF(S6="Receiving",M6,"") | Y6: =IF(S6="Received",M6,"") | Z6: =IF(S6="Approved",M6,"") | AA6: =IF(S6="Paying",M6,"") | AB6: =IF(S6="Completed",M6,"") | AC6: =IF(OR(AD6="船东付",AD6="待收"),0,L6) -> 0 | AD6: 待收
A7: 46281 | B7: 冰种+码头管理费 | C7: EPILT26004 | D7: DanTecs (HK) Marine Solutions Limited | E7: PILET26004 | F7: EPILT26004订单确认报告_20260930161523.pdf | G7: 560 | H7: 1 | I7: 560 | J7: 2000008 | L7: 560 | M7: 560 | S7: Received | V7: EPILT26004__INVOICE.pdf | W7: =IF(S7="Accrual",M7,"") | X7: =IF(S7="Receiving",M7,"") | Y7: =IF(S7="Received",M7,"") -> 560 | Z7: =IF(S7="Approved",M7,"") | AA7: =IF(S7="Paying",M7,"") | AB7: =IF(S7="Completed",M7,"") | AC7: =IF(OR(AD7="船东付",AD7="待收"),0,L7) -> 0 | AD7: 待收
A8: 46262 | B8: 甲板克令吊 | C8: EPILP26019 | D8: DanTecs (HK) Marine Solutions Limited | E8: PILEP26019 | F8: EPILP26019-PIONEER LADY 订单确认报告_20260923151916.pdf | G8: 3206.79 | H8: 1 | I8: 3206.79 | J8: 3000004 | L8: 3206.79 | M8: 1620.58 | Q8: 46283 | R8: 46313 | S8: Received | V8: EPILP26019__INVOICE.pdf | W8: =IF(S8="Accrual",M8,"") | X8: =IF(S8="Receiving",M8,"") | Y8: =IF(S8="Received",M8,"") -> 1620.58 | Z8: =IF(S8="Approved",M8,"") | AA8: =IF(S8="Paying",M8,"") | AB8: =IF(S8="Completed",M8,"") | AC8: =IF(OR(AD8="船东付",AD8="待收"),0,L8) -> 0 | AD8: 待收
A9: 46262 | B9: 汽笛+运费 | C9: EPILP26015 | D9: ZHOUSHAN HAISHAN MARINE SERVICE CO., LIMITED | E9: PILEP26015 | F9: EPILP26015-PIONEER LADY 订单确认报告_20260923143458.pdf | G9: 1127.37 | H9: 1 | I9: =G9*H9 -> 1127.37 | J9: 3000006 | L9: =I9 -> 1127.37 | M9: =L9+100 -> 1227.37 | Q9: 46287 | S9: Received | U9: EPILP26015 ＋运费发票.pdf | V9: PIONEER LADY 备件发票.pdf | X9: =IF(S9="Receiving",M9,"") | Y9: =IF(S9="Received",M9,"") -> 1227.37 | Z9: =IF(S9="Approved",M9,"") | AA9: =IF(S9="Paying",M9,"") | AB9: =IF(S9="Completed",M9,"") | AC9: =IF(OR(AD9="船东付",AD9="待收"),0,L9) -> 0 | AD9: 待收
A10: 46262 | B10: 通导设备修理 | D10: Fuzhou Changxin Electronic Co.,Ltd | F10: Pioneer Lady 船舶申请订单确认报告(驾驶台设备修理).pdf | G10: 17900 | H10: 0.149 | I10: =G10*H10 -> 2667.1 | J10: 4000010 | L10: =I10 -> 2667.1 | M10: =22000*0.149 -> 3278 | S10: Accrual | V10: PIONEER LADY通导修理等结算(2).pdf | W10: =IF(S10="Accrual",M10,"") -> 3278 | X10: =IF(S10="Receiving",M10,"") | Y10: =IF(S10="Received",M10,"") | Z10: =IF(S10="Approved",M10,"") | AA10: =IF(S10="Paying",M10,"") | AB10: =IF(S10="Completed",M10,"") | AC10: =IF(OR(AD10="船东付",AD10="待收"),0,L10) -> 0 | AD10: 待收
A11: 46262 | B11: 压载水处理系统 | C11: EPILP26017 | D11: DanTecs (HK) Marine Solutions Limited | E11: PILEP26017 | F11: EPILP26017-PIONEER LADY 订单确认报告_20260923150418.pdf | G11: 1741.1 | H11: 1 | I11: 1741.1 | J11: 3000010 | L11: 1741.1 | M11: 1837.47 | Q11: 46283 | R11: 46313 | S11: Received | V11: EPILP26017__INVOICE.pdf | W11: =IF(S11="Accrual",M11,"") | X11: =IF(S11="Receiving",M11,"") | Y11: =IF(S11="Received",M11,"") -> 1837.47 | Z11: =IF(S11="Approved",M11,"") | AA11: =IF(S11="Paying",M11,"") | AB11: =IF(S11="Completed",M11,"") | AC11: =IF(OR(AD11="船东付",AD11="待收"),0,L11) -> 0 | AD11: 待收
A12: 46262 | B12: 液压块 | C12: EPILP26024 | D12: DanTecs (HK) Marine Solutions Limited | E12: PILEP26024 | F12: EPILP26024-PIONEER LADY 订单确认报告_20260923155407.pdf | G12: 653 | H12: 1 | I12: =G12*H12 -> 653 | J12: 3000004 | L12: =I12 -> 653 | M12: =L12 -> 653 | Q12: 46283 | R12: 46313 | S12: Received | V12: EPILP26024__INVOICE.pdf | W12: =IF(S12="Accrual",M12,"") | X12: =IF(S12="Receiving",M12,"") | Y12: =IF(S12="Received",M12,"") -> 653 | Z12: =IF(S12="Approved",M12,"") | AA12: =IF(S12="Paying",M12,"") | AB12: =IF(S12="Completed",M12,"") | AC12: =IF(OR(AD12="船东付",AD12="待收"),0,L12) -> 0 | AD12: 待收
A13: 46262 | B13: 2号滑油分油机马达 | C13: EPILP26025 | D13: DanTecs (HK) Marine Solutions Limited | E13: PILEP26025 | F13: EPILP26025-PIONEER LADY 订单确认报告_20260923155439.pdf | G13: 285 | H13: 1 | I13: =G13 -> 285 | J13: 3000012 | L13: =I13 -> 285 | M13: =L13 -> 285 | Q13: 46283 | R13: 46313 | S13: Received | V13: EPILP26025__INVOICE.pdf | W13: =IF(S13="Accrual",M13,"") | X13: =IF(S13="Receiving",M13,"") | Y13: =IF(S13="Received",M13,"") -> 285 | Z13: =IF(S13="Approved",M13,"") | AA13: =IF(S13="Paying",M13,"") | AB13: =IF(S13="Completed",M13,"") | AC13: =IF(OR(AD13="船东付",AD13="待收"),0,L13) -> 0 | AD13: 待收
A14: 46261 | B14: 冰机压缩机一台—周总支付 | D14: GORDON MARINE REFRIGERATION CO.,LTD | F14: Pioneer Lady 船舶申请订单确认报告(EPILP26026冰机修理)(1).pdf | G14: 12500 | H14: 0.148148 | I14: =G14*H14 -> 1851.85 | J14: 3000007 | L14: =I14 -> 1851.85 | M14: 1851.85 | V14: PIONEER LADY -形式发票(1).pdf | W14: =IF(S14="Accrual",M14,"") | X14: =IF(S14="Receiving",M14,"") | Y14: =IF(S14="Received",M14,"") | Z14: =IF(S14="Approved",M14,"") | AA14: =IF(S14="Paying",M14,"") | AB14: =IF(S14="Completed",M14,"") | AC14: =IF(OR(AD14="船东付",AD14="待收"),0,L14) -> 1851.85 | AD14: 已收
A15: 46252 | B15: 气瓶押金 | D15: Wilhelmsen Ships Service AS | E15: S10329491 | G15: 8121.24 | H15: 1 | I15: =G15*H15 -> 8121.24 | J15: 6000016 | L15: =I15 -> 8121.24 | M15: =L15 -> 8121.24 | S15: Completed | T15: 32.48 | U15: 20260903_气瓶押金8,121.24 USD_付款凭证.pdf | V15: Proforma Invoice - PIONEER LADY(1).pdf | X15: =IF(S15="Receiving",M15,"") | Y15: =IF(S15="Received",M15,"") | Z15: =IF(S15="Approved",M15,"") | AA15: =IF(S15="Paying",M15,"") | AB15: =IF(S15="Completed",M15,"") -> 8121.24 | AC15: =IF(OR(AD15="船东付",AD15="待收"),0,L15) -> 8121.24 | AD15: 已收 | AE15: =Y13+Y12+Y11+W10+Y9+Y8+Y7+W6+W5+AB4 -> #VALUE!
A16: 46247 | B16: Water ingress detection 备件 - 潜水式压力变送器 LMK457 | D16: OCEAN FLEET (HK) SPARE PARTS CO., LIMITED | E16: PILM26052101 | G16: 475 | H16: 1 | I16: =G16*H16 -> 475 | J16: 3000012 | L16: =I16 -> 475 | M16: =L16 -> 475 | Q16: 46247 | R16: 46277 | V16: PIONEERLADY PILM26052101water ingress detection OCEAN FLEET(2).pdf | W16: =IF(S16="Accrual",M16,"") | X16: =IF(S16="Receiving",M16,"") | Y16: =IF(S16="Received",M16,"") | Z16: =IF(S16="Approved",M16,"") | AA16: =IF(S16="Paying",M16,"") | AB16: =IF(S16="Completed",M16,"") | AC16: =IF(OR(AD16="船东付",AD16="待收"),0,L16) -> 0 | AD16: 船东付
A17: 46237 | B17: Vizada 通信订阅费（接船） | D17: TELEOCEAN INC | G17: 150 | H17: 1 | I17: =G17*H17 -> 150 | J17: 6000017 | K17: 46237 | L17: =I17 -> 150 | M17: =L17 -> 150 | N17: 0 | O17: 0 | P17: 0 | Q17: 46237 | R17: 46252 | S17: Completed | U17: 20260814TELEOCEAN INC2230付款凭证.pdf | V17: Invoice_PIONEER LADY_C Monthly_2026_07_21356047_Vizada.pdf | W17: =IF(S17="Accrual",M17,"") | X17: =IF(S17="Receiving",M17,"") | Y17: =IF(S17="Received",M17,"") | Z17: =IF(S17="Approved",M17,"") | AA17: =IF(S17="Paying",M17,"") | AB17: =IF(S17="Completed",M17,"") -> 150 | AC17: =IF(OR(AD17="船东付",AD17="待收"),0,L17) -> 150 | AD17: 已收
A18: 46234 | B18: AAIC 接船相关费用（年费+LOG+旗国激活+押金） | D18: TELEOCEAN INC | G18: 2080 | H18: 1 | I18: 2080 | J18: 6000014 | K18: 46234 | L18: =I18 -> 2080 | M18: =L18 -> 2080 | N18: 0 | O18: 0 | P18: 0 | Q18: 46234 | R18: 46249 | S18: Completed | T18: 20 | V18: Invoice_PIONEER LADY_AAIC_2026_07_21351855_AAIC.pdf | W18: =IF(S18="Accrual",M18,"") | X18: =IF(S18="Receiving",M18,"") | Y18: =IF(S18="Received",M18,"") | Z18: =IF(S18="Approved",M18,"") | AA18: =IF(S18="Paying",M18,"") | AB18: =IF(S18="Completed",M18,"") -> 2080 | AC18: =IF(OR(AD18="船东付",AD18="待收"),0,L18) -> 2080 | AD18: 已收
A19: 46233 | B19: 制作新船章两枚 | D19: CTM | G19: 25 | H19: 1 | I19: =G19*H19 -> 25 | J19: 6000013 | K19: 46234 | L19: =I19 -> 25 | M19: =L19 -> 25 | N19: 0 | O19: 0 | P19: 0 | S19: Completed | V19: 制作两枚船章(1).pdf | W19: =IF(S19="Accrual",M19,"") | X19: =IF(S19="Receiving",M19,"") | Y19: =IF(S19="Received",M19,"") | Z19: =IF(S19="Approved",M19,"") | AA19: =IF(S19="Paying",M19,"") | AB19: =IF(S19="Completed",M19,"") -> 25 | AC19: =IF(OR(AD19="船东付",AD19="待收"),0,L19) -> 25 | AD19: 已收

Sheet BMA Flag Change
A1: 入账日期 | B1: 类型 | C1: RQA | D1: Supplier | E1: PO Nos | F1: Pay. Approval | G1: PO Current | H1: Rating | I1: PO Amount (USD) | J1: Account Code | K1: GRN/Date | L1: GRN Amount(USD) | M1: Invoice Amount(USD) | N1: C/N,Accural | O1: C/N Profit | P1: Profit | Q1: Invoice Date | R1: Due Date | S1: Payment Status | T1: Bank Charge | U1: Attachement | V1: Bank Slip | W1: Attachement | X1: Accrual | Y1: Receiving | Z1: Received | AA1: Approved | AB1: Paying | AC1: Completed | AD1: 已收 | AE1: 已开票 | AF1: 待收 | AG1: 船东付
C2: Receiving | D2: Received | E2: Approved | G2: Paying | H2: Completed | I2: =SUM(I3:I25) -> 52356.58 | L2: =SUM(L3:L25) -> 52356.58 | M2: =SUM(M3:M25) -> 52356.58 | N2: =SUM(N3:N25) -> 0 | O2: =SUM(O3:O25) -> 0 | P2: =SUM(P3:P25) -> 0 | T2: =SUM(T3:T25) -> 60.9 | U2: =SUM(U3:U25) -> 0 | W2: =SUM(W3:W25) -> 0 | X2: =SUM(X3:X25) -> 0 | Y2: =SUM(Y3:Y25) -> 0 | Z2: =SUM(Z3:Z25) -> 185.76 | AA2: =SUM(AA3:AA25) -> 0 | AB2: =SUM(AB3:AB25) -> 0 | AC2: =SUM(AC3:AC25) -> 26095 | AD2: =SUM(X2:AC2)+T2 -> 26341.66 | AE2: 备注
X3: =IF(S3="Accrual",M3,"") | Y3: =IF(S3="Receiving",M3,"") | Z3: =IF(S3="Received",M3,"") | AA3: =IF(S3="Approved",M3,"") | AB3: =IF(S3="Paying",M3,"") | AC3: =IF(S3="Completed",M3,"")
X4: =IF(S4="Accrual",M4,"") | Y4: =IF(S4="Receiving",M4,"") | Z4: =IF(S4="Received",M4,"") | AA4: =IF(S4="Approved",M4,"") | AB4: =IF(S4="Paying",M4,"") | AC4: =IF(S4="Completed",M4,"")
X5: =IF(S5="Accrual",M5,"") | Y5: =IF(S5="Receiving",M5,"") | Z5: =IF(S5="Received",M5,"") | AA5: =IF(S5="Approved",M5,"") | AB5: =IF(S5="Paying",M5,"") | AC5: =IF(S5="Completed",M5,"")
X6: =IF(S6="Accrual",M6,"") | Y6: =IF(S6="Receiving",M6,"") | Z6: =IF(S6="Received",M6,"") | AA6: =IF(S6="Approved",M6,"") | AB6: =IF(S6="Paying",M6,"") | AC6: =IF(S6="Completed",M6,"")
X7: =IF(S7="Accrual",M7,"") | Y7: =IF(S7="Receiving",M7,"") | Z7: =IF(S7="Received",M7,"") | AA7: =IF(S7="Approved",M7,"") | AB7: =IF(S7="Paying",M7,"") | AC7: =IF(S7="Completed",M7,"")
X8: =IF(S8="Accrual",M8,"") | Y8: =IF(S8="Receiving",M8,"") | Z8: =IF(S8="Received",M8,"") | AA8: =IF(S8="Approved",M8,"") | AB8: =IF(S8="Paying",M8,"") | AC8: =IF(S8="Completed",M8,"")
X9: =IF(S9="Accrual",M9,"") | Y9: =IF(S9="Receiving",M9,"") | Z9: =IF(S9="Received",M9,"") | AA9: =IF(S9="Approved",M9,"") | AB9: =IF(S9="Paying",M9,"") | AC9: =IF(S9="Completed",M9,"")
X10: =IF(S10="Accrual",M10,"") | Y10: =IF(S10="Receiving",M10,"") | Z10: =IF(S10="Received",M10,"") | AA10: =IF(S10="Approved",M10,"") | AB10: =IF(S10="Paying",M10,"") | AC10: =IF(S10="Completed",M10,"")
X11: =IF(S11="Accrual",M11,"") | Y11: =IF(S11="Receiving",M11,"") | Z11: =IF(S11="Received",M11,"") | AA11: =IF(S11="Approved",M11,"") | AB11: =IF(S11="Paying",M11,"") | AC11: =IF(S11="Completed",M11,"")
A12: 46286 | B12: Termination of FME | D12: The LISCR Trust Company | F12: Pioneer Lady 船舶申请订单确认报告(DPILT-LISCR)(1)_20260923115119.pdf | G12: 300 | H12: 1 | I12: =G12*H12 -> 300 | J12: 9000005 | L12: =I12 -> 300 | M12: =L12 -> 300 | Q12: 46285 | S12: Completed | V12: 同下合并支付 | W12: PRO-FORMA INVOICE.pdf | X12: =IF(S12="Accrual",M12,"") | Z12: =IF(S12="Received",M12,"") | AC12: =IF(S12="Completed",M12,"") -> 300 | AD12: =IF(OR(AE12="船东付",AE12="待收"),0,M12) -> 0 | AE12: 待收
A13: 46286 | B13: LISCR Annual Registration+Agent Fee | D13: The LISCR Trust Company | F13: Pioneer Lady 船舶申请订单确认报告(DPILT-LISCR)(2)_20260923115309.pdf | G13: 1050 | H13: 1 | I13: =G13*H13 -> 1050 | J13: 9000005 | L13: =I13 -> 1050 | M13: =L13 -> 1050 | Q13: 46183 | R13: 46254 | S13: Completed | T13: 20 | V13: Payment_Certificate_20260922163203.pdf | W13: Annual Fee Invoice# 2431470.pdf | X13: =IF(S13="Accrual",M13,"") | Z13: =IF(S13="Received",M13,"") | AC13: =IF(S13="Completed",M13,"") -> 1050 | AD13: =IF(OR(AE13="船东付",AE13="待收"),0,M13) -> 0 | AE13: 待收
A14: 46269 | B14: BMA 换旗相关证书费用 | D14: Top Marine Limited | G14: 2565 | H14: 1 | I14: =G14*H14 -> 2565 | J14: 9000000 | L14: =I14 -> 2565 | M14: =L14 -> 2565 | S14: Completed | V14: 船员换班，工资，船旗证书合并支付 | W14: PIONEER LADY 8月证书费用.pdf | X14: =IF(S14="Accrual",M14,"") | Z14: =IF(S14="Received",M14,"") | AB14: =IF(S14="Paying",M14,"") | AC14: =IF(S14="Completed",M14,"") -> 2565 | AD14: =IF(OR(AE14="船东付",AE14="待收"),0,M14) -> 2565 | AE14: 已收
A15: 46266 | B15: 海事海关系统更改费用 | D15: CTM | G15: 375 | H15: 1 | I15: =G15*H15 -> 375 | J15: 6000011 | K15: =A15 -> 46266 | L15: =I15 -> 375 | M15: =L15 -> 375 | S15: Completed | W15: 海事海关系统更改费用375美元.pdf | X15: =IF(S15="Accrual",M15,"") | Y15: =IF(S15="Received",M15,"") | Z15: =IF(S15="Received",M15,"") | AA15: =IF(S15="Paying",M15,"") | AB15: =IF(S15="Paying",M15,"") | AC15: =IF(S15="Completed",M15,"") -> 375 | AE15: 待收
A16: 46247 | B16: BMA Flag Statutory Record Book | D16: DANTECS (HK) MARINE SOLUTIONS LIMITED | G16: 185.76 | H16: 1 | I16: =G16*H16 -> 185.76 | J16: 2000007 | L16: =I16 -> 185.76 | M16: =L16 -> 185.76 | S16: Received | W16: 20260813巴哈马国旗法定记录本__INVOICE.pdf | X16: =IF(S16="Accrual",M16,"") | Y16: =IF(S16="Receiving",M16,"") | Z16: =IF(S16="Received",M16,"") -> 185.76 | AA16: =IF(S16="Approved",M16,"") | AB16: =IF(S16="Paying",M16,"") | AC16: =IF(S16="Completed",M16,"") | AD16: =IF(OR(AE16="船东付",AE16="待收"),0,M16) -> 185.76 | AE16: 已收
A17: 46241 | B17: Flag Change Radio Survey Charge | D17: Fuzhou Changxin Electronic Co.,Ltd | G17: 10225 | H17: 1 | I17: =G17*H17 -> 10225 | J17: 4000010 | L17: =I17 -> 10225 | M17: =L17 -> 10225 | S17: Completed | T17: 40.9 | V17: MSTS_PIONEER LADY20260731_泗水服务付款凭证(1).pdf | W17: 20260469 - Fuzhou C hangzin Electronic (PIONEER LADY)(2).pdf | X17: =IF(S17="Accrual",M17,"") | Y17: =IF(S17="Receiving",M17,"") | Z17: =IF(S17="Received",M17,"") | AA17: =IF(S17="Approved",M17,"") | AB17: =IF(S17="Paying",M17,"") | AC17: =IF(S17="Completed",M17,"") -> 10225 | AD17: =IF(OR(AE17="船东付",AE17="待收"),0,M17) -> 10225 | AE17: 已收
A18: 46238 | B18: 改船籍港特殊劳务费200美元 | D18: CTM | G18: 200 | H18: 1 | I18: =G18*H18 -> 200 | J18: 9990001 | K18: 46238 | L18: =I18 -> 200 | M18: =L18 -> 200 | S18: Completed | W18: 改船籍港特殊劳务费200美元(1).pdf | X18: =IF(S18="Accrual",M18,"") | Y18: =IF(S18="Receiving",M18,"") | Z18: =IF(S18="Received",M18,"") | AA18: =IF(S18="Approved",M18,"") | AB18: =IF(S18="Paying",M18,"") | AC18: =IF(S18="Completed",M18,"") -> 200 | AD18: =IF(OR(AE18="船东付",AE18="待收"),0,M18) -> 200 | AE18: 已收
A19: 46238 | B19: BMA Flag register Fee-Owner Paid | D19: OCEAN QUEEN SHIPPING CO.,LTD. | G19: 10769.64 | H19: 1 | I19: =G19*H19 -> 10769.64 | J19: 9000000 | L19: =I19 -> 10769.64 | M19: =L19 -> 10769.64 | X19: =IF(S19="Accrual",M19,"") | Y19: =IF(S19="Receiving",M19,"") | Z19: =IF(S19="Received",M19,"") | AA19: =IF(S19="Approved",M19,"") | AB19: =IF(S19="Paying",M19,"") | AC19: =IF(S19="Completed",M19,"") | AD19: =IF(OR(AE19="船东付",AE19="待收"),0,M19) -> 0 | AE19: 船东付
A20: 46235 | B20: LR船检两名外锚地登离船代理费用支出 | D20: CTM | G20: 9230 | H20: 1 | I20: =G20*H20 -> 9230 | J20: 9990001 | K20: 46236 | L20: =I20 -> 9230 | M20: =L20 -> 9230 | S20: Completed | W20: LR 两名船检猫的登离船代理费用支出(1).pdf | X20: =IF(S20="Accrual",M20,"") | Y20: =IF(S20="Receiving",M20,"") | Z20: =IF(S20="Received",M20,"") | AA20: =IF(S20="Approved",M20,"") | AB20: =IF(S20="Paying",M20,"") | AC20: =IF(S20="Completed",M20,"") -> 9230 | AD20: =IF(OR(AE20="船东付",AE20="待收"),0,M20) -> 9230 | AE20: 已收
A21: 46234 | B21: LISCR Deletion Overtime Cost-Owner Paid | D21: LISCR Flag | G21: 1435 | H21: 1 | I21: =G21*H21 -> 1435 | J21: 9000000 | L21: =I21 -> 1435 | M21: =L21 -> 1435 | X21: =IF(S21="Accrual",M21,"") | Y21: =IF(S21="Receiving",M21,"") | Z21: =IF(S21="Received",M21,"") | AA21: =IF(S21="Approved",M21,"") | AB21: =IF(S21="Paying",M21,"") | AC21: =IF(S21="Completed",M21,"") | AD21: =IF(OR(AE21="船东付",AE21="待收"),0,M21) -> 0 | AE21: 船东付
A22: 46234 | B22: GMDSS年检共工程师登离船代理费用支出 | D22: CTM | G22: 2150 | H22: 1 | I22: =G22*H22 -> 2150 | J22: 9990001 | K22: 46235 | L22: =I22 -> 2150 | M22: =L22 -> 2150 | S22: Completed | W22: GMDSS年检工程师登离轮代理费支出(1).pdf | X22: =IF(S22="Accrual",M22,"") | Y22: =IF(S22="Receiving",M22,"") | Z22: =IF(S22="Received",M22,"") | AA22: =IF(S22="Approved",M22,"") | AB22: =IF(S22="Paying",M22,"") | AC22: =IF(S22="Completed",M22,"") -> 2150 | AD22: =IF(OR(AE22="船东付",AE22="待收"),0,M22) -> 2150 | AE22: 已收
A23: 46232 | B23: BMA Pre-inspection Fee-Owner Paid | D23: Intermaritime Group Services | G23: 6580 | H23: 1 | I23: =G23*H23 -> 6580 | J23: 9000000 | L23: =I23 -> 6580 | M23: =L23 -> 6580 | X23: =IF(S23="Accrual",M23,"") | Y23: =IF(S23="Receiving",M23,"") | Z23: =IF(S23="Received",M23,"") | AA23: =IF(S23="Approved",M23,"") | AB23: =IF(S23="Paying",M23,"") | AC23: =IF(S23="Completed",M23,"") | AD23: =IF(OR(AE23="船东付",AE23="待收"),0,M23) -> 0 | AE23: 船东付
A24: 46231 | B24: 招待费—周琦支付 | G24: 441.18 | H24: 1 | I24: =G24*H24 -> 441.18 | J24: 6000002 | L24: =I24 -> 441.18 | M24: =L24 -> 441.18 | W24: Invoice--Pioneer Lady PILEP260827-OF(1).docx | X24: =IF(S24="Accrual",M24,"") | Y24: =IF(S24="Receiving",M24,"") | Z24: =IF(S24="Received",M24,"") | AA24: =IF(S24="Approved",M24,"") | AB24: =IF(S24="Paying",M24,"") | AC24: =IF(S24="Completed",M24,"") | AD24: =IF(OR(AE24="船东付",AE24="待收"),0,M24) -> 441.18 | AE24: 已收
A25: 46227 | B25: LISCR Deletion Charge-Owner Paid | G25: 6850 | H25: 1 | I25: =G25*H25 -> 6850 | J25: 9000000 | L25: =I25 -> 6850 | M25: =L25 -> 6850 | X25: =IF(S25="Accrual",M25,"") | Y25: =IF(S25="Receiving",M25,"") | Z25: =IF(S25="Received",M25,"") | AA25: =IF(S25="Approved",M25,"") | AB25: =IF(S25="Paying",M25,"") | AC25: =IF(S25="Completed",M25,"") | AD25: =IF(OR(AE25="船东付",AE25="待收"),0,M25) -> 0 | AE25: 船东付
AE33: =155000+AE30 -> 155000

Sheet DD Cost
A1: 入账日期 | B1: 类型 | C1: RQA | D1: Supplier | E1: PO Nos | F1: PO Current | G1: Rating | H1: PO Amount (USD) | I1: Account Code | J1: GRN/Date | K1: GRN Amount(USD) | L1: Invoice Amount(USD) | M1: C/N,Accural | N1: C/N Profit | O1: Profit | P1: Invoice Date | Q1: Due Date | R1: Payment Status | S1: Bank Charge | T1: Attachement | U1: Attachement | V1: Accrual | W1: Receiving | X1: Received | Y1: Approved | Z1: Paying | AA1: Completed | AB1: 已收 | AC1: 已开票 | AD1: 待收 | AE1: 船东付
C2: Receiving | D2: Received | E2: Approved | F2: Paying | G2: Completed | H2: =SUM(H3:H24) -> 0 | I2: =SUM(I3:I24) -> 0 | J2: =SUM(J3:J24) -> 0 | K2: =SUM(K3:K24) -> 0 | L2: =SUM(L3:L24) -> 0 | M2: =SUM(M3:M24) -> 0 | N2: =SUM(N3:N24) -> 0 | O2: =SUM(O3:O24) -> 0 | Q2: =SUM(Q3:Q24) -> 0 | R2: =SUM(R3:R24) -> 0 | S2: =SUM(S3:S24) -> 0 | T2: =SUM(T3:T24) -> 0 | U2: =SUM(U3:U24) -> 0 | V2: =SUM(V3:V24) -> 0 | W2: =SUM(W3:W24) -> 0 | X2: =SUM(X3:X24) -> 0 | ... AA2: =SUM(AA3:AA24) -> 0 | AB2: =SUM(V2:AA2)+S2 -> 0 | AC2: 备注
V3: =IF(R3="Accrual",L3,"") | W3: =IF(R3="Receiving",L3,"") | X3: =IF(R3="Received",L3,"") | Y3: =IF(R3="Approved",L3,"") | Z3: =IF(R3="Paying",L3,"") | AA3: =IF(R3="Completed",L3,"")
V4: =IF(R4="Accrual",L4,"") | W4: =IF(R4="Receiving",L4,"") | X4: =IF(R4="Received",L4,"") | Y4: =IF(R4="Approved",L4,"") | Z4: =IF(R4="Paying",L4,"") | AA4: =IF(R4="Completed",L4,"")
V5: =IF(R5="Accrual",L5,"") | W5: =IF(R5="Receiving",L5,"") | X5: =IF(R5="Received",L5,"") | Y5: =IF(R5="Approved",L5,"") | Z5: =IF(R5="Paying",L5,"") | AA5: =IF(R5="Completed",L5,"")
V6: =IF(R6="Accrual",L6,"") | W6: =IF(R6="Receiving",L6,"") | X6: =IF(R6="Received",L6,"") | Y6: =IF(R6="Approved",L6,"") | Z6: =IF(R6="Paying",L6,"") | AA6: =IF(R6="Completed",L6,"")
V7: =IF(R7="Accrual",L7,"") | W7: =IF(R7="Receiving",L7,"") | X7: =IF(R7="Received",L7,"") | Y7: =IF(R7="Approved",L7,"") | Z7: =IF(R7="Paying",L7,"") | AA7: =IF(R7="Completed",L7,"")
V8: =IF(R8="Accrual",L8,"") | W8: =IF(R8="Receiving",L8,"") | X8: =IF(R8="Received",L8,"") | Y8: =IF(R8="Approved",L8,"") | Z8: =IF(R8="Paying",L8,"") | AA8: =IF(R8="Completed",L8,"")
V9: =IF(R9="Accrual",L9,"") | W9: =IF(R9="Receiving",L9,"") | X9: =IF(R9="Received",L9,"") | Y9: =IF(R9="Approved",L9,"") | Z9: =IF(R9="Paying",L9,"") | AA9: =IF(R9="Completed",L9,"")
V10: =IF(R10="Accrual",L10,"") | W10: =IF(R10="Receiving",L10,"") | X10: =IF(R10="Received",L10,"") | Y10: =IF(R10="Approved",L10,"") | Z10: =IF(R10="Paying",L10,"") | AA10: =IF(R10="Completed",L10,"")
V11: =IF(R11="Accrual",L11,"") | W11: =IF(R11="Receiving",L11,"") | X11: =IF(R11="Received",L11,"") | Y11: =IF(R11="Approved",L11,"") | Z11: =IF(R11="Paying",L11,"") | AA11: =IF(R11="Completed",L11,"")
V12: =IF(R12="Accrual",L12,"") | W12: =IF(R12="Receiving",L12,"") | X12: =IF(R12="Received",L12,"") | Y12: =IF(R12="Approved",L12,"") | Z12: =IF(R12="Paying",L12,"") | AA12: =IF(R12="Completed",L12,"")
V13: =IF(R13="Accrual",L13,"") | W13: =IF(R13="Receiving",L13,"") | X13: =IF(R13="Received",L13,"") | Y13: =IF(R13="Approved",L13,"") | Z13: =IF(R13="Paying",L13,"") | AA13: =IF(R13="Completed",L13,"")
V14: =IF(R14="Accrual",L14,"") | W14: =IF(R14="Receiving",L14,"") | X14: =IF(R14="Received",L14,"") | Y14: =IF(R14="Approved",L14,"") | Z14: =IF(R14="Paying",L14,"") | AA14: =IF(R14="Completed",L14,"")
... V24: =IF(R24="Accrual",L24,"") | W24: =IF(R24="Receiving",L24,"") | X24: =IF(R24="Received",L24,"") | Y24: =IF(R24="Approved",L24,"") | Z24: =IF(R24="Paying",L24,"") | AA24: =IF(R24="Completed",L24,"")

Sheet 分析
A1: 船名 | B1: 类型 | C1: RQA | D1: Supplier | E1: PO Nos | F1: PO Current | G1: Rating | H1: PO Amount (USD)
C2: Received | D2: Uploaded | E2: Approved | F2: Paying | G2: Completed | H2: =SUM(H4:H67) -> 0 | I2: Changes | J2: Owner | K2: Factor | M2: Lowest | N2: Reasonable | O2: Highest | R2: WAHSIN 结账
I3: Catalogue | J3: Agreement | K3: Place | L3: O/T | M3: =SUM(M4:M66) -> 0 | N3: =SUM(N4:N66) -> 0 | O3: =SUM(O4:O66) -> 0 | P3: Flag Change | R3: 7.3
G4: 1 | H4: =F4/G4 -> 0 | I4: Shipowner | J4: Take-over | K4: 0 | L4: 0 | M4: =H4 -> 0 | O4: =H4 -> 0 | P4: Non-Flag Change | R4: CNY | S4: =R3*S3 -> 0
G5: 1 | H5: =F5/G5 -> 0 | I5: Shipowner | J5: Take-over | K5: 0 | L5: 0 | M5: =H5 -> 0 | O5: =H5 -> 0 | P5: DOC Change | R5: 2401-2412
G6: 1 | H6: =F6/G6 -> 0 | I6: Shipowner | J6: Take-over | K6: 0 | L6: 0 | M6: =H6 -> 0 | O6: =H6 -> 0 | P6: RSO Change | R6: 0.45 | S6: =(-S5-S9) -> 0
G7: 1 | H7: =F7/G7 -> 0 | I7: Flag | J7: Take-over | K7: 0 | L7: 0 | M7: =H7 -> 0 | O7: =H7 -> 0 | P7: ITF-Yes | R7: 我USD | S7: =S5+S6 -> 0
G8: 1 | H8: =F8/G8 -> 0 | I8: Flag | J8: Take-over | K8: 0 | L8: 0 | M8: =H8 -> 0 | O8: =H8 -> 0 | P8: ITF-No | R8: 我CNY | S8: =R3*S7 -> 0
G9: 1 | H9: =F9/G9 -> 0 | I9: Shipowner | J9: Take-over | K9: 0 | L9: 0 | M9: =H9 -> 0 | O9: =H9 -> 0 | P9: ITF-OPEX | R9: 0.55 | S9: =R9*(-S5) -> 0
G10: 1 | H10: =F10/G10 -> 0 | I10: Flag | J10: Take-over | K10: 0 | L10: 0 | M10: =H10 -> 0 | O10: =H10 -> 0 | P10: Rightship-Yes | R10: 55%CNY | S10: =S9*R3 -> 0
G11: 1 | H11: =F11/G11 -> 0 | I11: Flag | J11: Take-over | K11: 0 | L11: 0 | M11: =H11 -> 0 | O11: =H11 -> 0 | P11: Rightship-No
G12: 1 | H12: =F12/G12 -> 0 | I12: Flag | J12: Take-over | K12: 0 | L12: 0 | M12: =H12 -> 0 | O12: =H12 -> 0 | P12: Rightship-OPEX
G13: 1 | H13: =F13/G13 -> 0 | I13: Flag | J13: Take-over | K13: 0 | L13: 0 | M13: =H13 -> 0 | O13: =H13 -> 0 | P13: Take-over
G14: 1 | H14: =F14/G14 -> 0 | I14: Flag | J14: Take-over | K14: 0 | L14: 0 | M14: =H14 -> 0 | O14: =H14 -> 0 | P14: OPEX | T14: SCORPIO WQ 付款申请
G15: 1 | H15: =F15/G15 -> 0 | I15: Flag | J15: Take-over | K15: 0 | L15: 0 | M15: =H15 -> 0 | O15: =H15 -> 0 | P15: Charge-Normal | T15: SCORPIO WQ 电子回单
G16: 1 | H16: =F16/G16 -> 0 | I16: Flag | J16: Take-over | K16: 0 | L16: 0 | M16: =H16 -> 0 | O16: =H16 -> 0 | P16: Charge-Subcharge | T16: SCORPIO WQ 银行流水明细
G17: 1 | H17: =F17/G17 -> 0 | I17: Flag | J17: Take-over | K17: 0 | L17: 0 | M17: =H17 -> 0 | O17: =H17 -> 0 | P17: Port | T17: SCORPIO WQ 核算,考核盈亏
G18: 1 | H18: =F18/G18 -> 0 | I18: Flag | J18: OPEX | K18: 0 | L18: 0 | O18: =H18 -> 0 | P18: Anchorage | T18: SCORPIO WQ 带章银行月结单
G19: 1 | H19: =F19/G19 -> 0 | I19: Flag | J19: OPEX | K19: 0 | L19: 0 | O19: =H19 -> 0 | P19: Working | T19: SCORPIO WQ 电子对账单
G20: 1 | H20: =F20/G20 -> 0 | I20: DOC | J20: Take-over | K20: 0 | L20: 0 | M20: 0 | O20: =H20 -> 0 | P20: Wenked | T20: 华兴银行账户资料
G21: 1 | H21: =F21/G21 -> 0 | I21: RSO | J21: Take-over | K21: 0 | L21: 0 | M21: =H21 -> 0 | O21: =H21 -> 0 | P21: Yes | T21: 公司注册文件存档
G22: 1 | H22: =F22/G22 -> 0 | I22: RSO | J22: Take-over | K22: 0 | L22: 0 | M22: =H22 -> 0 | O22: =H22 -> 0 | P22: No | T22: 审计报告
G23: 1 | H23: =F23/G23 -> 0 | I23: RSO | J23: Take-over | K23: 0 | L23: 0 | M23: =H23 -> 0 | O23: =H23 -> 0
G24: 1 | H24: =F24/G24 -> 0 | I24: RSO | J24: Take-over | K24: 0 | L24: 0 | M24: =H24 -> 0 | O24: =H24 -> 0
G25: 1 | H25: =F25/G25 -> 0 | I25: RSO | J25: Take-over | K25: 0 | L25: 0 | M25: =H25 -> 0 | O25: =H25 -> 0
G26: 1 | H26: =F26/G26 -> 0 | I26: DOC | J26: Take-over | K26: 0 | L26: 0 | M26: =H26 -> 0 | O26: =H26 -> 0
G27: 1 | H27: =F27/G27 -> 0 | I27: DOC | J27: Take-over | K27: 0 | L27: 0 | M27: =H27 -> 0 | O27: =H27 -> 0 | P27: Content | Q27: Yes/No
G28: 1 | H28: =F28/G28 -> 0 | I28: DOC | J28: Take-over | K28: 0 | L28: 0 | M28: =H28 -> 0 | O28: =H28 -> 0 | P28: Shipowner | Q28: Yes
G29: 1 | H29: =F29/G29 -> 0 | I29: DOC | J29: Take-over | K29: 0 | L29: 0 | M29: =H29 -> 0 | O29: =H29 -> 0 | P29: Flag | Q29: Yes
G30: 1 | H30: =F30/G30 -> 0 | I30: DOC | J30: Take-over | K30: 0 | L30: 0 | M30: =H30 -> 0 | O30: =H30 -> 0 | P30: RSO | Q30: Yes
G31: 1 | H31: =F31/G31 -> 0 | I31: DOC | J31: Take-over | K31: 0 | L31: 0 | M31: =H31 -> 0 | O31: =H31 -> 0 | P31: RO | Q31: No
G32: 1 | H32: =F32/G32 -> 0 | I32: DOC | J32: Take-over | K32: 0 | L32: 0 | M32: =H32 -> 0 | O32: =H32 -> 0 | P32: DOC | Q32: Yes
G33: 1 | H33: =F33/G33 -> 0 | I33: DOC | J33: Take-over | K33: 0 | L33: 0 | M33: =H33 -> 0 | O33: =H33 -> 0 | P33: Crew | Q33: Yes
G34: 1 | H34: =F34/G34 -> 0 | I34: DOC | J34: Take-over | K34: 0 | L34: 0.5 | M34: =H34*(1-L34) -> 0 | O34: =H34 -> 0 | P34: Shipname | Q34: Yes
G35: 1 | H35: =F35/G35 -> 0 | I35: Crew | J35: Take-over | K35: 0.3 | L35: 0 | M35: =H35 -> 0 | O35: =H35 -> 0 | P35: Spare Parts | Q35: Yes
G36: 1 | H36: =F36/G36 -> 0 | I36: Spare Parts | J36: Take-over | K36: 0.3 | L36: 0 | M36: =H36 -> 0 | O36: =H36 -> 0 | P36: Stores | Q36: Yes
G37: 1 | H37: =F37/G37 -> 0 | I37: Crew | J37: Take-over | K37: 0 | L37: 0 | M37: =H37*Q43/3 -> 0 | O37: =H37 -> 0 | P37: ITF | Q37: Yes
G38: 1 | H38: =F38/G38 -> 0 | I38: DOC | J38: Take-over | K38: 0.3 | L38: 0 | M38: =H38 -> 0 | O38: =H38 -> 0 | P38: Rightship(>14Year) | Q38: Yes
G39: 1 | H39: =F39/G39 -> 0 | I39: DOC | J39: Take-over | K39: 0.3 | L39: 0.5 | M39: =H39 -> 0 | O39: =H39 -> 0 | P39: P&I(>15Years) | Q39: Yes
G40: 1 | H40: =F40/G40 -> 0 | I40: Shipowner | J40: Take-over | K40: 0.3 | L40: 0.1 | M40: =H40 -> 0 | O40: =H40 -> 0 | P40: Place | Q40: Anchorage
G41: 1 | H41: =F41/G41 -> 0 | I41: Flag | J41: Take-over | K41: 0 | L41: 0 | M41: =H41 -> 0 | O41: =H41 -> 0 | P41: Time | Q41: Wenked
G42: 1 | H42: =F42/G42 -> 0 | I42: DOC | J42: Take-over | K42: 0 | L42: 0.5 | M42: =H42 -> 0 | O42: =H42 -> 0 | P42: Crew Ridding Days | Q42: 30
G43: 1 | H43: =F43/G43 -> 0 | I43: DOC | J43: OPEX | K43: 0 | L43: 0 | O43: =H43 -> 0 | P43: Crew Waiting Days | Q43: 1
G44: 1 | H44: =F44/G44 -> 0 | I44: DOC | J44: OPEX | K44: 0 | L44: 0 | O44: =H44 -> 0
G45: 1 | H45: =F45/G45 -> 0 | I45: Crew | J45: Take-over | K45: 0 | L45: 0 | M45: =H45 -> 0 | O45: =H45 -> 0
G46: 1 | H46: =F46/G46 -> 0 | I46: Crew | J46: Take-over | K46: 0 | L46: 0 | M46: =H46 -> 0 | O46: =H46 -> 0
G47: 1 | H47: =F47/G47 -> 0 | I47: Crew | J47: Take-over | K47: 0 | L47: 0 | M47: =H47*Q42/45 -> 0 | O47: =H47 -> 0
G48: 1 | H48: =F48/G48 -> 0 | I48: Crew | J48: Take-over | K48: 0 | L48: 0 | M48: =H48 -> 0 | O48: =H48 -> 0
G49: 7.05 | H49: =F49/G49 -> 0 | I49: DOC | J49: Take-over | K49: 0 | L49: 0 | M49: =H49 -> 0 | O49: =H49 -> 0
G50: 1 | H50: =F50/G50 -> 0 | I50: DOC | J50: Take-over | K50: 0 | L50: 0 | M50: =H50 -> 0 | O50: =H50 -> 0
G51: 1 | H51: =F51/G51 -> 0 | I51: DOC | J51: Take-over | K51: 0 | L51: 0 | M51: =H51 -> 0 | O51: =H51 -> 0
G52: 1 | H52: =F52*G52 -> 0 | I52: DOC | J52: Take-over | K52: 0 | L52: 0 | M52: =H52 -> 0 | O52: =H52 -> 0
G53: 1 | H53: =F53/G53 -> 0 | I53: DOC | J53: Take-over | K53: 0 | L53: 0 | M53: =H53*0 -> 0 | O53: =H53 -> 0
G54: 1 | H54: =F54/G54 -> 0 | I54: DOC | J54: Take-over | K54: 0 | L54: 0 | M54: =H54*0 -> 0 | O54: =H54 -> 0
G55: 7.05 | H55: =F55/G55 -> 0 | I55: DOC | J55: Take-over | K55: 0 | L55: 0 | M55: =H55*0 -> 0 | O55: =H55 -> 0
G56: 1 | H56: =F56/G56 -> 0 | I56: DOC | J56: Take-over | K56: 0 | L56: 0 | M56: =H56*0 -> 0 | O56: =H56 -> 0
G57: 1 | H57: =F57/G57 -> 0 | I57: DOC | J57: Take-over | K57: 0 | L57: 0 | M57: =H57 -> 0 | O57: =H57 -> 0
G58: 1 | H58: =F58/G58 -> 0 | I58: DOC | J58: OPEX | K58: 0 | L58: 0 | O58: =H58 -> 0
G59: 1 | H59: =F59/G59 -> 0 | I59: DOC | J59: OPEX | K59: 0 | L59: 0 | O59: =H59 -> 0
G60: 1 | H60: =F60/G60 -> 0 | I60: DOC | J60: OPEX | K60: 0 | L60: 0 | O60: =H60 -> 0
G61: 1 | H61: =F61/G61 -> 0 | I61: DOC | J61: OPEX | K61: 0 | L61: 0 | O61: =H61 -> 0
G62: 1 | H62: =F62/G62 -> 0 | I62: DOC | J62: OPEX | K62: 0 | L62: 0 | O62: =H62 -> 0
G63: 1 | H63: =F63/G63 -> 0 | I63: DOC | J63: Take-over | K63: 0 | L63: 0 | M63: =H63 -> 0 | O63: =H63 -> 0
G64: 1 | H64: =F64/G64 -> 0 | I64: DOC | J64: OPEX | K64: 0 | L64: 0 | M64: 0 | O64: =H64 -> 0
G65: 1 | H65: =F65/G65 -> 0 | I65: DOC | J65: OPEX | K65: 0 | L65: 0 | M65: 0 | O65: =H65 -> 0
G66: 1 | H66: =F66/G66 -> 0 | I66: DOC | J66: OPEX | K66: 0 | L66: 0 | M66: 0 | O66: =H66 -> 0

Sheet Account Code-2版
C2: Ship Management Account Code | G2: Crew Dept Account Code
C3: Account Code | D3: Ship's Account Description | E3: PIC | G3: Account Code | H3: Description
C4: 1000000 | D4: CREW 船员 | G4: 10000001 | H4: Basic Wage | I4: 基本工资
C5: 1000001 | D5: Wages Pay Onboard | E5: Crewing | G5: 10000002 | H5: Leave Pay | I5: 休假工资
C6: 1000002 | D6: Victualling--Budget | E6: Crewing | G6: 10000003 | H6: Leave Pay P.Hols | I6: 法定公休假期工资（Public Holidays）
C7: 10000021 | D7: Victualling--Supplement Record | G7: 10000004 | H7: Fixed Overtime | I7: 固定加班费
C8: 10000022 | D8: Victualling--Inventory Record | G8: 10000005 | H8: Sub-ITF/IBF/CBA | I8: ITF/IBF/ 集体协议补贴（ITF 国际运输工人联合会，CBA 集体谈判协议）
C9: 1000003 | D9: Joining/Repatriation | E9: Crewing | G9: 10000006 | H9: Sub-Owner | I9: 船东补贴
C10: 1000004 | D10: Crewing Manning Agent | E10: Crewing | G10: 10000007 | H10: Seniority/Rejoining Bonus | I10: 工龄 / 返船奖金
C11: 1000005 | D11: Flag, Union Fees, ITF, CBA,SEPF,SSD etc | E11: Crewing | G11: 10000008 | H11: Overlap/Travelling Wages | I11: 交接重叠期 / 旅途工资
C12: 1000006 | D12: Uniform, Working Gears,Medicine,Entertainment etc | E12: Crewing | G12: 10000009 | H12: Others | I12: 其他费用
C13: 1000007 | D13: Crew Welfare, Other Expenses | E13: Crewing | G13: 10000010 | H13: Victualling Fee | I13: 膳食伙食费（船舶伙食）
C14: 1000090 | D14: Crew--Change Oversea:(Owner Account) | E14: Crewing | G14: 10000011 | H14: Overlap Victualling & Sundries | I14: 船员交接重叠期伙食及杂项费
C15: 1000091 | D15: Crew--Non Budget(Owner) | E15: Crewing | G15: 10000012 | H15: Victualling Allowance | I15: 伙食津贴
C16: 1000092 | D16: Crew--Insurance Claim | E16: Crewing | G16: 10000013 | H16: Crew Changes Fee | I16: 船员换班费用
C17: 2000000 | D17: STORES & SUPPLIES 物料与供应品 | E17: PIC | G17: 10000014 | H17: Crew Medical Examination Fee | I17: 船员体检费
C18: 2000001 | D18: Deck Stores-Medical | E18: Technical | G18: 10000015 | H18: Joinning Port Visa Fees etc. | I18: 上船港口签证费等
C19: 2000002 | D19: Deck Stores-Chart and public | E19: Technical | G19: 10000016 | H19: Manning Agent Fee | I19: 船员外派代理费（配员代理费）
C20: 2000003 | D20: Deck Stores-Ropes and Wires | E20: Technical | G20: 10000017 | H20: Flag State/Union/ITF | I20: 船旗国 / 工会 / 国际运输工人联合会相关费用
... C27: 2000010 | D27: Engine Stores-BWTS | E27: Technical | G27: 10000092 | H27: Crew--Non Budget | I27: 船员类非预算费用
C28: 2000011 | D28: Engine stores – others | E28: Technical
C29: 2000012 | D29: Steward Stores | E29: Technical | G29: RQA No. rule
C30: 2000013 | D30: Stores-Other | E30: Technical | G30: Deck | H30: SWYYMMDD+xx(even, onward)
C31: 2000014 | D31: Store-Accruals | E31: Technical/Accounts | G31: Engine | H31: SWYYMMDD+xx(odd,onward)
C32: 2000090 | D32: Store-03rd Part/Charterer Expenses | E32: Technical /03rd Party | G32: wahsin Office | H32: SWYYMMDD+xx(99 downward)
C33: 2000091 | D33: Store-Non Budget(Owner) | E33: Technical /Owner | G33: PO No. rule
C34: 2000092 | D34: Store-Insurance Claim | E34: Technical / Insurance | G34: Deck | H34: YYMMDD+xx(even)
C35: 3000000 | D35: SPARES 备件 | E35: PIC | G35: Engine | H35: YYMMDD+xx(odd)
C36: 3000001 | D36: SPARE DECK-HULL & TANKS | E36: Technical
C37: 3000002 | D37: SPARE-RADIO & NAVIGATION EQUIPMENT | E37: Technical
C38: 3000003 | D38: SPARE-FFE & LSA EQUIPMENT | E38: Technical
C39: 3000004 | D39: SPARE-DECK MACHINERY | E39: Technical
C40: 3000005 | D40: SPARE-CARGO RELATED EQUIPMENT | E40: Technical
C41: 3000006 | D41: SPARE-DECK OTHERS | E41: Technical
C42: 3000007 | D42: SPARE ENGINE-MAIN ENGINE | E42: Technical
C43: 3000008 | D43: SPARE ENGINE-GEN ENGINE | E43: Technical
C44: 3000009 | D44: SPARES-ENGINE-BOILERS | E44: Technical
C45: 3000010 | D45: SPARES-ENGINE-BWTS | E45: Technical
C46: 3000011 | D46: SPARES-ENGINE-Ele | E46: Technical
C47: 3000012 | D47: SPARE ENGINE-OTHER | E47: Technical
... C108: 6000019 | D108: General Services--Non Budget | E108: Techncial / Insurance
C109: 6000020 | D109: Bound Store Supplement | E109: Master | G109: 非预算
C110: 60000201 | D110: Bound Store Inventory Record | E110: Master
C111: 60000202 | D111: Bound Store Cost Record | E111: Master
C112: 7000000 | D112: INSURANCE 保险 | E112: PIC
C113: 7000001 | D113: Hull & Machinery | E113: Insurance
C114: 7000002 | D114: Hull Interest/Increased Value | E114: Insurance
C115: 7000003 | D115: FDD | E115: Insurance
C116: 7000004 | D116: Protection & Indemnity – P & I | E116: Insurance
C117: 7000005 | D117: Freight Interest | E117: Insurance
C118: 7000006 | D118: Delay | E118: Insurance
C119: 7000007 | D119: Loss Of Hire | E119: Insurance
C120: 7000008 | D120: War risk | E120: Insurance
C121: 7000009 | D121: Crew medical cost | E121: Insurance
... C141: 9000005 | D141: Payment O.B.O Shipowner | E141: Technical / Owner
C142: 9900000 | D142: DRYDOCK/SURVEYS 进坞 / 检验 | E142: PIC
C143: 9900001 | D143: Docking Expenses and Shipyard Final Bill | E143: Technical
C144: 9900002 | D144: Docking Owner's Work | E144: Technical
C145: 9900003 | D145: Docking Spares | E145: Technical
C146: 9900004 | D146: Docking Stores | E146: Technical
C147: 9900005 | D147: Docking Paint | E147: Technical
C148: 9900006 | D148: Docking Slop Disposal | E148: Technical
C149: 9900007 | D149: Docking Others | E149: Technical
C150: 9900008 | D150: Docking Supt Cost | E150: Technical
C151: 9900009 | D151: Docking Agency Disbursements | E151: Technical
C152: 9900010 | D152: Docking Class/Survey Fee | E152: Technical
C153: 9900011 | D153: Docking-NON BUDGET(Incl. Deviation, FO, Offhire cost etc) | E153: Technical
... C163: 9999001 | D163: REBATE / DISCOUNT | E163: ALL

Sheet 伙食海关库房管理
B14: MV Pioneer Lady 轮备用金流水账 | H14: Month | I14: 46235 | K14: MV Pioneer Lady 轮本月伙食费收支一览表 | O14: =I14 -> 46235 | Q14: MV Pioneer Lady 轮本月Bound Store 费用 | U14: =O14 -> 46235
B15: 序号 | C15: 摘要 | D15: 现金变动 | E15: 招待品库存 | F15: 伙食库存 | G15: 混合余额 | H15: 余额变动 | I15: 备注 | K15: 序号 | L15: 项目 | N15: 金额（RMB） | O15: 合美元(USD) | Q15: 序号 | R15: 项目 | T15: 金额（RMB） | U15: 合美元(USD)
B16: 0 | C16: 月初余额 | D16: =D41 -> 0 | E16: 0 | F16: 0 | G16: =D16+E16+F16 -> 0 | K16: 1 | L16: 本期收入 | M16: 伙食费 | Q16: 1 | R16: 本期收入 | S16: 购买招待品
B17: 1 | I17: 做费用 | K17: 2 | M17: 客饭费 | Q17: 2 | S17: 船员购买
B18: 2 | I18: 做费用 | K18: 3 | M18: 招待用伙食 | Q18: 3 | S18: 收入合计 | U18: =SUM(U16:U17) -> 0
B19: 3 | I19: 做费用 | K19: 4 | M19: 船员购伙 | Q19: 4 | R19: 本期支出 | S19: 招待-船员 | U19: 0
B20: 4 | I20: 做费用 | K20: 5 | M20: 收入合计 | O20: =SUM(O16:O19) -> 0 | Q20: 5 | S20: 招待-客人 | U20: 0
B21: 5 | I21: 做费用 | K21: 6 | L21: 本期支出 | M21: 购入伙食 | O21: 0 | Q21: 6 | S21: 船员购买 | U21: 0
B22: 6 | I22: 收入 | K22: 7 | M22: 上期库存 | O22: 0 | Q22: 7 | S22: 上期库存 | U22: 0
B23: 7 | I23: 做费用 | K23: 8 | M23: 本期库存 | O23: 0 | Q23: 8 | S23: 本期库存 | U23: 0
B24: 8 | K24: 9
B25: 9 | K25: 10
B26: 10 | K26: 11
B27: 11 | M27: 支出合计 | O27: =O21+O22-O23 -> 0 | Q27: 9 | S27: 支出合计 | U27: =SUM(U19:U23) -> 0
B28: 结账 | C28: 月底余额 | D28: =SUM(D16:D27) -> 0 | E28: =SUM(E16:E27) -> 0 | F28: =SUM(F16:F27) -> 0 | G28: =SUM(G16:G27) -> 0 | H28: =SUM(H17:H27) -> 0 | K28: 结账 | L28: 本月应发放伙食费 | M28: 0 | N28: 0 | O28: =O20-O27 -> 0 | Q28: 结账 | R28: 本月Bound Store平衡 | S28: 0 | T28: 0 | U28: =U18-U27 -> 0
B30: MV Pioneer Lady 轮备用金流水账 | H30: Month | I30: 46204 | K30: MV Pioneer Lady 轮本月伙食费收支一览表 | O30: =I30 -> 46204 | Q30: MV Pioneer Lady 轮本月Bound Store 费用 | U30: =O30 -> 46204
B31: 序号 | C31: 摘要 | D31: 现金变动 | E31: 招待品库存 | F31: 伙食库存 | G31: 混合余额 | H31: 余额变动 | I31: 备注 | K31: 序号 | L31: 项目 | N31: 金额（RMB） | O31: 合美元(USD) | Q31: 序号 | R31: 项目 | T31: 金额（RMB） | U31: 合美元(USD)
B32: 0 | C32: 月初余额 | D32: 0 | E32: 0 | F32: 0 | G32: =D32+E32+F32 -> 0 | H32: 0 | K32: 1 | L32: 本期收入 | M32: 伙食费 | O32: =D20 -> 0 | Q32: 1 | R32: 本期收入 | S32: 购买招待品
B33: 1 | I33: 收入14815 | K33: 2 | M33: 客饭费 | Q33: 2 | S33: 船员购买
B34: 2 | I34: 做费用 | K34: 3 | M34: 招待用伙食 | Q34: 3 | S34: 收入合计 | U34: =SUM(U32:U33) -> 0
B35: 3 | K35: 4 | M35: 船员购伙 | Q35: 4 | R35: 本期支出 | S35: 招待-船员 | U35: 0
B36: 4 | K36: 5 | M36: 收入合计 | O36: =SUM(O32:O35) -> 0 | Q36: 5 | S36: 招待-客人 | U36: 0
B37: 5 | K37: 6 | L37: 本期支出 | M37: 购入伙食 | Q37: 6 | S37: 船员购买 | U37: 0
B38: 6 | K38: 7 | M38: 上期库存 | O38: 0 | Q38: 7 | S38: 上期库存 | U38: 0
B39: 7 | K39: 8 | M39: 本期库存 | O39: 0 | Q39: 8 | S39: 本期库存 | U39: 0
B40: 8 | K40: 9 | M40: 支出合计 | O40: =O37+O38-O39 -> 0 | Q40: 9 | S40: 支出合计 | U40: =SUM(U35:U39) -> 0
B41: 结账 | C41: 月底余额 | D41: =SUM(D32:D40) -> 0 | E41: =SUM(E32:E40) -> 0 | F41: =SUM(F32:F40) -> 0 | G41: =SUM(G32:G40) -> 0 | H41: =SUM(H34:H40) -> 0 | K41: 结账 | L41: 本月应发放伙食费 | M41: 0 | N41: 0 | O41: =O36-O40 -> 0 | Q41: 结账 | R41: 本月Bound Store平衡 | S41: 0 | T41: 0 | U41: =U34-U40 -> 0
